Workbook
Name Crédito: 'Calculadora '!#REF!
Name Crédito: 'Calculadora Cabina Diciembre'!#REF!
Name Crédito: 'Calculadora Cabina Noviembre'!#REF!
Name Crédito: 'Calculadora Cabina Octubre'!#REF!
Name Crédito: 'Calculadora Cabina Septiembre'!#REF!
Name Crédito: 'Calculadora Conec Diciembre'!#REF!
Name Crédito: 'Calculadora Conec Enero'!#REF!
Name Crédito: 'Calculadora Conec Noviembre'!#REF!
Name Crédito: 'Calculadora Conec Octubre'!#REF!
Name Crédito: 'Calculadora Conec Septiembre'!#REF!
Name Crédito: 'Calculadora Corp Diciembre'!#REF!
Name Crédito: 'Calculadora Corp Enero'!#REF!
Name Crédito: 'Calculadora Corp Noviembre'!#REF!
Name Crédito: 'Calculadora Corp Octubre'!#REF!
Name Crédito: 'Calculadora Corp Septiembre'!#REF!
Name Crédito: 'Calculadora INC Abril'!#REF!
Name Crédito: 'Calculadora INC Agosto'!#REF!
Name Crédito: 'Calculadora INC Julio'!#REF!
Name Crédito: 'Calculadora INC Junio'!#REF!
Name Crédito: 'Calculadora INC Marzo'!#REF!
Name Crédito: 'Calculadora INC Mayo'!#REF!
Name Crédito: 'Calculadora MCS Abril'!#REF!
Name Crédito: 'Calculadora MCS Agosto'!#REF!
Name Crédito: 'Calculadora MCS Febrero'!#REF!
Name Crédito: 'Calculadora MCS Julio'!#REF!
Name Crédito: 'Calculadora MCS Junio'!#REF!
Name Crédito: 'Calculadora MCS Marzo'!#REF!
Name Crédito: 'Calculadora MCS Mayo'!#REF!
Name Crédito: 'Calculadora INC Febrero'!#REF!
Name Descuento_adicional: 'Calculadora '!$F$18
Name Descuento_adicional: 'Calculadora Cabina Diciembre'!$F$17
Name Descuento_adicional: 'Calculadora Cabina Noviembre'!$F$17
Name Descuento_adicional: 'Calculadora Cabina Octubre'!$F$17
Name Descuento_adicional: 'Calculadora Cabina Septiembre'!$F$17
Name Descuento_adicional: 'Calculadora Conec Diciembre'!$F$15
Name Descuento_adicional: 'Calculadora Conec Enero'!$F$15
Name Descuento_adicional: 'Calculadora Conec Noviembre'!$F$15
Name Descuento_adicional: 'Calculadora Conec Octubre'!$F$14
Name Descuento_adicional: 'Calculadora Conec Septiembre'!$F$14
Name Descuento_adicional: 'Calculadora Corp Diciembre'!$F$22
Name Descuento_adicional: 'Calculadora Corp Enero'!$F$21
Name Descuento_adicional: 'Calculadora Corp Noviembre'!$F$22
Name Descuento_adicional: 'Calculadora Corp Octubre'!$F$21
Name Descuento_adicional: 'Calculadora Corp Septiembre'!$F$21
Name Descuento_adicional: 'Calculadora INC Abril'!$F$24
Name Descuento_adicional: 'Calculadora INC Agosto'!$F$24
Name Descuento_adicional: 'Calculadora INC Julio'!$F$24
Name Descuento_adicional: 'Calculadora INC Junio'!$F$24
Name Descuento_adicional: 'Calculadora INC Marzo'!$F$24
Name Descuento_adicional: 'Calculadora INC Mayo'!$F$24
Name Descuento_adicional: 'Calculadora MCS Abril'!$F$22
Name Descuento_adicional: 'Calculadora MCS Agosto'!$F$24
Name Descuento_adicional: 'Calculadora MCS Febrero'!$F$22
Name Descuento_adicional: 'Calculadora MCS Julio'!$F$24
Name Descuento_adicional: 'Calculadora MCS Junio'!$F$24
Name Descuento_adicional: 'Calculadora MCS Marzo'!$F$22
Name Descuento_adicional: 'Calculadora MCS Mayo'!$F$24
Name Descuento_adicional: 'Calculadora INC Febrero'!$F$24
Name Importe: '[1]Propuesta 2'!$C1*'[1]Propuesta 2'!$E1-IF('[1]Propuesta 2'!$C1*'[1]Propuesta 2'!$E1>ImporteParaElDescuento,1,0)*'[1]Propuesta 2'!$C1*'[1]Propuesta 2'!$E1*PorcentajeDeDescuento
Name ImporteParaElDescuento: '[1]Propuesta 2'!#REF!

Sheet Calculadora Conec Enero
C3: Addiuva Enterprises Ayuda sin fronteras
F6: Fecha: | G6: =TODAY() -> 45974
C11: Item | D11: Concepto | E11: Cantidad | F11: Subtotal | G11: Total
C12: 1 | D12: MPLS | E12: 1 | F12: 3539 | G12: =+Table_216181721242730[[#This Row],[Cantidad]]*Table_216181721242730[[#This Row],[Subtotal]] -> 3539 | I12: **Detalle: Tener en cuenta que este concepto se incluyo en la cabina de Colombia
C13: 2 | D13: Conectividad | E13: 1 | F13: -50 | G13: =+Table_216181721242730[[#This Row],[Cantidad]]*Table_216181721242730[[#This Row],[Subtotal]] -> -50 | I13: **Pendiente incluir este detalle, no tenemos todavia facturas**
F14: Subtotal | G14: =+G13 -> -50
F16: ='Calculadora Conec Enero'!Saldo_pendiente -> #REF!

Sheet Calculadora Corp Enero
C3: Addiuva Enterprises Ayuda sin fronteras
F6: Fecha: | G6: =TODAY() -> 45974
C11: Item | D11: Concepto | E11: Cantidad | F11: Subtotal | G11: Total
C12: 1 | D12: Fee Corporativo | E12: 2 | F12: 3150 | G12: =+Table_2161820232629[[#This Row],[Cantidad]]*Table_2161820232629[[#This Row],[Subtotal]] -> 6300
C13: 2 | D13: Gmail | E13: 47 | F13: 12.5 | G13: =+Table_2161820232629[[#This Row],[Cantidad]]*Table_2161820232629[[#This Row],[Subtotal]] -> 587.5
C14: 3 | D14: Odoo | E14: 7 | F14: 1500 | G14: =+Table_2161820232629[[#This Row],[Cantidad]]*Table_2161820232629[[#This Row],[Subtotal]] -> 10500
C15: 4 | D15: Biblioteca SAP | E15: 1 | F15: 500 | G15: =+Table_2161820232629[[#This Row],[Cantidad]]*Table_2161820232629[[#This Row],[Subtotal]] -> 500
C16: 5 | D16: Strategic management | E16: 1 | F16: 105 | G16: =+Table_2161820232629[[#This Row],[Cantidad]]*Table_2161820232629[[#This Row],[Subtotal]] -> 105 | J16: CONCEPTOS CORP | K16: =+G20 -> 42040
C17: 6 | D17: Factorial | E17: 1 | F17: 87.5 | G17: =+Table_2161820232629[[#This Row],[Cantidad]]*Table_2161820232629[[#This Row],[Subtotal]] -> 87.5 | J17: DESCUENTOS | K17: 35520.09 | L17: Confirmado
C18: 7 | D18: Estrategia Tributaria | E18: 1 | F18: 350 | G18: =+Table_2161820232629[[#This Row],[Cantidad]]*Table_2161820232629[[#This Row],[Subtotal]] -> 350 | K18: =+K16-K17 -> 6519.91
C19: 8 | D19: Contabilidad - Filial PR | E19: 1 | F19: 23610 | G19: =+Table_2161820232629[[#This Row],[Cantidad]]*Table_2161820232629[[#This Row],[Subtotal]] -> 23610
F20: Subtotal | G20: =SUBTOTAL(109,G12:G19) -> 42040
F22: ='Calculadora Corp Enero'!Saldo_pendiente -> #REF!

Sheet Calculadora 
C3: Addiuva Enterprises Ayuda sin fronteras
F6: Fecha: | G6: =TODAY() -> 45974
C11: Item | D11: Concepto | E11: Cantidad | F11: Subtotal | G11: Total | H11: Cabina Mes Anterior | I11: Variación | J11: %Variación
C12: 1 | D12: Cabina INC | E12: 1 | F12: =+'Servicios de Cabina INC'!U61-3434 -> 48656.268 | G12: =+Table_21619222528[[#This Row],[Subtotal]] -> 48656.268 | H12: 46370.245 | I12: =Table_21619222528[[#This Row],[Subtotal]]-Table_21619222528[[#This Row],[Cabina Mes Anterior]] -> 2286.0223 | J12: =+Table_21619222528[[#This Row],[Variación]]/Table_21619222528[[#This Row],[Total]] -> 0.046983101
C13: 2 | D13: Cabina Smart | E13: 1 | F13: =+'Servicios de Cabina MCS'!U61-3434 -> 209984.67 | G13: =+Table_21619222528[[#This Row],[Subtotal]] -> 209984.67 | H13: 200549.2 | I13: =Table_21619222528[[#This Row],[Subtotal]]-Table_21619222528[[#This Row],[Cabina Mes Anterior]] -> 9435.4653 | J13: =+Table_21619222528[[#This Row],[Variación]]/Table_21619222528[[#This Row],[Total]] -> 0.044934068
C14: 3 | D14: Calidad | E14: 1 | F14: 500 | G14: =+Table_21619222528[[#This Row],[Cantidad]]*Table_21619222528[[#This Row],[Subtotal]] -> 500
C15: 4 | D15: Conectividad | E15: 1 | G15: =+Table_21619222528[[#This Row],[Cantidad]]*Table_21619222528[[#This Row],[Subtotal]] -> 0 | L15: Pendiente
C16: 5 | D16: Descuentos Corporativos | E16: 1 | F16: =-(2252+187.5+3088.95+3679.38) -> -9207.83 | G16: =+Table_21619222528[[#This Row],[Cantidad]]*Table_21619222528[[#This Row],[Subtotal]] -> -9207.83
F17: Subtotal | G17: =SUBTOTAL(109,G12:G16) -> 249933.1
H21: Valores a Facturar
E22: Colombia | F22: 0.668 | G22: =+(G12+G13)*F22 -> 172772.14 | H22: =+G22+G14+G15+G16 -> 164064.31 | I22: Se incluye CALIDAD, CONECTIVIDAD Y DESCUENTOS en Colombia
E23: Guatemala | F23: 0.332 | G23: =+(G12+G13)*F23 -> 85868.79 | H23: =+G23 -> 85868.79
H24: =+H22+H23-G17 -> 0

Sheet Calculadora Conec Diciembre
C3: Addiuva Enterprises Ayuda sin fronteras
F6: Fecha: | G6: =TODAY() -> 45974
C11: Item | D11: Concepto | E11: Cantidad | F11: Subtotal | G11: Total
C12: 1 | D12: MPLS | E12: 1 | F12: 3539 | G12: =+Table_2161817212427[[#This Row],[Cantidad]]*Table_2161817212427[[#This Row],[Subtotal]] -> 3539 | I12: **Detalle: Tener en cuenta que este concepto se incluyo en la cabina de Colombia
C13: 2 | D13: Conectividad | E13: 1 | F13: =1858.94-48.08 -> 1810.86 | G13: =+Table_2161817212427[[#This Row],[Cantidad]]*Table_2161817212427[[#This Row],[Subtotal]] -> 1810.86
F14: Subtotal | G14: =+G13 -> 1810.86
F16: ='Calculadora Conec Diciembre'!Saldo_pendiente -> #REF!

Sheet Calculadora Corp Diciembre
C3: Addiuva Enterprises Ayuda sin fronteras
F6: Fecha: | G6: =TODAY() -> 45974
C11: Item | D11: Concepto | E11: Cantidad | F11: Subtotal | G11: Total
C12: 1 | D12: Fee Corporativo | E12: 2 | F12: 3150 | G12: =+Table_21618202326[[#This Row],[Cantidad]]*Table_21618202326[[#This Row],[Subtotal]] -> 6300
C13: 2 | D13: Gmail | E13: 47 | F13: 12.5 | G13: =+Table_21618202326[[#This Row],[Cantidad]]*Table_21618202326[[#This Row],[Subtotal]] -> 587.5
C14: 3 | D14: Odoo | E14: 7 | F14: 1500 | G14: =+Table_21618202326[[#This Row],[Cantidad]]*Table_21618202326[[#This Row],[Subtotal]] -> 10500
C15: 4 | D15: Biblioteca SAP | E15: 1 | F15: 500 | G15: =+Table_21618202326[[#This Row],[Cantidad]]*Table_21618202326[[#This Row],[Subtotal]] -> 500
C16: 5 | D16: Strategic management | E16: 1 | F16: 105 | G16: =+Table_21618202326[[#This Row],[Cantidad]]*Table_21618202326[[#This Row],[Subtotal]] -> 105 | J16: CONCEPTOS CORP | K16: =+G21 -> 42088.08
C17: 6 | D17: Factorial | E17: 1 | F17: 87.5 | G17: =+Table_21618202326[[#This Row],[Cantidad]]*Table_21618202326[[#This Row],[Subtotal]] -> 87.5 | J17: DESCUENTOS | K17: 34771.22
C18: 7 | D18: Estrategia Tributaria | E18: 1 | F18: 350 | G18: =+Table_21618202326[[#This Row],[Cantidad]]*Table_21618202326[[#This Row],[Subtotal]] -> 350 | K18: =+K16-K17 -> 7316.86
C19: 8 | D19: Contabilidad - Filial PR | E19: 1 | F19: 23610 | G19: =+Table_21618202326[[#This Row],[Cantidad]]*Table_21618202326[[#This Row],[Subtotal]] -> 23610
C20: 9 | D20: Licencias | E20: 1 | F20: 48.08 | G20: =+Table_21618202326[[#This Row],[Cantidad]]*Table_21618202326[[#This Row],[Subtotal]] -> 48.08
F21: Subtotal | G21: =SUBTOTAL(109,G12:G20) -> 42088.08
F23: ='Calculadora Corp Diciembre'!Saldo_pendiente -> #REF!
M29: pagado x Carmen | N29: 24765
M30: 0.64 | N30: =+$N$29*M30 -> 15849.6 | O30: voccare
M31: 0.3 | N31: =+$N$29*M31 -> 7429.5 | O31: addiuva
M32: 0.06 | N32: =+$N$29*M32 -> 1485.9 | O32: ikatech

Sheet Calculadora Cabina Diciembre
C3: Addiuva Enterprises Ayuda sin fronteras
F6: Fecha: | G6: =TODAY() -> 45974
C11: Item | D11: Concepto | E11: Cantidad | F11: Subtotal | G11: Total | H11: Cabina Mes Anterior | I11: Variación | J11: %Variación
C12: 1 | D12: Cabina INC | E12: 1 | F12: =+'Servicios de Cabina INC'!V61-3150 -> -3150 | G12: =+'Calculadora Cabina Diciembre'!$F12 -> -3150 | H12: =+Table_2161922[[#This Row],[Total]] -> 48940.268 | I12: =+Table_216192225[[#This Row],[Subtotal]]-Table_216192225[[#This Row],[Cabina Mes Anterior]] -> -52090.268 | J12: =+Table_216192225[[#This Row],[Variación]]/Table_216192225[[#This Row],[Total]] -> 16.536593
C13: 2 | D13: Calidad INC | E13: 1 | F13: 500 | G13: ='Calculadora Cabina Diciembre'!$E13*'Calculadora Cabina Diciembre'!$F13 -> 500 | H13: 500 | I13: =+Table_216192225[[#This Row],[Total]]-Table_216192225[[#This Row],[Cabina Mes Anterior]] -> 0 | J13: =+Table_216192225[[#This Row],[Variación]]/Table_216192225[[#This Row],[Total]] -> 0
C14: 4 | D14: Cabina Smart | E14: 1 | F14: =+'Servicios de Cabina MCS'!V61-3150 -> -3150 | G14: 170796.87 | H14: =+Table_2161922[[#This Row],[Total]] -> 210268.67 | I14: =+Table_216192225[[#This Row],[Subtotal]]-Table_216192225[[#This Row],[Cabina Mes Anterior]] -> -213418.67 | J14: =+Table_216192225[[#This Row],[Variación]]/Table_216192225[[#This Row],[Total]] -> -1.2495467
F16: Subtotal | G16: =SUBTOTAL(109,G12:G14) -> 168146.87
F18: ='Calculadora Cabina Diciembre'!Saldo_pendiente -> #REF!
E20: Colombia | F20: 0.71 | G20: =+G16*F20 -> 119384.28 | H20: =+G20+3539 -> 122923.28 | I20: Incluye el MPLS por 3.539 - Conectividad
E21: Guatemala | F21: 0.29 | G21: =+G16*F21 -> 48762.593 | H21: =+G21 -> 48762.593

Sheet Calculadora Conec Noviembre
C3: Addiuva Enterprises Ayuda sin fronteras
F6: Fecha: | G6: =TODAY() -> 45974
C11: Item | D11: Concepto | E11: Cantidad | F11: Subtotal | G11: Total
C12: 1 | D12: MPLS | E12: 1 | F12: 3539 | G12: =+Table_21618172124[[#This Row],[Cantidad]]*Table_21618172124[[#This Row],[Subtotal]] -> 3539 | I12: **Detalle: Tener en cuenta que este concepto se incluyo en la cabina de Colombia
C13: 2 | D13: Conectividad | E13: 1 | F13: 10616 | G13: =+Table_21618172124[[#This Row],[Cantidad]]*Table_21618172124[[#This Row],[Subtotal]] -> 10616
F14: Subtotal | G14: =SUBTOTAL(109,G12:G13) -> 14155
F16: ='Calculadora Conec Noviembre'!Saldo_pendiente -> #REF!
D18: ** Pendiente facturar el concepto de Conectividad de Maplink y Alo Global de julio, agosto, septiembre**

Sheet Calculadora Corp Noviembre
C3: Addiuva Enterprises Ayuda sin fronteras
F6: Fecha: | G6: =TODAY() -> 45974
C11: Item | D11: Concepto | E11: Cantidad | F11: Subtotal | G11: Total
C12: 1 | D12: Fee Corporativo | E12: 2 | F12: 3150 | G12: =+Table_216182023[[#This Row],[Cantidad]]*Table_216182023[[#This Row],[Subtotal]] -> 6300
C13: 2 | D13: Gmail | E13: 47 | F13: 12.5 | G13: =+Table_216182023[[#This Row],[Cantidad]]*Table_216182023[[#This Row],[Subtotal]] -> 587.5
C14: 3 | D14: Odoo | E14: 7 | F14: 1500 | G14: =+Table_216182023[[#This Row],[Cantidad]]*Table_216182023[[#This Row],[Subtotal]] -> 10500
C15: 4 | D15: Biblioteca SAP | E15: 1 | F15: 500 | G15: =+Table_216182023[[#This Row],[Cantidad]]*Table_216182023[[#This Row],[Subtotal]] -> 500
C16: 5 | D16: Strategic management | E16: 1 | F16: 105 | G16: =+Table_216182023[[#This Row],[Cantidad]]*Table_216182023[[#This Row],[Subtotal]] -> 105 | J16: CONCEPTOS CORP | K16: =+G21 -> 42561
C17: 6 | D17: Factorial | E17: 1 | F17: 87.5 | G17: =+Table_216182023[[#This Row],[Cantidad]]*Table_216182023[[#This Row],[Subtotal]] -> 87.5 | J17: DESCUENTOS | K17: 34771.22
C18: 7 | D18: Estrategia Tributaria | E18: 1 | F18: 350 | G18: =+Table_216182023[[#This Row],[Cantidad]]*Table_216182023[[#This Row],[Subtotal]] -> 350 | K18: =+K16-K17 -> 7789.78
C19: 8 | D19: Contabilidad - Filial PR | E19: 1 | F19: 23610 | G19: =+Table_216182023[[#This Row],[Cantidad]]*Table_216182023[[#This Row],[Subtotal]] -> 23610
C20: 9 | D20: Licencias | E20: 1 | F20: 521 | G20: =+Table_216182023[[#This Row],[Cantidad]]*Table_216182023[[#This Row],[Subtotal]] -> 521
F21: Subtotal | G21: =SUBTOTAL(109,G12:G20) -> 42561
F23: ='Calculadora Corp Noviembre'!Saldo_pendiente -> #REF!
D25: ** Pendiente facturar el concepto de Conectividad de Octubre**

Sheet Calculadora Cabina Noviembre
C3: Addiuva Enterprises Ayuda sin fronteras
F6: Fecha: | G6: =TODAY() -> 45974
C11: Item | D11: Concepto | E11: Cantidad | F11: Subtotal | G11: Total | H11: Cabina Mes Anterior | I11: Variación | J11: %Variación
C12: 1 | D12: Cabina INC | E12: 1 | F12: =+'Servicios de Cabina INC'!U61-3150 -> 48940.268 | G12: =+'Calculadora Cabina Noviembre'!$F12 -> 48940.268 | H12: =+Table_21619[[#This Row],[Total]] -> 46654.245 | I12: =+Table_2161922[[#This Row],[Subtotal]]-Table_2161922[[#This Row],[Cabina Mes Anterior]] -> 2286.0223 | J12: =+Table_2161922[[#This Row],[Variación]]/Table_2161922[[#This Row],[Total]] -> 0.046710458
C13: 2 | D13: Calidad INC | E13: 1 | F13: 500 | G13: ='Calculadora Cabina Noviembre'!$E13*'Calculadora Cabina Noviembre'!$F13 -> 500 | H13: 500 | I13: =+Table_2161922[[#This Row],[Total]]-Table_2161922[[#This Row],[Cabina Mes Anterior]] -> 0 | J13: =+Table_2161922[[#This Row],[Variación]]/Table_2161922[[#This Row],[Total]] -> 0
C14: 4 | D14: Cabina Smart | E14: 1 | F14: =+'Servicios de Cabina MCS'!U61-3150 -> 210268.67 | G14: =+Table_2161922[[#This Row],[Subtotal]] -> 210268.67 | H14: =+Table_21619[[#This Row],[Total]] -> 162617.43 | I14: =+Table_2161922[[#This Row],[Subtotal]]-Table_2161922[[#This Row],[Cabina Mes Anterior]] -> 47651.234 | J14: =+Table_2161922[[#This Row],[Variación]]/Table_2161922[[#This Row],[Total]] -> 0.22662071
F16: Subtotal | G16: =SUBTOTAL(109,G12:G14) -> 259708.93
F18: ='Calculadora Cabina Noviembre'!Saldo_pendiente -> #REF!
E20: Colombia | F20: 0.71 | G20: =+G16*F20 -> 184393.34 | H20: =+G20+3539 -> 187932.34 | I20: Incluye el MPLS por 3.539 - Conectividad
E21: Guatemala | F21: 0.29 | G21: =+G16*F21 -> 75315.591 | H21: =+G21 -> 75315.591

Sheet Calculadora Conec Octubre
C3: Addiuva Enterprises Ayuda sin fronteras
F6: Fecha: | G6: =TODAY() -> 45974
C11: Item | D11: Concepto | E11: Cantidad | F11: Subtotal | G11: Total
C12: 1 | D12: MPLS | E12: 1 | F12: 3539 | G12: =+Table_216181721[[#This Row],[Cantidad]]*Table_216181721[[#This Row],[Subtotal]] -> 3539 | I12: **Detalle: Tener en cuenta que este concepto se incluyo en la cabina de Colombia
F13: Subtotal | G13: =SUBTOTAL(109,G12:G12) -> 3539
F15: ='Calculadora Conec Octubre'!Saldo_pendiente -> #REF!
D17: ** Pendiente facturar el concepto de Conectividad de Maplink y Alo Global de julio, agosto, septiembre**

Sheet Calculadora Corp Octubre
C3: Addiuva Enterprises Ayuda sin fronteras
F6: Fecha: | G6: =TODAY() -> 45974
C11: Item | D11: Concepto | E11: Cantidad | F11: Subtotal | G11: Total
C12: 1 | D12: Fee Corporativo | E12: 2 | F12: 3150 | G12: =+Table_2161820[[#This Row],[Cantidad]]*Table_2161820[[#This Row],[Subtotal]] -> 6300
C13: 2 | D13: Gmail | E13: 47 | F13: 12.5 | G13: =+Table_2161820[[#This Row],[Cantidad]]*Table_2161820[[#This Row],[Subtotal]] -> 587.5 | J13: DETALLE CONTABILIDAD
C14: 3 | D14: Odoo | E14: 7 | F14: 1500 | G14: =+Table_2161820[[#This Row],[Cantidad]]*Table_2161820[[#This Row],[Subtotal]] -> 10500 | J14: Nomina PR | K14: 23610
C15: 4 | D15: Biblioteca SAP | E15: 1 | F15: 500 | G15: =+Table_2161820[[#This Row],[Cantidad]]*Table_2161820[[#This Row],[Subtotal]] -> 500 | J15: Vacaciones Diana B | K15: =1750000/4100 -> 426.82927
C16: 5 | D16: Strategic management | E16: 1 | F16: 105 | G16: =+Table_2161820[[#This Row],[Cantidad]]*Table_2161820[[#This Row],[Subtotal]] -> 105 | J16: Audifonos | K16: =150000/4100 -> 36.585366
C17: 6 | D17: Factorial | E17: 1 | F17: 87.5 | G17: =+Table_2161820[[#This Row],[Cantidad]]*Table_2161820[[#This Row],[Subtotal]] -> 87.5 | J17: Papeleria | K17: =538200/4100 -> 131.26829
C18: 7 | D18: Estrategia Tributaria | E18: 1 | F18: 350 | G18: =+Table_2161820[[#This Row],[Cantidad]]*Table_2161820[[#This Row],[Subtotal]] -> 350 | J18: Vacaciones Lina | K18: =303333/4100 -> 73.983659
C19: 8 | D19: Contabilidad - Filial PR | E19: 1 | F19: =23610+1450-614 -> 24446 | G19: =+Table_2161820[[#This Row],[Cantidad]]*Table_2161820[[#This Row],[Subtotal]] -> 24446 | J19: Premios MCS | K19: =687000/4100 -> 167.56098
F20: Subtotal | G20: =SUBTOTAL(109,G12:G19) -> 42876 | J20: Total | K20: =SUM(K14:K19) -> 24446.228
F22: ='Calculadora Corp Octubre'!Saldo_pendiente -> #REF!
D24: ** Pendiente facturar el concepto de Conectividad de Maplink y Alo Global de julio, agosto, septiembre**

Sheet Calculadora Cabina Octubre
C3: Addiuva Enterprises Ayuda sin fronteras
F6: Fecha: | G6: =TODAY() -> 45974
C11: Item | D11: Concepto | E11: Cantidad | F11: Subtotal | G11: Total | H11: Cabina Mes Anterior | I11: Variación | J11: %Variación
C12: 1 | D12: Cabina INC | E12: 1 | F12: =+'Servicios de Cabina INC'!T61-3150 -> 46654.245 | G12: =+'Calculadora Cabina Octubre'!$F12 -> 46654.245 | H12: 42042.878 | I12: =+Table_21619[[#This Row],[Subtotal]]-Table_21619[[#This Row],[Cabina Mes Anterior]] -> 4611.367 | J12: =+Table_21619[[#This Row],[Variación]]/Table_21619[[#This Row],[Total]] -> 0.098841317
C13: 2 | D13: Calidad INC | E13: 1 | F13: 500 | G13: ='Calculadora Cabina Octubre'!$E13*'Calculadora Cabina Octubre'!$F13 -> 500 | H13: 500 | I13: =+Table_21619[[#This Row],[Total]]-Table_21619[[#This Row],[Cabina Mes Anterior]] -> 0 | J13: =+Table_21619[[#This Row],[Variación]]/Table_21619[[#This Row],[Total]] -> 0
C14: 4 | D14: Cabina Smart | E14: 1 | F14: =+'Servicios de Cabina MCS'!T61-3150 -> 200833.2 | G14: 162617.43 | H14: =+'Calculadora MCS Agosto'!G12-3150 -> 184096.57 | I14: =+Table_21619[[#This Row],[Subtotal]]-Table_21619[[#This Row],[Cabina Mes Anterior]] -> 16736.629 | J14: =+Table_21619[[#This Row],[Variación]]/Table_21619[[#This Row],[Total]] -> 0.10292026
F16: Subtotal | G16: =SUBTOTAL(109,G12:G14) -> 209771.68
F18: ='Calculadora Cabina Octubre'!Saldo_pendiente -> #REF!
E20: Colombia | F20: 0.7 | G20: =+G16*F20-3150 -> 143690.17 | H20: =+G20+3539 -> 147229.17 | I20: Incluye el MPLS por 3.539 - Conectividad
E21: Guatemala | F21: 0.3 | G21: =+G16*F21 -> 62931.503

Sheet Calculadora Conec Septiembre
C3: Addiuva Enterprises Ayuda sin fronteras
F6: Fecha: | G6: =TODAY() -> 45974
C11: Item | D11: Concepto | E11: Cantidad | F11: Subtotal | G11: Total
C12: 1 | D12: MPLS | E12: 1 | F12: 3539 | G12: =+Table_2161817[[#This Row],[Cantidad]]*Table_2161817[[#This Row],[Subtotal]] -> 3539 | I12: **Detalle: Tener en cuenta que este concepto se incluyo en la cabina de Colombia
F13: Subtotal | G13: =SUBTOTAL(109,G12:G12) -> 3539
F15: ='Calculadora Conec Septiembre'!Saldo_pendiente -> #REF!
D17: ** Pendiente facturar el concepto de Conectividad de Maplink y Alo Global de julio y agosto**

Sheet Calculadora Corp Septiembre
C3: Addiuva Enterprises Ayuda sin fronteras
F6: Fecha: | G6: =TODAY() -> 45974
C11: Item | D11: Concepto | E11: Cantidad | F11: Subtotal | G11: Total
C12: 1 | D12: Fee Corporativo | E12: 2 | F12: 3150 | G12: =+Table_21618[[#This Row],[Cantidad]]*Table_21618[[#This Row],[Subtotal]] -> 6300
C13: 2 | D13: Gmail | E13: 47 | F13: 12.5 | G13: =+Table_21618[[#This Row],[Cantidad]]*Table_21618[[#This Row],[Subtotal]] -> 587.5
C14: 3 | D14: Odoo | E14: 7 | F14: 1500 | G14: =+Table_21618[[#This Row],[Cantidad]]*Table_21618[[#This Row],[Subtotal]] -> 10500
C15: 4 | D15: Biblioteca SAP | E15: 1 | F15: 500 | G15: =+Table_21618[[#This Row],[Cantidad]]*Table_21618[[#This Row],[Subtotal]] -> 500
C16: 5 | D16: Strategic management | E16: 1 | F16: 105 | G16: =+Table_21618[[#This Row],[Cantidad]]*Table_21618[[#This Row],[Subtotal]] -> 105
C17: 6 | D17: Factorial | E17: 1 | F17: 87.5 | G17: =+Table_21618[[#This Row],[Cantidad]]*Table_21618[[#This Row],[Subtotal]] -> 87.5
C18: 7 | D18: Estrategia Tributaria | E18: 1 | F18: 350 | G18: =+Table_21618[[#This Row],[Cantidad]]*Table_21618[[#This Row],[Subtotal]] -> 350
C19: 8 | D19: Contabilidad - Filial PR | E19: 1 | F19: =23610+1450 -> 25060 | G19: =+Table_21618[[#This Row],[Cantidad]]*Table_21618[[#This Row],[Subtotal]] -> 25060
F20: Subtotal | G20: =SUBTOTAL(109,G12:G19) -> 43490
F22: ='Calculadora Corp Septiembre'!Saldo_pendiente -> #REF!
D24: ** Pendiente facturar el concepto de Conectividad de Maplink y Alo Global de julio y agosto**

Sheet Calculadora Cabina Septiembre
C3: Addiuva Enterprises Ayuda sin fronteras
F6: Fecha: | G6: =TODAY() -> 45974
C11: Item | D11: Concepto | E11: Cantidad | F11: Subtotal | G11: Total | H11: Cabina Mes Anterior | I11: Variación | J11: %Variación
C12: 1 | D12: Cabina INC | E12: 1 | F12: =+'Servicios de Cabina INC'!S61-3150 -> 48079.809 | G12: =+'Calculadora Cabina Septiembre'!$F12 -> 48079.809 | H12: =40773.08287925 -> 40773.083 | I12: =+Table_216[[#This Row],[Subtotal]]-Table_216[[#This Row],[Cabina Mes Anterior]] -> 7306.7263 | J12: =+Table_216[[#This Row],[Variación]]/Table_216[[#This Row],[Total]] -> 0.15197078
C13: 2 | D13: Calidad INC | E13: 1 | F13: 500 | G13: ='Calculadora Cabina Septiembre'!$E13*'Calculadora Cabina Septiembre'!$F13 -> 500 | H13: 500 | I13: =+Table_216[[#This Row],[Total]]-Table_216[[#This Row],[Cabina Mes Anterior]] -> 0 | J13: =+Table_216[[#This Row],[Variación]]/Table_216[[#This Row],[Total]] -> 0
C14: 4 | D14: Cabina Smart | E14: 1 | F14: =+'Servicios de Cabina MCS'!S61-3150 -> 185343.95 | G14: 165767.43 | H14: =+'Calculadora MCS Agosto'!G12-3150 -> 184096.57 | I14: =+Table_216[[#This Row],[Subtotal]]-Table_216[[#This Row],[Cabina Mes Anterior]] -> 1247.3824 | J14: =+Table_216[[#This Row],[Variación]]/Table_216[[#This Row],[Total]] -> 0.0075248945
F16: Subtotal | G16: =SUBTOTAL(109,G12:G14) -> 214347.24
F18: ='Calculadora Cabina Septiembre'!Saldo_pendiente -> #REF!
E20: Colombia | F20: 0.76 | G20: =+G16*F20 -> 162903.9 | H20: =+G20+3539 -> 166442.9 | I20: Incluye el MPLS por 3.539
E21: Guatemala | F21: 0.24 | G21: 49994.474

Sheet Consolidado Agosto
B2: INGRESO | C2: MCS | D2: INC | E2: TOTAL | F2: Cabina Mes Anterior | G2: Cabina Total | I2: COL | J2: GT
B3: CABINA | C3: =+'Calculadora MCS Agosto'!G12-C4 -> 184096.57 | D3: =+'Calculadora INC Agosto'!G12-D4 -> 46456.252 | E3: =SUM(C3:D3) -> 230552.82 | F3: =+'Consolidado Julio'!G3 -> 228463.77 | G3: =+E3 -> 230552.82 | H3: =+E3-6300 -> 224252.82 | I3: =+H3*C37 -> 179402.93 | J3: =+H3*C39 -> 44849.892 | K3: =+G3*80% -> 184442.26 | L3: Colombia
B4: Fee Corporativo | C4: 3150 | D4: 3150 | E4: =SUM(C4:D4) -> 6300 | F4: =+E3-F3 -> 2089.0524 | G4: =+E4 -> 6300 | K4: =+G3*20% -> 46110.565 | L4: Guatemala
B5: Gmail | C5: ='[3]Calculadora MCS Enero-24'!C15 -> 0 | D5: =+'Calculadora INC Agosto'!G13 -> 587.5 | E5: =SUM(C5:D5) -> 587.5 | F5: =+F4/F3 -> 0.0091439111 | G5: =+E5 -> 587.5 | H5: =+E16-E3 -> #REF!
B6: SAP-ODOO | C6: =+'Calculadora MCS Agosto'!G13 -> 6000 | D6: =+'Calculadora INC Agosto'!G14+'Calculadora INC Agosto'!G15 -> 5000 | E6: =SUM(C6:D6) -> 11000 | G6: =+E6 -> 11000
B7: MPLS | D7: =+'Calculadora INC Agosto'!G19 -> 3539 | E7: =SUM(C7:D7) -> 3539 | G7: =+E7 -> 3539 | H7: TASA | I7: 3917 | J7: 7.7
B8: Calidad | D8: =+'Calculadora INC Agosto'!G20 -> 500 | E8: =SUM(C8:D8) -> 500 | G8: =+E8 -> 500 | M8: Ruby*9007
B9: Apoyo Contable | C9: 0 | D9: =+'Calculadora INC Agosto'!G21 -> 23610 | E9: =SUM(C9:D9) -> 23610 | G9: =+E9 -> 23610 | I9: =+I3*I7 -> 7.0272128e+08 | J9: =+J3*J7 -> 345344.17 | M9: Rp*25169007
B10: Strategic management | D10: =+'Calculadora INC Agosto'!G16 -> 105 | E10: =SUM(C10:D10) -> 105 | G10: =+E10 -> 105 | M10: Ruby9007
B11: Factorial | D11: =+'Calculadora INC Agosto'!G17 -> 87.5 | E11: =SUM(C11:D11) -> 87.5 | G11: =+E11 -> 87.5 | M11: Rp*9007
B12: Estrategia Tributaria | D12: =+'Calculadora INC Agosto'!G18 -> 350 | E12: =SUM(C12:D12) -> 350 | G12: =+E12 -> 350
B13: Compras Colombia | C13: =+'[3]Calculadora MCS Enero-24'!C19 -> 0 | D13: =+#REF! -> #REF! | E13: =SUM(C13:D13) -> #REF! | G13: =+E13 -> #REF!
B14: Conectividad Maplink | E14: 929.3224 | G14: =+E14 -> 929.3224
B15: Conectividad Alo Global | E15: 247 | G15: =+E15 -> 247
C16: =SUM(C3:C13) -> 193246.57 | D16: =SUM(D3:D13) -> #REF! | E16: =SUM(E3:E15) -> #REF! | G16: =SUM(G3:G15) -> #REF!
B17: TOTAL INGRESO
B20: DESCUENTOS
B21: Legales | C21: =+'Calculadora MCS Julio'!G14 -> -19243 | E21: =SUM(C21:D21) -> -19243 | F21: Pereira | G21: =E21 -> -19243
B22: Datateck | C22: =+'Calculadora MCS Julio'!G15 -> -2252 | E22: =SUM(C22:D22) -> -2252 | F22: Pereira | G22: =E22 -> -2252
B23: Claro SIP Julio | C23: =+'Calculadora MCS Julio'!G16 -> -187.5 | E23: =SUM(C23:D23) -> -187.5 | F23: Pereira | G23: =E23 -> -187.5
B24: Worldnet lineas tel adicionales | C24: =+'Calculadora MCS Julio'!G17 -> -861.79 | E24: =SUM(C24:D24) -> -861.79 | F24: Pereira | G24: =E24 -> -861.79
B25: Comision PR (transcita) | C25: ='Calculadora MCS Julio'!F19 -> -3679.38 | D25: 0 | E25: =SUM(C25:D25) -> -3679.38 | F25: Pereira | G25: =E25 -> -3679.38 | N25: =+C3+C25 -> 180417.19
B26: Legales Bono GT & LC Cuota 8/12 | C26: =+'Calculadora MCS Julio'!F18 -> -2995.63 | E26: =SUM(C26:D26) -> -2995.63 | F26: Pereira | G26: =E26 -> -2995.63
B27: Almacenamiento de Llamadas | C27: =+'Calculadora MCS Julio'!G20 -> 0 | E27: =SUM(C27:D27) -> 0 | F27: Pereira | G27: =E27 -> 0
B28: Salario Ana Borland | C28: =-#REF! -> #REF! | E28: =SUM(C28:D28) -> #REF! | F28: Pereira | G28: =E28 -> #REF!
B29: Salario Ana Borland Cuota 2/6 | C29: =-#REF!/6 -> #REF! | E29: =SUM(C29:D29) -> #REF! | F29: Pereira | G29: =E29 -> #REF!
B30: Neptuno | C30: =+'Calculadora MCS Julio'!G21 -> -4248.2653 | E30: =SUM(C30:D30) -> -4248.2653 | F30: Pereira | G30: =E30 -> -4248.2653
B31: Amex Ana Borland | C31: =+'Calculadora MCS Agosto'!G22 -> -215.18 | E31: =SUM(C31:D31) -> -215.18 | F31: Pereira | G31: =E31 -> -215.18
C32: =SUM(C21:C31) -> #REF! | D32: =SUM(D21:D30) -> 0 | E32: =SUM(E21:E31) -> #REF! | G32: =SUM(G21:J31) -> #REF!
D36: Total Ingreso | E36: Descuentos | F36: Total Factura
B37: Col | C37: =100%-C39 -> 0.800003 | D37: =+$G$16*C37 -> #REF! | E37: =+G32 -> #REF! | F37: =+D37+E37 -> #REF! | I37: =+D37-H5 -> #REF!
B38: Mex | D38: =+$G$16*C38 -> #REF! | F38: =+D38+E38 -> #REF! | I38: =+I37*I7 -> #REF!
B39: GT | C39: 0.199997 | D39: =+$G$16*C39 -> #REF! | E39: 0 | F39: =+D39+E39 -> #REF!
C41: =C37+C38+C39 -> 1 | D41: =D37+D38+D39 -> #REF! | E41: =E37+E38+E39 -> #REF! | F41: =F37+F38+F39 -> #REF!
B44: Se relizaron 3 facturas por Colombia
B45: Cabina Colombia | D45: =+F37 -> #REF!
B46: Personal MCS 100%
B47: Ajuste llamadas outbound marzo
B48: Ajuste llamadas outbound abril
D49: =SUM(D45:D48) -> #REF!

Sheet Calculadora INC Agosto
C3: Addiuva Enterprises Ayuda sin fronteras
F6: Fecha: | G6: =TODAY() -> 45974
C11: Item | D11: Concepto | E11: Cantidad | F11: Subtotal | G11: Total | H11: Cabina mes anterior
C12: 1 | D12: Cabina | E12: 1 | F12: =+'Servicios de Cabina INC'!R61 -> 49606.252 | G12: ='Calculadora INC Agosto'!$E12*'Calculadora INC Agosto'!$F12 -> 49606.252 | H12: =+'Calculadora INC Julio'!$G12 -> 48826.35
C13: 2 | D13: Gmail | E13: 47 | F13: 12.5 | G13: ='Calculadora INC Agosto'!$E13*'Calculadora INC Agosto'!$F13 -> 587.5 | H13: =+G12-H12 -> 779.90229
C14: 3 | D14: ODOO | E14: 3 | F14: 1500 | G14: ='Calculadora INC Agosto'!$E14*'Calculadora INC Agosto'!$F14 -> 4500 | H14: =+H13/H12 -> 0.01597298
C15: 4 | D15: Biblioteca SAP | E15: 1 | F15: 500 | G15: ='Calculadora INC Agosto'!$E15*'Calculadora INC Agosto'!$F15 -> 500
C16: 5 | D16: Strategic management | E16: 1 | F16: 105 | G16: ='Calculadora INC Agosto'!$E16*'Calculadora INC Agosto'!$F16 -> 105
C17: 6 | D17: Factorial | E17: 1 | F17: 87.5 | G17: ='Calculadora INC Agosto'!$E17*'Calculadora INC Agosto'!$F17 -> 87.5
C18: 7 | D18: Estrategia Tributaria | E18: 1 | F18: 350 | G18: ='Calculadora INC Agosto'!$E18*'Calculadora INC Agosto'!$F18 -> 350
C19: 8 | D19: MPLS | E19: 1 | F19: 3539 | G19: ='Calculadora INC Agosto'!$E19*'Calculadora INC Agosto'!$F19 -> 3539
C20: 9 | D20: Calidad | E20: 1 | F20: 500 | G20: ='Calculadora INC Agosto'!$E20*'Calculadora INC Agosto'!$F20 -> 500
C21: 10 | D21: Apoyo Contable | E21: 1 | F21: 23610 | G21: ='Calculadora INC Agosto'!$E21*'Calculadora INC Agosto'!$F21 -> 23610
C22: 11 | D22: Compras Colombia | E22: 1 | F22: 0 | G22: ='Calculadora INC Agosto'!$E22*'Calculadora INC Agosto'!$F22 -> 0
F23: Subtotal | G23: =SUM(G12:G22) -> 83385.252
F25: ='Calculadora INC Agosto'!Saldo_pendiente -> #REF!

Sheet Calculadora MCS Agosto
C3: Addiuva Enterprises Ayuda sin fronteras
F6: Fecha: | G6: =TODAY() -> 45974
C11: Item | D11: Concepto | E11: Cantidad | F11: Subtotal | G11: Total | H11: Cabina mes anterior
C12: 1 | D12: Cabina | E12: 1 | F12: =+'Servicios de Cabina MCS'!R61 -> 187246.57 | G12: =+'Calculadora MCS Agosto'!$F12 -> 187246.57 | H12: =+'Calculadora MCS Julio'!$G12 -> 204641.15
C13: 2 | D13: ODOO | E13: 4 | F13: 1500 | G13: ='Calculadora MCS Agosto'!$E13*'Calculadora MCS Agosto'!$F13 -> 6000 | H13: =+G12-H12 -> -17394.576
C14: 3 | D14: Legales | E14: 1 | F14: -19243 | G14: ='Calculadora MCS Agosto'!$E14*'Calculadora MCS Agosto'!$F14 -> -19243 | H14: =+H13/H12 -> -0.085000384
C15: 4 | D15: Datateck | E15: 1 | F15: -2252 | G15: ='Calculadora MCS Agosto'!$E15*'Calculadora MCS Agosto'!$F15 -> -2252
C16: 5 | D16: Claro SIP Mayo | E16: 1 | F16: -187.5 | G16: ='Calculadora MCS Agosto'!$E16*'Calculadora MCS Agosto'!$F16 -> -187.5
C17: 6 | D17: Worldnet lineas tel adicionales | E17: 1 | F17: -861.79 | G17: ='Calculadora MCS Agosto'!$E17*'Calculadora MCS Agosto'!$F17 -> -861.79
C18: 7 | D18: Legales Bono GT & LC Cuota 8/12 | E18: 1 | F18: -2995.63 | G18: ='Calculadora MCS Agosto'!$E18*'Calculadora MCS Agosto'!$F18 -> -2995.63
C19: 8 | D19: Comision PR (Transcita) | E19: 1 | F19: -3679.38 | G19: ='Calculadora MCS Agosto'!$E19*'Calculadora MCS Agosto'!$F19 -> -3679.38
C20: 9 | D20: Almacenamiento de Llamadas | E20: 1 | F20: 0 | G20: ='Calculadora MCS Agosto'!$E20*'Calculadora MCS Agosto'!$F20 -> 0
C21: 10 | D21: Neptuno | E21: 1 | F21: -4248.2653 | G21: ='Calculadora MCS Agosto'!$E21*'Calculadora MCS Agosto'!$F21 -> -4248.2653
C22: 11 | D22: Gastos Ana Borland | F22: -215.18 | G22: -215.18
F23: Subtotal | G23: =SUM(G12:G22) -> 159563.83
F25: ='Calculadora MCS Agosto'!Saldo_pendiente -> #REF!

Sheet Consolidado Julio
B2: INGRESO | C2: MCS | D2: INC | E2: TOTAL | F2: Cabina Mes Anterior | G2: Cabina Total | I2: COL | J2: GT
B3: CABINA | C3: =+'Calculadora MCS Julio'!G12-C4 -> 201491.15 | D3: =+'Calculadora INC Julio'!G12-D4 -> 45676.35 | E3: =SUM(C3:D3) -> 247167.5 | F3: =+'Consolidado Junio'!E3 -> 229434.6 | G3: =+'Calculadora MCS Julio'!H12+'Calculadora INC Julio'!F12-G4 -> 228463.77 | H3: =+E3-6300 -> 240867.5 | I3: =+H3*C36 -> 192694 | J3: =+H3*C38 -> 48173.499 | K3: =+G3*C38 -> 45692.754
B4: Fee Corporativo | C4: 3150 | D4: 3150 | E4: =SUM(C4:D4) -> 6300 | F4: =+E3-F3 -> 17732.897 | G4: =+E4 -> 6300
B5: Gmail | C5: ='[3]Calculadora MCS Enero-24'!C15 -> 0 | D5: =+'Calculadora INC Julio'!G13 -> 587.5 | E5: =SUM(C5:D5) -> 587.5 | F5: =+F4/F3 -> 0.077289549 | G5: =+E5 -> 587.5 | H5: =+E16-E3 -> 51894.5
B6: SAP-ODOO | C6: =+'Calculadora MCS Julio'!G13 -> 6000 | D6: =+'Calculadora INC Julio'!G14+'Calculadora INC Julio'!G15 -> 5500 | E6: =SUM(C6:D6) -> 11500 | G6: =+E6 -> 11500
B7: MPLS | C7: #REF! | D7: =+'Calculadora INC Julio'!G19 -> 3539 | E7: =SUM(C7:D7) -> 3539 | G7: =+E7 -> 3539 | H7: TASA | I7: 3917 | J7: 7.7
B8: Calidad | C8: #REF! | D8: =+'Calculadora INC Julio'!G20 -> 500 | E8: =SUM(C8:D8) -> 500 | G8: =+E8 -> 500
B9: Apoyo Contable | C9: 0 | D9: =+'Calculadora INC Julio'!G21 -> 23000 | E9: =SUM(C9:D9) -> 23000 | G9: =+E9 -> 23000 | I9: =+I3*I7 -> 7.5478239e+08 | J9: =+J3*J7 -> 370935.95
B10: Strategic management | D10: =+'Calculadora INC Julio'!G16+105 -> 210 | E10: =SUM(C10:D10) -> 210 | G10: =+E10 -> 210
B11: Factorial | D11: =+'Calculadora INC Julio'!G17+87.5 -> 175 | E11: =SUM(C11:D11) -> 175 | G11: =+E11 -> 175
B12: Estrategia Tributaria | D12: =+'Calculadora INC Julio'!G18+350 -> 700 | E12: =SUM(C12:D12) -> 700 | G12: =+E12 -> 700
B13: Compras Colombia | C13: =+'[3]Calculadora MCS Enero-24'!C19 -> 0 | D13: =+'Calculadora INC Mayo'!G22 -> 0 | E13: =SUM(C13:D13) -> 0 | G13: =+E13 -> 0
B14: Conectividad Maplink | E14: 4459 | G14: =+E14 -> 4459
B15: Conectividad Alo Global | E15: 924 | G15: =+E15 -> 924
C16: =SUM(C3:C13) -> 210641.15 | D16: =SUM(D3:D13) -> 83037.85 | E16: =SUM(E3:E15) -> 299062 | G16: =SUM(G3:G15) -> 280358.27
B17: TOTAL INGRESO
B20: DESCUENTOS
B21: Legales | C21: =+'Calculadora MCS Julio'!G14 -> -19243 | E21: =SUM(C21:D21) -> -19243 | F21: Pereira | G21: =E21 -> -19243
B22: Datateck | C22: =+'Calculadora MCS Julio'!G15 -> -2252 | E22: =SUM(C22:D22) -> -2252 | F22: Pereira | G22: =E22 -> -2252
B23: Claro SIP Julio | C23: =+'Calculadora MCS Julio'!G16 -> -187.5 | E23: =SUM(C23:D23) -> -187.5 | F23: Pereira | G23: =E23 -> -187.5
B24: Worldnet lineas tel adicionales | C24: =+'Calculadora MCS Julio'!G17 -> -861.79 | E24: =SUM(C24:D24) -> -861.79 | F24: Pereira | G24: =E24 -> -861.79
B25: Comision PR (transcita) | C25: ='Calculadora MCS Julio'!F19 -> -3679.38 | D25: 0 | E25: =SUM(C25:D25) -> -3679.38 | F25: Pereira | G25: =E25 -> -3679.38
B26: Legales Bono GT & LC Cuota 7/12 | C26: =+'Calculadora MCS Julio'!F18 -> -2995.63 | E26: =SUM(C26:D26) -> -2995.63 | F26: Pereira | G26: =E26 -> -2995.63
B27: Almacenamiento de Llamadas | C27: =+'Calculadora MCS Julio'!G20 -> 0 | E27: =SUM(C27:D27) -> 0 | F27: Pereira | G27: =E27 -> 0
B28: Salario Ana Borland | C28: =-#REF! -> #REF! | E28: =SUM(C28:D28) -> #REF! | F28: Pereira | G28: =E28 -> #REF!
B29: Salario Ana Borland Cuota 1/6 | C29: =-#REF!/6 -> #REF! | E29: =SUM(C29:D29) -> #REF! | F29: Pereira | G29: =E29 -> #REF!
B30: Neptuno | C30: =+'Calculadora MCS Julio'!G21 -> -4248.2653 | E30: =SUM(C30:D30) -> -4248.2653 | F30: Pereira | G30: =E30 -> -4248.2653
C31: =SUM(C21:C30) -> #REF! | D31: =SUM(D21:D30) -> 0 | E31: =SUM(E21:E30) -> #REF! | G31: =SUM(G21:G30) -> #REF!
D35: Total Ingreso | E35: Descuentos | F35: Total Factura
B36: Col | C36: 0.8 | D36: =+$G$16*C36 -> 224286.62 | E36: =+G31 -> #REF! | F36: =+D36+E36 -> #REF! | I36: =+D36-H5 -> 172392.12
B37: Mex | D37: =+$G$16*C37 -> 0 | F37: =+D37+E37 -> 0 | I37: =+I36*I7 -> 6.7525992e+08
B38: GT | C38: 0.2 | D38: =+$G$16*C38 -> 56071.654 | E38: 0 | F38: =+D38+E38 -> 56071.654
C40: =C36+C37+C38 -> 1 | D40: =D36+D37+D38 -> 280358.27 | E40: =E36+E37+E38 -> #REF! | F40: =F36+F37+F38 -> #REF!
B43: Se realizaron 3 facturas por Colombia
B44: Cabina | D44: =+F36 -> #REF!
B45: Personal MCS 100% | D45: 17051
B46: Ajuste llamadas outbound marzo (factura de abril) | D46: 11238.07
B47: Ajuste llamadas outbound abril (factura de mayo) | D47: 10841.91
D48: =SUM(D44:D47) -> #REF!
B50: Por Guatemala | D50: =+F38 -> 56071.654
D51: =+D50 -> 56071.654
D53: =+D48+D51 -> #REF!

Sheet Calculadora INC Julio
C3: Addiuva Enterprises Ayuda sin fronteras
F6: Fecha: | G6: =TODAY() -> 45974
C11: Item | D11: Concepto | E11: Cantidad | F11: Subtotal | G11: Total | H11: Cabina mes anterior
C12: 1 | D12: Cabina | E12: 1 | F12: =+'Servicios de Cabina INC'!Q61 -> 48826.35 | G12: ='Calculadora INC Julio'!$E12*'Calculadora INC Julio'!$F12 -> 48826.35 | H12: =+'Calculadora INC Junio'!$G12 -> 49797.179
C13: 2 | D13: Gmail | E13: 47 | F13: 12.5 | G13: ='Calculadora INC Julio'!$E13*'Calculadora INC Julio'!$F13 -> 587.5 | H13: =+G12-H12 -> -970.8294
C14: 3 | D14: ODOO | E14: 3 | F14: 1500 | G14: ='Calculadora INC Julio'!$E14*'Calculadora INC Julio'!$F14 -> 4500 | H14: =+H13/H12 -> -0.019495671
C15: 4 | D15: Biblioteca SAP | E15: 1 | F15: 1000 | G15: ='Calculadora INC Julio'!$E15*'Calculadora INC Julio'!$F15 -> 1000
C16: 5 | D16: Strategic management | E16: 1 | F16: 105 | G16: ='Calculadora INC Julio'!$E16*'Calculadora INC Julio'!$F16 -> 105
C17: 6 | D17: Factorial | E17: 1 | F17: 87.5 | G17: ='Calculadora INC Julio'!$E17*'Calculadora INC Julio'!$F17 -> 87.5
C18: 7 | D18: Estrategia Tributaria | E18: 1 | F18: 350 | G18: ='Calculadora INC Julio'!$E18*'Calculadora INC Julio'!$F18 -> 350
C19: 8 | D19: MPLS | E19: 1 | F19: 3539 | G19: ='Calculadora INC Julio'!$E19*'Calculadora INC Julio'!$F19 -> 3539
C20: 9 | D20: Calidad | E20: 1 | F20: 500 | G20: ='Calculadora INC Julio'!$E20*'Calculadora INC Julio'!$F20 -> 500
C21: 10 | D21: Apoyo Contable | E21: 1 | F21: =23000 -> 23000 | G21: ='Calculadora INC Julio'!$E21*'Calculadora INC Julio'!$F21 -> 23000
C22: 11 | D22: Compras Colombia | E22: 1 | F22: 0 | G22: ='Calculadora INC Julio'!$E22*'Calculadora INC Julio'!$F22 -> 0
F23: Subtotal | G23: =SUM(G12:G22) -> 82495.35
F25: ='Calculadora INC Julio'!Saldo_pendiente -> #REF!

Sheet Calculadora MCS Julio
C3: Addiuva Enterprises Ayuda sin fronteras
F6: Fecha: | G6: =TODAY() -> 45974
C11: Item | D11: Concepto | E11: Cantidad | F11: Subtotal | G11: Total | H11: Cabina mes anterior
C12: 1 | D12: Cabina | E12: 1 | F12: =+'Servicios de Cabina MCS'!Q61 -> 204641.15 | G12: =+'Calculadora MCS Julio'!$F12 -> 204641.15 | H12: =+'Calculadora MCS Junio'!$G12 -> 185937.42
C13: 2 | D13: ODOO | E13: 4 | F13: 1500 | G13: ='Calculadora MCS Julio'!$E13*'Calculadora MCS Julio'!$F13 -> 6000 | H13: =+G12-H12 -> 18703.726
C14: 3 | D14: Legales | E14: 1 | F14: -19243 | G14: ='Calculadora MCS Julio'!$E14*'Calculadora MCS Julio'!$F14 -> -19243 | H14: =+H13/H12 -> 0.10059151
C15: 4 | D15: Datateck | E15: 1 | F15: -2252 | G15: ='Calculadora MCS Julio'!$E15*'Calculadora MCS Julio'!$F15 -> -2252
C16: 5 | D16: Claro SIP Mayo | E16: 1 | F16: -187.5 | G16: ='Calculadora MCS Julio'!$E16*'Calculadora MCS Julio'!$F16 -> -187.5
C17: 6 | D17: Worldnet lineas tel adicionales | E17: 1 | F17: -861.79 | G17: ='Calculadora MCS Julio'!$E17*'Calculadora MCS Julio'!$F17 -> -861.79
C18: 7 | D18: Legales Bono GT & LC Cuota 5/12 | E18: 1 | F18: -2995.63 | G18: ='Calculadora MCS Julio'!$E18*'Calculadora MCS Julio'!$F18 -> -2995.63
C19: 8 | D19: Comision PR (Transcita) | E19: 1 | F19: -3679.38 | G19: ='Calculadora MCS Julio'!$E19*'Calculadora MCS Julio'!$F19 -> -3679.38
C20: 9 | D20: Almacenamiento de Llamadas | E20: 1 | F20: 0 | G20: ='Calculadora MCS Julio'!$E20*'Calculadora MCS Julio'!$F20 -> 0
C21: 10 | D21: Neptuno | E21: 1 | F21: -4248.2653 | G21: ='Calculadora MCS Julio'!$E21*'Calculadora MCS Julio'!$F21 -> -4248.2653
F23: Subtotal | G23: =SUM(G12:G22) -> 177173.58
F25: ='Calculadora MCS Julio'!Saldo_pendiente -> #REF!

Sheet Consolidado Junio
B2: INGRESO | C2: MCS | D2: INC | E2: TOTAL | F2: Cabina Mes Anterior | G2: Cabina Total | I2: COL | J2: GT
B3: CABINA | C3: =+'Calculadora MCS Junio'!G12-C4 -> 182787.42 | D3: =+'Calculadora INC Junio'!G12-D4 -> 46647.179 | E3: =SUM(C3:D3) -> 229434.6 | F3: 188304.7 | G3: =+E3 -> 229434.6 | H3: =+E3-6300 -> 223134.6 | I3: =+H3*C34 -> 187433.06 | J3: =+H3*C36 -> 35701.536
B4: Fee Corporativo | C4: 3150 | D4: 3150 | E4: =SUM(C4:D4) -> 6300 | F4: =+E3-F3 -> 41129.899 | G4: =+E4 -> 6300
B5: Gmail | C5: ='[3]Calculadora MCS Enero-24'!C15 -> 0 | D5: =+'Calculadora INC Junio'!G13 -> 587.5 | E5: =SUM(C5:D5) -> 587.5 | F5: =+F4/F3 -> 0.21842205 | G5: =+E5 -> 587.5 | H5: =+E15-E3 -> 44969
B6: SAP-ODOO | C6: =+'Calculadora MCS Junio'!G13 -> 6000 | D6: =+'Calculadora INC Mayo'!G14 -> 4500 | E6: =SUM(C6:D6) -> 10500 | G6: =+E6 -> 10500
B7: MPLS | C7: #REF! | D7: =+'Calculadora INC Junio'!G19 -> 3539 | E7: =SUM(C7:D7) -> 3539 | G7: =+E7 -> 3539 | H7: TASA | I7: 3917 | J7: 7.7
B8: Calidad | C8: #REF! | D8: =+'Calculadora INC Junio'!G20 -> 500 | E8: =SUM(C8:D8) -> 500 | G8: =+E8 -> 500
B9: Apoyo Contable | C9: 0 | D9: =+'Calculadora INC Junio'!G21 -> 23000 | E9: =SUM(C9:D9) -> 23000 | G9: =+E9 -> 23000 | I9: =+I3*I7 -> 7.3417531e+08 | J9: =+J3*J7 -> 274901.83
B10: Strategic management | D10: =+'Calculadora INC Junio'!G16 -> 105 | E10: =SUM(C10:D10) -> 105 | G10: =+E10 -> 105
B11: Factorial | D11: =+'Calculadora INC Junio'!G17 -> 87.5 | E11: =SUM(C11:D11) -> 87.5 | G11: =+E11 -> 87.5
B12: Estrategia Tributaria | D12: =+'Calculadora INC Junio'!G18 -> 350 | E12: =SUM(C12:D12) -> 350 | G12: =+E12 -> 350
B13: Compras Colombia | C13: =+'[3]Calculadora MCS Enero-24'!C19 -> 0 | D13: =+'Calculadora INC Mayo'!G22 -> 0 | E13: =SUM(C13:D13) -> 0 | G13: =+E13 -> 0
C15: =SUM(C3:C13) -> 191937.42 | D15: =SUM(D3:D13) -> 82466.179 | E15: =SUM(E3:E13) -> 274403.6 | G15: =SUM(G3:G14) -> 274403.6
B16: TOTAL INGRESO
B19: DESCUENTOS
B20: Legales | C20: =+'Calculadora MCS Junio'!G14 -> -19243 | E20: =SUM(C20:D20) -> -19243 | F20: Pereira | G20: =E20 -> -19243
B21: Datateck | C21: =+'Calculadora MCS Junio'!G15 -> -2252 | E21: =SUM(C21:D21) -> -2252 | F21: Pereira | G21: =E21 -> -2252
B22: Claro SIP Enero | C22: =+'Calculadora MCS Junio'!G16 -> -187.5 | E22: =SUM(C22:D22) -> -187.5 | F22: Pereira | G22: =E22 -> -187.5
B23: Worldnet lineas tel adicionales | C23: =+'Calculadora MCS Junio'!G17 -> -861.79 | E23: =SUM(C23:D23) -> -861.79 | F23: Pereira | G23: =E23 -> -861.79
B24: Comision PR (transcita) | C24: =+'Calculadora MCS Junio'!G19 -> -3679.38 | D24: 0 | E24: =SUM(C24:D24) -> -3679.38 | F24: Pereira | G24: =E24 -> -3679.38
B25: Legales Bono GT & LC Cuota 6/12 | C25: =+'Calculadora MCS Junio'!G18 -> -2995.63 | E25: =SUM(C25:D25) -> -2995.63 | F25: Pereira | G25: =E25 -> -2995.63
B26: Almacenamiento de Llamadas | C26: 0 | E26: =SUM(C26:D26) -> 0 | F26: Pereira | G26: =E26 -> 0
B27: Salario Ana Borland | C27: =-#REF! -> #REF! | E27: =SUM(C27:D27) -> #REF! | F27: Pereira | G27: =E27 -> #REF!
B28: Neptuno | C28: =-#REF! -> #REF! | E28: =SUM(C28:D28) -> #REF! | F28: Pereira | G28: =E28 -> #REF!
C29: =SUM(C20:C28) -> #REF! | D29: =SUM(D20:D28) -> 0 | E29: =SUM(E20:E28) -> #REF! | G29: =SUM(G20:G28) -> #REF!
D33: Total Ingreso | E33: Descuentos | F33: Total Factura
B34: Col | C34: 0.84 | D34: =+$E$15*C34 -> 230499.02 | E34: =+G29 -> #REF! | F34: =+D34+E34 -> #REF! | I34: =+D34-H5 -> 185530.02
B35: Mex | D35: =+$E$15*C35 -> 0 | F35: =+D35+E35 -> 0 | I35: =+I34*I7 -> 7.267211e+08
B36: GT | C36: 0.16 | D36: =+$E$15*C36 -> 43904.576 | E36: 0 | F36: =+D36+E36 -> 43904.576
C38: =C34+C35+C36 -> 1 | D38: =D34+D35+D36 -> 274403.6 | E38: =E34+E35+E36 -> #REF! | F38: =F34+F35+F36 -> #REF!
B41: Se relizaron 2 facturas por Colombia
B42: Cabina | D42: 167255
B43: Personal MCS 100% | D43: 17051
D44: =+D42+D43 -> 184306

Sheet Calculadora INC Junio
C3: Addiuva Enterprises Ayuda sin fronteras
F6: Fecha: | G6: =TODAY() -> 45974
C11: Item | D11: Concepto | E11: Cantidad | F11: Subtotal | G11: Total | H11: Cabina mes anterior
C12: 1 | D12: Cabina | E12: 1 | F12: =+'Servicios de Cabina INC'!P61 -> 49797.179 | G12: ='Calculadora INC Junio'!$E12*'Calculadora INC Junio'!$F12 -> 49797.179 | H12: =+'Calculadora INC Mayo'!$G12 -> 49104.493
C13: 2 | D13: Gmail | E13: 47 | F13: 12.5 | G13: ='Calculadora INC Junio'!$E13*'Calculadora INC Junio'!$F13 -> 587.5 | H13: =+G12-H12 -> 692.68674
C14: 3 | D14: ODOO | E14: 3 | F14: 1500 | G14: ='Calculadora INC Junio'!$E14*'Calculadora INC Junio'!$F14 -> 4500 | H14: =+H13/H12 -> 0.014106382
C15: 4 | D15: Biblioteca SAP | E15: 1 | F15: 0 | G15: ='Calculadora INC Junio'!$E15*'Calculadora INC Junio'!$F15 -> 0
C16: 5 | D16: Strategic management | E16: 1 | F16: 105 | G16: ='Calculadora INC Junio'!$E16*'Calculadora INC Junio'!$F16 -> 105
C17: 6 | D17: Factorial | E17: 1 | F17: 87.5 | G17: ='Calculadora INC Junio'!$E17*'Calculadora INC Junio'!$F17 -> 87.5
C18: 7 | D18: Estrategia Tributaria | E18: 1 | F18: 350 | G18: ='Calculadora INC Junio'!$E18*'Calculadora INC Junio'!$F18 -> 350
C19: 8 | D19: MPLS | E19: 1 | F19: 3539 | G19: ='Calculadora INC Junio'!$E19*'Calculadora INC Junio'!$F19 -> 3539
C20: 9 | D20: Calidad | E20: 1 | F20: 500 | G20: ='Calculadora INC Junio'!$E20*'Calculadora INC Junio'!$F20 -> 500
C21: 10 | D21: Apoyo Contable | E21: 1 | F21: =23000 -> 23000 | G21: ='Calculadora INC Junio'!$E21*'Calculadora INC Junio'!$F21 -> 23000
C22: 11 | D22: Compras Colombia | E22: 1 | F22: 0 | G22: ='Calculadora INC Junio'!$E22*'Calculadora INC Junio'!$F22 -> 0
F23: Subtotal | G23: =SUM(G12:G22) -> 82466.179
F25: ='Calculadora INC Junio'!Saldo_pendiente -> #REF!

Sheet Calculadora MCS Junio
C3: Addiuva Enterprises Ayuda sin fronteras
F6: Fecha: | G6: =TODAY() -> 45974
C11: Item | D11: Concepto | E11: Cantidad | F11: Subtotal | G11: Total | H11: Cabina mes anterior
C12: 1 | D12: Cabina | E12: 1 | F12: =+'Servicios de Cabina MCS'!P61 -> 185937.42 | G12: =+'Calculadora MCS Junio'!$F12 -> 185937.42 | H12: =+'Calculadora MCS Mayo'!$G12 -> 187848.26
C13: 2 | D13: ODOO | E13: 4 | F13: 1500 | G13: ='Calculadora MCS Junio'!$E13*'Calculadora MCS Junio'!$F13 -> 6000 | H13: =+G12-H12 -> -1910.8434
C14: 3 | D14: Legales | E14: 1 | F14: -19243 | G14: ='Calculadora MCS Junio'!$E14*'Calculadora MCS Junio'!$F14 -> -19243 | H14: =+H13/H12 -> -0.010172271
C15: 4 | D15: Datateck | E15: 1 | F15: -2252 | G15: ='Calculadora MCS Junio'!$E15*'Calculadora MCS Junio'!$F15 -> -2252
C16: 5 | D16: Claro SIP Mayo | E16: 1 | F16: -187.5 | G16: ='Calculadora MCS Junio'!$E16*'Calculadora MCS Junio'!$F16 -> -187.5
C17: 6 | D17: Worldnet lineas tel adicionales | E17: 1 | F17: -861.79 | G17: ='Calculadora MCS Junio'!$E17*'Calculadora MCS Junio'!$F17 -> -861.79
C18: 7 | D18: Legales Bono GT & LC Cuota 5/12 | E18: 1 | F18: -2995.63 | G18: ='Calculadora MCS Junio'!$E18*'Calculadora MCS Junio'!$F18 -> -2995.63
C19: 8 | D19: Comision PR (Transcita) | E19: 1 | F19: -3679.38 | G19: ='Calculadora MCS Junio'!$E19*'Calculadora MCS Junio'!$F19 -> -3679.38
C20: 9 | D20: Almacenamiento de Llamadas | E20: 1 | F20: 0 | G20: ='Calculadora MCS Junio'!$E20*'Calculadora MCS Junio'!$F20 -> 0
C21: 10 | D21: Neptuno | E21: 1 | F21: -4248.2653 | G21: ='Calculadora MCS Junio'!$E21*'Calculadora MCS Junio'!$F21 -> -4248.2653
F23: Subtotal | G23: =SUM(G12:G22) -> 158469.86
F25: ='Calculadora MCS Junio'!Saldo_pendiente -> #REF!

Sheet Consolidado Mayo
B2: INGRESO | C2: MCS | D2: INC | E2: TOTAL | F2: Cabina Mes Anterior | G2: Cabina Total | I2: COL | J2: GT
B3: CABINA | C3: =+'Servicios de Cabina MCS'!O61 -> 187848.26 | D3: =+'Servicios de Cabina INC'!O61 -> 49104.493 | E3: =SUM(C3:D3) -> 236952.76 | F3: =+'Consolidado Abril'!E3 -> 242175.23 | G3: =+E3 -> 236952.76 | H3: =+E3-6300 -> 230652.76 | I3: =+H3*C32 -> 179909.15 | J3: =+H3*C34 -> 50743.607
B4: Gmail | C4: ='[3]Calculadora MCS Enero-24'!C15 -> 0 | D4: =+'Calculadora INC Mayo'!G13 -> 575 | E4: =SUM(C4:D4) -> 575 | F4: =+E3-F3 -> -5222.4765 | G4: =+E4 -> 575 | H4: =+E14-E3 -> 38656.5
B5: SAP-ODOO | C5: =+'Calculadora MCS Mayo'!G13 -> 6000 | D5: =+'Calculadora INC Mayo'!G14 -> 4500 | E5: =SUM(C5:D5) -> 10500 | F5: =+F4/F3 -> -0.021564866 | G5: =+E5 -> 10500
B6: MPLS | C6: #REF! | D6: =+'Calculadora INC Mayo'!G19 -> 3539 | E6: =SUM(C6:D6) -> 3539 | G6: =+E6 -> 3539 | H6: TASA | I6: 3917 | J6: 7.7
B7: Calidad | C7: #REF! | D7: =+'Calculadora INC Mayo'!G20 -> 500 | E7: =SUM(C7:D7) -> 500 | G7: =+E7 -> 500
B8: Apoyo Contable | C8: 0 | D8: =+'Calculadora INC Mayo'!G21 -> 23000 | E8: =SUM(C8:D8) -> 23000 | G8: =+E8 -> 23000 | I8: =+I3*I6 -> 7.0470414e+08 | J8: =+J3*J6 -> 390725.77 | M8: 3384875
B9: Strategic management | D9: =+'Calculadora INC Mayo'!G16 -> 105 | E9: =SUM(C9:D9) -> 105 | G9: =+E9 -> 105 | M9: =M8/#REF! -> #REF!
B10: Factorial | D10: =+'Calculadora INC Mayo'!G17 -> 87.5 | E10: =SUM(C10:D10) -> 87.5 | G10: =+E10 -> 87.5
B11: Estrategia Tributaria | D11: =+'Calculadora INC Mayo'!G18 -> 350 | E11: =SUM(C11:D11) -> 350 | G11: =+E11 -> 350
B12: Compras Colombia | C12: =+'[3]Calculadora MCS Enero-24'!C19 -> 0 | D12: =+'Calculadora INC Mayo'!G22 -> 0 | E12: =SUM(C12:D12) -> 0 | G12: =+E12 -> 0
C14: =SUM(C3:C13) -> 193848.26 | D14: =SUM(D3:D13) -> 81760.993 | E14: =SUM(E3:E13) -> 275609.26 | G14: =E14+F14 -> 275609.26
B15: TOTAL INGRESO
E16: =SUM(E4:E11)+6300 -> 44956.5
E17: 50926.154 | F17: =+E14-E17-E16 -> 179726.6
B18: DESCUENTOS
B19: Legales | C19: =+'Calculadora MCS Abril'!F14 -> -19243 | E19: =SUM(C19:D19) -> -19243 | F19: Pereira | G19: =E19 -> -19243
B20: Datateck | C20: =+'Calculadora MCS Abril'!F15 -> -2252 | E20: =SUM(C20:D20) -> -2252 | F20: Guatemala | G20: =E20 -> -2252
B21: Claro SIP Enero | C21: =+'Calculadora MCS Abril'!F16 -> -187.5 | E21: =SUM(C21:D21) -> -187.5 | F21: Guatemala | G21: =E21 -> -187.5
B22: Worldnet lineas tel adicionales | C22: =+'Calculadora MCS Abril'!F17 -> -861.79 | E22: =SUM(C22:D22) -> -861.79 | F22: Guatemala | G22: =E22 -> -861.79
B23: Comision PR (transcita) | C23: =+'Calculadora MCS Abril'!F19 -> -3679.38 | D23: 0 | E23: =SUM(C23:D23) -> -3679.38 | F23: Pereira | G23: =E23 -> -3679.38
B24: Legales Bono GT & LC Cuota 5/12 | C24: =+'Calculadora MCS Abril'!F18 -> -2995.63 | E24: =SUM(C24:D24) -> -2995.63 | F24: Pereira | G24: =E24 -> -2995.63
B25: Almacenamiento de Llamadas | C25: 0 | E25: =SUM(C25:D25) -> 0 | F25: Guatemala | G25: =E25 -> 0
B26: Neptuno | C26: =-#REF! -> #REF! | E26: =SUM(C26:D26) -> #REF! | F26: Guatemala | G26: =E26 -> #REF!
C27: =SUM(C19:C26) -> #REF! | D27: =SUM(D19:D26) -> 0 | E27: =SUM(E19:E26) -> #REF! | G27: =SUM(G19:G26) -> #REF!
D31: Total Ingreso | E31: Descuentos | F31: Total Factura
B32: Col | C32: 0.78 | D32: =+$E$14*C32 -> 214975.22 | E32: =+G19+G23+G24 -> -25918.01 | F32: =+D32+E32 -> 189057.21 | I32: =+D32-H4 -> 176318.72
B33: Mex | D33: =+$E$14*C33 -> 0 | F33: =+D33+E33 -> 0 | I33: =+I32*I6 -> 6.9064043e+08
B34: GT | C34: 0.22 | D34: =+$E$14*C34 -> 60634.037 | E34: =+G20+G21+G22+G25+G26 -> #REF! | F34: =+D34+E34 -> #REF!
C36: =C32+C33+C34 -> 1 | D36: =D32+D33+D34 -> 275609.26 | E36: =E32+E33+E34 -> #REF! | F36: =F32+F33+F34 -> #REF!

Sheet Calculadora INC Mayo
C3: Addiuva Enterprises Ayuda sin fronteras
F6: Fecha: | G6: =TODAY() -> 45974
C11: Item | D11: Concepto | E11: Cantidad | F11: Subtotal | G11: Total | H11: Cabina mes anterior
C12: 1 | D12: Cabina | E12: 1 | F12: =+'Servicios de Cabina INC'!O61 -> 49104.493 | G12: ='Calculadora INC Mayo'!$E12*'Calculadora INC Mayo'!$F12 -> 49104.493 | H12: =+'Servicios de Cabina INC'!M61 -> 46185.214
C13: 2 | D13: Gmail | E13: 46 | F13: 12.5 | G13: ='Calculadora INC Mayo'!$E13*'Calculadora INC Mayo'!$F13 -> 575 | H13: =+G12-H12 -> 2919.2788
C14: 3 | D14: ODOO | E14: 3 | F14: 1500 | G14: ='Calculadora INC Mayo'!$E14*'Calculadora INC Mayo'!$F14 -> 4500 | H14: =+H13/H12 -> 0.063208081
C15: 4 | D15: Biblioteca SAP | E15: 1 | F15: 0 | G15: ='Calculadora INC Mayo'!$E15*'Calculadora INC Mayo'!$F15 -> 0
C16: 5 | D16: Strategic management | E16: 1 | F16: 105 | G16: ='Calculadora INC Mayo'!$E16*'Calculadora INC Mayo'!$F16 -> 105
C17: 6 | D17: Factorial | E17: 1 | F17: 87.5 | G17: ='Calculadora INC Mayo'!$E17*'Calculadora INC Mayo'!$F17 -> 87.5
C18: 7 | D18: Estrategia Tributaria | E18: 1 | F18: 350 | G18: ='Calculadora INC Mayo'!$E18*'Calculadora INC Mayo'!$F18 -> 350
C19: 8 | D19: MPLS | E19: 1 | F19: 3539 | G19: ='Calculadora INC Mayo'!$E19*'Calculadora INC Mayo'!$F19 -> 3539
C20: 9 | D20: Calidad | E20: 1 | F20: 500 | G20: ='Calculadora INC Mayo'!$E20*'Calculadora INC Mayo'!$F20 -> 500
C21: 10 | D21: Apoyo Contable | E21: 1 | F21: 23000 | G21: ='Calculadora INC Mayo'!$E21*'Calculadora INC Mayo'!$F21 -> 23000
C22: 11 | D22: Compras Colombia | E22: 1 | F22: 0 | G22: ='Calculadora INC Mayo'!$E22*'Calculadora INC Mayo'!$F22 -> 0
F23: Subtotal | G23: =SUM(G12:G22) -> 81760.993
F25: ='Calculadora INC Mayo'!Saldo_pendiente -> #REF!

Sheet Calculadora MCS Mayo
C3: Addiuva Enterprises Ayuda sin fronteras
F6: Fecha: | G6: =TODAY() -> 45974
C11: Item | D11: Concepto | E11: Cantidad | F11: Subtotal | G11: Total | H11: Cabina mes anterior
C12: 1 | D12: Cabina | E12: 1 | F12: =+'Servicios de Cabina MCS'!O61 -> 187848.26 | G12: =+'Calculadora MCS Mayo'!$F12 -> 187848.26 | H12: =+'Calculadora MCS Marzo'!$G12 -> 171366.78
C13: 2 | D13: ODOO | E13: 4 | F13: 1500 | G13: ='Calculadora MCS Mayo'!$E13*'Calculadora MCS Mayo'!$F13 -> 6000 | H13: =+G12-H12 -> 16481.489
C14: 3 | D14: Legales | E14: 1 | F14: -19243 | G14: ='Calculadora MCS Mayo'!$E14*'Calculadora MCS Mayo'!$F14 -> -19243 | H14: =+H13/H12 -> 0.096176688
C15: 4 | D15: Datateck | E15: 1 | F15: -2252 | G15: ='Calculadora MCS Mayo'!$E15*'Calculadora MCS Mayo'!$F15 -> -2252
C16: 5 | D16: Claro SIP Mayo | E16: 1 | F16: -187.5 | G16: ='Calculadora MCS Mayo'!$E16*'Calculadora MCS Mayo'!$F16 -> -187.5
C17: 6 | D17: Worldnet lineas tel adicionales | E17: 1 | F17: -861.79 | G17: ='Calculadora MCS Mayo'!$E17*'Calculadora MCS Mayo'!$F17 -> -861.79
C18: 7 | D18: Legales Bono GT & LC Cuota 5/12 | E18: 1 | F18: -2995.63 | G18: ='Calculadora MCS Mayo'!$E18*'Calculadora MCS Mayo'!$F18 -> -2995.63
C19: 8 | D19: Comision PR (Transcita) | E19: 1 | F19: -3679.38 | G19: ='Calculadora MCS Mayo'!$E19*'Calculadora MCS Mayo'!$F19 -> -3679.38
C20: 9 | D20: Almacenamiento de Llamadas | E20: 1 | F20: 0 | G20: ='Calculadora MCS Mayo'!$E20*'Calculadora MCS Mayo'!$F20 -> 0
C21: 10 | D21: Neptuno | E21: 1 | F21: -4248.2653 | G21: ='Calculadora MCS Mayo'!$E21*'Calculadora MCS Mayo'!$F21 -> -4248.2653
F23: Subtotal | G23: =SUM(G12:G22) -> 160380.7
F25: ='Calculadora MCS Mayo'!Saldo_pendiente -> #REF!

Sheet Consolidado Abril
B2: INGRESO | C2: MCS | D2: INC | E2: TOTAL | F2: Cabina Mes Anterior | G2: Cabina Total
B3: CABINA | C3: =+'Calculadora MCS Abril'!G12 -> 192446.56 | D3: =+'Calculadora INC Abril'!G12 -> 49728.671 | E3: =SUM(C3:D3) -> 242175.23 | F3: =+'Consolidado Marzo'!G3 -> 217551.99 | G3: =+E3 -> 242175.23
B4: Gmail | C4: ='[3]Calculadora MCS Enero-24'!C15 -> 0 | D4: =+'Calculadora INC Abril'!G13 -> 575 | E4: =SUM(C4:D4) -> 575 | F4: =+E3-F3 -> 24623.244 | G4: =+E4 -> 575
B5: SAP-ODOO | C5: =+'Calculadora MCS Abril'!G13 -> 6000 | D5: =+'Calculadora INC Abril'!G14 -> 4500 | E5: =SUM(C5:D5) -> 10500 | F5: =+F4/F3 -> 0.11318326 | G5: =+E5 -> 10500
B6: MPLS | C6: #REF! | D6: =+'Calculadora INC Abril'!G19 -> 3539 | E6: =SUM(C6:D6) -> 3539 | G6: =+E6 -> 3539
B7: Calidad | C7: #REF! | D7: =+'Calculadora INC Abril'!G20 -> 500 | E7: =SUM(C7:D7) -> 500 | G7: =+E7 -> 500
B8: Apoyo Contable | C8: 0 | D8: 23000 | E8: =SUM(C8:D8) -> 23000 | G8: =+E8 -> 23000 | N8: 3384875
B9: Strategic management | D9: =+'Calculadora INC Abril'!F16 -> 105 | E9: =SUM(C9:D9) -> 105 | G9: =+E9 -> 105 | N9: =N8/#REF! -> #REF!
B10: Factorial | D10: =+'Calculadora INC Marzo'!G17 -> 87.5 | E10: =SUM(C10:D10) -> 87.5 | G10: =+E10 -> 87.5
B11: Estrategia Tributaria | D11: =+'Calculadora INC Marzo'!G18 -> 350 | E11: =SUM(C11:D11) -> 350 | G11: =+E11 -> 350
B12: Compras Colombia | C12: =+'[3]Calculadora MCS Enero-24'!C19 -> 0 | D12: 0 | E12: =SUM(C12:D12) -> 0 | G12: =+E12 -> 0
C14: =SUM(C3:C13) -> 198446.56 | D14: =SUM(D3:D13) -> 82385.171 | E14: =SUM(E3:E13) -> 280831.73 | G14: =E14+F14 -> 280831.73
B15: TOTAL INGRESO
B18: DESCUENTOS
B19: Legales | C19: =+'Calculadora MCS Abril'!F14 -> -19243 | E19: =SUM(C19:D19) -> -19243 | F19: Pereira | G19: =E19 -> -19243
B20: Datateck | C20: =+'Calculadora MCS Abril'!F15 -> -2252 | E20: =SUM(C20:D20) -> -2252 | F20: Guatemala | G20: =E20 -> -2252
B21: Claro SIP Enero | C21: =+'Calculadora MCS Abril'!F16 -> -187.5 | E21: =SUM(C21:D21) -> -187.5 | F21: Guatemala | G21: =E21 -> -187.5
B22: Worldnet lineas tel adicionales | C22: =+'Calculadora MCS Abril'!F17 -> -861.79 | E22: =SUM(C22:D22) -> -861.79 | F22: Guatemala | G22: =E22 -> -861.79
B23: Comision PR (transcita) | C23: =+'Calculadora MCS Abril'!F19 -> -3679.38 | D23: 0 | E23: =SUM(C23:D23) -> -3679.38 | F23: Pereira | G23: =E23 -> -3679.38
B24: Legales Bono GT & LC Cuota 4/12 | C24: =+'Calculadora MCS Abril'!F18 -> -2995.63 | E24: =SUM(C24:D24) -> -2995.63 | F24: Pereira | G24: =E24 -> -2995.63
B25: Almacenamiento de Llamadas | C25: =-#REF! -> #REF! | E25: =SUM(C25:D25) -> #REF! | F25: Guatemala | G25: =E25 -> #REF! | H25: Definir a que sociedad va ir el descuento
B26: Neptuno | C26: =-#REF! -> #REF! | E26: =SUM(C26:D26) -> #REF! | F26: Guatemala | G26: =E26 -> #REF!
C27: =SUM(C19:C26) -> #REF! | D27: =SUM(D19:D26) -> 0 | E27: =SUM(E19:E26) -> #REF! | G27: =SUM(G19:G26) -> #REF!
D31: Total Ingreso | E31: Descuentos | F31: Total Factura
B32: Col | C32: 0.655 | D32: =+$E$14*C32 -> 183944.79 | E32: =+G19+G23+G24 -> -25918.01 | F32: =+D32+E32 -> 158026.78
B33: Mex | C33: 0.075 | D33: =+$E$14*C33 -> 21062.38 | F33: =+D33+E33 -> 21062.38
B34: GT | C34: 0.27 | D34: =+$E$14*C34 -> 75824.568 | E34: =+G20+G21+G22+G25+G26 -> #REF! | F34: =+D34+E34 -> #REF!
C36: =C32+C33+C34 -> 1 | D36: =D32+D33+D34 -> 280831.73 | E36: =E32+E33+E34 -> #REF! | F36: =F32+F33+F34 -> #REF!

Sheet Calculadora INC Abril
C3: Addiuva Enterprises Ayuda sin fronteras
F6: Fecha: | G6: =TODAY() -> 45974
C11: Item | D11: Concepto | E11: Cantidad | F11: Subtotal | G11: Total | H11: Cabina mes anterior
C12: 1 | D12: Cabina | E12: 1 | F12: =+'Servicios de Cabina INC'!N61 -> 49728.671 | G12: ='Calculadora INC Abril'!$E12*'Calculadora INC Abril'!$F12 -> 49728.671 | H12: =+'Servicios de Cabina INC'!M61 -> 46185.214
C13: 2 | D13: Gmail | E13: 46 | F13: 12.5 | G13: ='Calculadora INC Abril'!$E13*'Calculadora INC Abril'!$F13 -> 575 | H13: =+G12-H12 -> 3543.4575
C14: 3 | D14: ODOO | E14: 3 | F14: 1500 | G14: ='Calculadora INC Abril'!$E14*'Calculadora INC Abril'!$F14 -> 4500 | H14: =+H13/H12 -> 0.076722769
C15: 4 | D15: Biblioteca SAP | E15: 1 | F15: 0 | G15: ='Calculadora INC Abril'!$E15*'Calculadora INC Abril'!$F15 -> 0
C16: 5 | D16: Strategic management | E16: 1 | F16: 105 | G16: ='Calculadora INC Abril'!$E16*'Calculadora INC Abril'!$F16 -> 105
C17: 6 | D17: Factorial | E17: 1 | F17: 87.5 | G17: ='Calculadora INC Abril'!$E17*'Calculadora INC Abril'!$F17 -> 87.5
C18: 7 | D18: Estrategia Tributaria | E18: 1 | F18: 350 | G18: ='Calculadora INC Abril'!$E18*'Calculadora INC Abril'!$F18 -> 350
C19: 8 | D19: MPLS | E19: 1 | F19: 3539 | G19: ='Calculadora INC Abril'!$E19*'Calculadora INC Abril'!$F19 -> 3539
C20: 9 | D20: Calidad | E20: 1 | F20: 500 | G20: ='Calculadora INC Abril'!$E20*'Calculadora INC Abril'!$F20 -> 500
C21: 10 | D21: Apoyo Contable | E21: 1 | F21: 22000 | G21: ='Calculadora INC Abril'!$E21*'Calculadora INC Abril'!$F21 -> 22000
C22: 11 | D22: Compras Colombia | E22: 1 | F22: =+#REF! -> #REF! | G22: ='Calculadora INC Abril'!$E22*'Calculadora INC Abril'!$F22 -> #REF!
F23: Subtotal | G23: =SUM(G12:G22) -> #REF!
F25: ='Calculadora INC Abril'!Saldo_pendiente -> #REF!

Sheet Calculadora MCS Abril
C3: Addiuva Enterprises Ayuda sin fronteras
F6: Fecha: | G6: =TODAY() -> 45974
C11: Item | D11: Concepto | E11: Cantidad | F11: Subtotal | G11: Total | H11: Cabina mes anterior
C12: 1 | D12: Cabina | E12: 1 | F12: =+'Servicios de Cabina MCS'!N61 -> 192446.56 | G12: =+'Calculadora MCS Abril'!$F12 -> 192446.56 | H12: =+'Calculadora MCS Marzo'!$G12 -> 171366.78
C13: 2 | D13: ODOO | E13: 4 | F13: 1500 | G13: ='Calculadora MCS Abril'!$E13*'Calculadora MCS Abril'!$F13 -> 6000 | H13: =+G12-H12 -> 21079.787
C14: 3 | D14: Legales | E14: 1 | F14: -19243 | G14: ='Calculadora MCS Abril'!$E14*'Calculadora MCS Abril'!$F14 -> -19243 | H14: =+H13/H12 -> 0.12300976
C15: 4 | D15: Datateck | E15: 1 | F15: -2252 | G15: ='Calculadora MCS Abril'!$E15*'Calculadora MCS Abril'!$F15 -> -2252
C16: 5 | D16: Claro SIP Enero | E16: 1 | F16: -187.5 | G16: ='Calculadora MCS Abril'!$E16*'Calculadora MCS Abril'!$F16 -> -187.5
C17: 6 | D17: Worldnet lineas tel adicionales | E17: 1 | F17: -861.79 | G17: ='Calculadora MCS Abril'!$E17*'Calculadora MCS Abril'!$F17 -> -861.79
C18: 7 | D18: Legales Bono GT & LC Cuota 4/12 | E18: 1 | F18: -2995.63 | G18: ='Calculadora MCS Abril'!$E18*'Calculadora MCS Abril'!$F18 -> -2995.63
C19: 8 | D19: Comision PR (Transcita) | E19: 1 | F19: -3679.38 | G19: ='Calculadora MCS Abril'!$E19*'Calculadora MCS Abril'!$F19 -> -3679.38
F21: Subtotal | G21: =SUM(G12:G20) -> 169227.26
F23: ='Calculadora MCS Abril'!Saldo_pendiente -> #REF!

Sheet Consolidado Marzo
B2: INGRESO | C2: MCS | D2: INC | E2: TOTAL | F2: Cabina Mes Anterior | G2: Cabina Total
B3: CABINA | C3: =+'Calculadora MCS Marzo'!G12 -> 171366.78 | D3: =+'Calculadora INC Marzo'!G12 -> 46185.214 | E3: =SUM(C3:D3) -> 217551.99 | F3: =+'Calculadora INC Febrero'!H12+'Calculadora MCS Febrero'!H12 -> 0 | G3: =+E3 -> 217551.99
B4: Gmail | C4: ='[3]Calculadora MCS Enero-24'!C15 -> 0 | D4: =+'Calculadora INC Marzo'!G13 -> 575 | E4: =SUM(C4:D4) -> 575 | F4: =+E3-F3 -> 217551.99 | G4: =+E4 -> 575
B5: SAP-ODOO | C5: =+'Calculadora MCS Marzo'!G13 -> 6000 | D5: =+'Calculadora INC Marzo'!G14 -> 4500 | E5: =SUM(C5:D5) -> 10500 | F5: =+F4/F3 -> #DIV/0! | G5: =+E5 -> 10500
B6: MPLS | C6: #REF! | D6: =+'Calculadora INC Marzo'!G19 -> 3539 | E6: =SUM(C6:D6) -> 3539 | G6: =+E6 -> 3539
B7: Calidad | C7: #REF! | D7: =+'Calculadora INC Marzo'!G20 -> 500 | E7: =SUM(C7:D7) -> 500 | G7: =+E7 -> 500
B8: Apoyo Contable | C8: 0 | D8: =+'Calculadora INC Marzo'!G21+1000 -> 23000 | E8: =SUM(C8:D8) -> 23000 | G8: =+E8 -> 23000 | I8: Ingreso de persona nueva equipo comercial | N8: 3384875
B9: Strategic management | D9: =+'Calculadora INC Marzo'!G16 -> 105 | E9: =SUM(C9:D9) -> 105 | G9: =+E9 -> 105 | N9: =N8/#REF! -> #REF!
B10: Factorial | D10: =+'Calculadora INC Marzo'!G17 -> 87.5 | E10: =SUM(C10:D10) -> 87.5 | G10: =+E10 -> 87.5
B11: Estrategia Tributaria | D11: =+'Calculadora INC Marzo'!G18 -> 350 | E11: =SUM(C11:D11) -> 350 | G11: =+E11 -> 350
B12: Compras Colombia | C12: =+'[3]Calculadora MCS Enero-24'!C19 -> 0 | D12: =+'Calculadora INC Marzo'!G22 -> #REF! | E12: =SUM(C12:D12) -> #REF! | G12: =+E12 -> #REF!
C14: =SUM(C3:C13) -> 177366.78 | D14: =SUM(D3:D13) -> #REF! | E14: =SUM(E3:E13) -> #REF! | G14: =E14+F14 -> #REF!
B15: TOTAL INGRESO
B18: DESCUENTOS
B19: Legales | C19: =+'Calculadora MCS Marzo'!G14 -> -19243 | E19: =SUM(C19:D19) -> -19243 | F19: Pereira | G19: =E19 -> -19243
B20: Datateck | C20: =+'Calculadora MCS Marzo'!G15 -> -2252 | E20: =SUM(C20:D20) -> -2252 | F20: Guatemala | G20: =E20 -> -2252
B21: Claro SIP Enero | C21: =+'Calculadora MCS Marzo'!G16 -> -187.5 | E21: =SUM(C21:D21) -> -187.5 | F21: Guatemala | G21: =E21 -> -187.5
B22: Worldnet lineas tel adicionales | C22: =+'Calculadora MCS Marzo'!G17 -> -861.79 | E22: =SUM(C22:D22) -> -861.79 | F22: Guatemala | G22: =E22 -> -861.79
B23: Comision PR (transcita) | C23: =+'Calculadora MCS Marzo'!G19 -> -3679.38 | D23: 0 | E23: =SUM(C23:D23) -> -3679.38 | F23: Pereira | G23: =E23 -> -3679.38
B24: Legales Bono GT & LC Cuota 3/12 | C24: =+'Calculadora MCS Marzo'!G18 -> -2995.63 | E24: =SUM(C24:D24) -> -2995.63 | F24: Pereira | G24: =E24 -> -2995.63
C25: =SUM(C19:C24) -> -29219.3 | D25: =SUM(D19:D24) -> 0 | E25: =SUM(E19:E24) -> -29219.3 | G25: =SUM(G19:G24) -> -29219.3
D29: Total Ingreso | E29: Descuentos | F29: Total Factura
B30: Col | C30: 0.655 | D30: =+$E$14*C30 -> #REF! | E30: =+G19+G23+G24 -> -25918.01 | F30: =+D30+E30 -> #REF!
B31: Mex | C31: 0.075 | D31: =+$E$14*C31 -> #REF! | F31: =+D31+E31 -> #REF!
B32: GT | C32: 0.27 | D32: =+$E$14*C32 -> #REF! | E32: =+G20+G21+G22 -> -3301.29 | F32: =+D32+E32 -> #REF!
C34: =C30+C31+C32 -> 1 | D34: =D30+D31+D32 -> #REF! | E34: =E30+E31+E32 -> -29219.3 | F34: =F30+F31+F32 -> #REF!

Sheet Calculadora INC Marzo
C3: Addiuva Enterprises Ayuda sin fronteras
F6: Fecha: | G6: =TODAY() -> 45974
C11: Item | D11: Concepto | E11: Cantidad | F11: Subtotal | G11: Total | H11: Cabina mes anterior
C12: 1 | D12: Cabina | E12: 1 | F12: =+'Servicios de Cabina INC'!M61 -> 46185.214 | G12: ='Calculadora INC Marzo'!$E12*'Calculadora INC Marzo'!$F12 -> 46185.214 | H12: =+'Calculadora INC Febrero'!$G12 -> 48812.702
C13: 2 | D13: Gmail | E13: 46 | F13: 12.5 | G13: ='Calculadora INC Marzo'!$E13*'Calculadora INC Marzo'!$F13 -> 575 | H13: =+G12-H12 -> -2627.4887
C14: 3 | D14: ODOO | E14: 3 | F14: 1500 | G14: ='Calculadora INC Marzo'!$E14*'Calculadora INC Marzo'!$F14 -> 4500 | H14: =+H13/H12 -> -0.05382797
C15: 4 | D15: Biblioteca SAP | E15: 1 | F15: 0 | G15: ='Calculadora INC Marzo'!$E15*'Calculadora INC Marzo'!$F15 -> 0
C16: 5 | D16: Strategic management | E16: 1 | F16: 105 | G16: ='Calculadora INC Marzo'!$E16*'Calculadora INC Marzo'!$F16 -> 105
C17: 6 | D17: Factorial | E17: 1 | F17: 87.5 | G17: ='Calculadora INC Marzo'!$E17*'Calculadora INC Marzo'!$F17 -> 87.5
C18: 7 | D18: Estrategia Tributaria | E18: 1 | F18: 350 | G18: ='Calculadora INC Marzo'!$E18*'Calculadora INC Marzo'!$F18 -> 350
C19: 8 | D19: MPLS | E19: 1 | F19: 3539 | G19: ='Calculadora INC Marzo'!$E19*'Calculadora INC Marzo'!$F19 -> 3539
C20: 9 | D20: Calidad | E20: 1 | F20: 500 | G20: ='Calculadora INC Marzo'!$E20*'Calculadora INC Marzo'!$F20 -> 500
C21: 10 | D21: Apoyo Contable | E21: 1 | F21: 22000 | G21: ='Calculadora INC Marzo'!$E21*'Calculadora INC Marzo'!$F21 -> 22000
C22: 11 | D22: Compras Colombia | E22: 1 | F22: =+#REF! -> #REF! | G22: ='Calculadora INC Marzo'!$E22*'Calculadora INC Marzo'!$F22 -> #REF!
F23: Subtotal | G23: =SUM(G12:G22) -> #REF!
F25: ='Calculadora INC Marzo'!Saldo_pendiente -> #REF!

Sheet Calculadora MCS Marzo
C3: Addiuva Enterprises Ayuda sin fronteras
F6: Fecha: | G6: =TODAY() -> 45974
C11: Item | D11: Concepto | E11: Cantidad | F11: Subtotal | G11: Total | H11: Cabina mes anterior
C12: 1 | D12: Cabina | E12: 1 | F12: =+'Servicios de Cabina MCS'!M61 -> 171366.78 | G12: =+'Calculadora MCS Marzo'!$F12 -> 171366.78 | H12: =+'Servicios de Cabina MCS'!L61 -> 181169.07
C13: 2 | D13: ODOO | E13: 4 | F13: 1500 | G13: ='Calculadora MCS Marzo'!$E13*'Calculadora MCS Marzo'!$F13 -> 6000 | H13: =+G12-H12 -> -9802.2943
C14: 3 | D14: Legales | E14: 1 | F14: -19243 | G14: ='Calculadora MCS Marzo'!$E14*'Calculadora MCS Marzo'!$F14 -> -19243 | H14: =+H13/H12 -> -0.054105782
C15: 4 | D15: Datateck | E15: 1 | F15: -2252 | G15: ='Calculadora MCS Marzo'!$E15*'Calculadora MCS Marzo'!$F15 -> -2252
C16: 5 | D16: Claro SIP Enero | E16: 1 | F16: -187.5 | G16: ='Calculadora MCS Marzo'!$E16*'Calculadora MCS Marzo'!$F16 -> -187.5
C17: 6 | D17: Worldnet lineas tel adicionales | E17: 1 | F17: -861.79 | G17: ='Calculadora MCS Marzo'!$E17*'Calculadora MCS Marzo'!$F17 -> -861.79
C18: 7 | D18: Legales Bono GT & LC Cuota 3/12 | E18: 1 | F18: -2995.63 | G18: ='Calculadora MCS Marzo'!$E18*'Calculadora MCS Marzo'!$F18 -> -2995.63
C19: 8 | D19: Comision PR (Transcita) | E19: 1 | F19: -3679.38 | G19: ='Calculadora MCS Marzo'!$E19*'Calculadora MCS Marzo'!$F19 -> -3679.38
F21: Subtotal | G21: =SUM(G12:G20) -> 148147.48
F23: ='Calculadora MCS Marzo'!Saldo_pendiente -> #REF!

Sheet Consolidado Febrero
B2: INGRESO | C2: MCS | D2: INC | E2: TOTAL | F2: Cabina Mes Anterior | G2: Cabina Total
B3: CABINA | C3: =+'Calculadora MCS Febrero'!G12 -> 181169.07 | D3: =+'Calculadora INC Febrero'!G12 -> 48812.702 | E3: =SUM(C3:D3) -> 229981.77 | F3: =+'Calculadora INC Febrero'!H12+'Calculadora MCS Febrero'!H12 -> 0 | G3: =+E3 -> 229981.77
B4: Gmail | C4: ='[3]Calculadora MCS Enero-24'!C15 -> 0 | D4: =+'Calculadora INC Febrero'!G13 -> 562.5 | E4: =SUM(C4:D4) -> 562.5 | F4: =+E3-F3 -> 229981.77 | G4: =+E4 -> 562.5
B5: SAP-ODOO | C5: =+'Calculadora MCS Febrero'!G13 -> 6000 | D5: ='[3]Calculadora INC Enero-24'!C16 -> 0 | E5: =SUM(C5:D5) -> 6000 | F5: =+F4/F3 -> #DIV/0! | G5: =+E5 -> 6000
B6: MPLS | C6: #REF! | D6: =+'Calculadora INC Febrero'!G19 -> 3539 | E6: =SUM(C6:D6) -> 3539 | G6: =+E6 -> 3539
B7: Calidad | C7: #REF! | D7: =+'Calculadora INC Febrero'!F20 -> 500 | E7: =SUM(C7:D7) -> 500 | G7: =+E7 -> 500
B8: Apoyo Contable | C8: 0 | D8: =+'Calculadora INC Febrero'!F21 -> 21000 | E8: =SUM(C8:D8) -> 21000 | G8: =+E8 -> 21000
B9: Strategic management | D9: =+'Calculadora INC Febrero'!G16 -> 105 | E9: =SUM(C9:D9) -> 105 | G9: =+E9 -> 105
B10: Factorial | D10: =+'Calculadora INC Febrero'!G17 -> 87.5 | E10: =SUM(C10:D10) -> 87.5 | G10: =+E10 -> 87.5
B11: Estrategia Tributaria | D11: =+'Calculadora INC Febrero'!G18 -> 350 | E11: =SUM(C11:D11) -> 350 | G11: =+E11 -> 350
B12: Compras Colombia | C12: =+'[3]Calculadora MCS Enero-24'!C19 -> 0 | D12: =+'Calculadora INC Febrero'!G22 -> #REF! | E12: =SUM(C12:D12) -> #REF! | G12: =+E12 -> #REF!
C14: =SUM(C3:C13) -> 187169.07 | D14: =SUM(D3:D13) -> #REF! | E14: =SUM(E3:E13) -> #REF! | G14: =E14+F14 -> #REF!
B15: TOTAL INGRESO
B18: DESCUENTOS
B19: Legales | C19: =+'Calculadora MCS Febrero'!G14 -> -18965 | E19: =SUM(C19:D19) -> -18965 | F19: Pereira | G19: =E19 -> -18965
B20: Datateck | C20: =+'Calculadora MCS Febrero'!G15 -> -2252 | E20: =SUM(C20:D20) -> -2252 | F20: Guatemala | G20: =E20 -> -2252
B21: Claro SIP Enero | C21: =+'Calculadora MCS Febrero'!G16 -> -187.5 | E21: =SUM(C21:D21) -> -187.5 | F21: Guatemala | G21: =E21 -> -187.5
B22: Worldnet lineas tel adicionales | C22: =+'Calculadora MCS Febrero'!G17 -> -861.79 | E22: =SUM(C22:D22) -> -861.79 | F22: Guatemala | G22: =E22 -> -861.79
B23: Comision PR (transcita) | C23: =+'Calculadora MCS Febrero'!G19 -> -3679.38 | D23: 0 | E23: =SUM(C23:D23) -> -3679.38 | F23: Pereira | G23: =E23 -> -3679.38
B24: Legales Bono GT & LC Cuota 1/12 | C24: =+'Calculadora MCS Febrero'!G18 -> -2995.63 | E24: =SUM(C24:D24) -> -2995.63 | F24: Pereira | G24: =E24 -> -2995.63
C25: =SUM(C19:C24) -> -28941.3 | D25: =SUM(D19:D24) -> 0 | E25: =SUM(E19:E24) -> -28941.3 | G25: =SUM(G19:G24) -> -28941.3
D29: Total Ingreso | E29: Descuentos | F29: Total Factura
B30: Col | C30: 0.655 | D30: =+$E$14*C30 -> #REF! | E30: =+G19+G23+G24 -> -25640.01 | F30: =+D30+E30 -> #REF!
B31: Mex | C31: 0.075 | D31: =+$E$14*C31 -> #REF! | F31: =+D31+E31 -> #REF!
B32: GT | C32: 0.27 | D32: =+$E$14*C32 -> #REF! | E32: =+G20+G21+G22 -> -3301.29 | F32: =+D32+E32 -> #REF!
C34: =C30+C31+C32 -> 1 | D34: =D30+D31+D32 -> #REF! | E34: =E30+E31+E32 -> -28941.3 | F34: =F30+F31+F32 -> #REF!

Sheet Calculadora INC Febrero
C3: Addiuva Enterprises Ayuda sin fronteras
F6: Fecha: | G6: =TODAY() -> 45974
C11: Item | D11: Concepto | E11: Cantidad | F11: Subtotal | G11: Total | H11: Cabina mes anterior
C12: 1 | D12: Cabina | E12: 1 | F12: =+'Servicios de Cabina INC'!L61 -> 48812.702 | G12: ='Calculadora INC Febrero'!$E12*'Calculadora INC Febrero'!$F12 -> 48812.702 | H12: =+'[3]Calculadora INC Enero-24'!$C$11 -> 0
C13: 2 | D13: Gmail | E13: 45 | F13: 12.5 | G13: ='Calculadora INC Febrero'!$E13*'Calculadora INC Febrero'!$F13 -> 562.5 | H13: =+G12-H12 -> 48812.702
C14: 3 | D14: ODOO | E14: 3 | F14: 1500 | G14: ='Calculadora INC Febrero'!$E14*'Calculadora INC Febrero'!$F14 -> 4500 | H14: =+H13/H12 -> #DIV/0!
C15: 4 | D15: Biblioteca SAP | E15: 1 | F15: 0 | G15: ='Calculadora INC Febrero'!$E15*'Calculadora INC Febrero'!$F15 -> 0
C16: 5 | D16: Strategic management | E16: 1 | F16: 105 | G16: ='Calculadora INC Febrero'!$E16*'Calculadora INC Febrero'!$F16 -> 105
C17: 6 | D17: Factorial | E17: 1 | F17: 87.5 | G17: ='Calculadora INC Febrero'!$E17*'Calculadora INC Febrero'!$F17 -> 87.5
C18: 7 | D18: Estrategia Tributaria | E18: 1 | F18: 350 | G18: ='Calculadora INC Febrero'!$E18*'Calculadora INC Febrero'!$F18 -> 350
C19: 8 | D19: MPLS | E19: 1 | F19: 3539 | G19: ='Calculadora INC Febrero'!$E19*'Calculadora INC Febrero'!$F19 -> 3539
C20: 9 | D20: Calidad | E20: 1 | F20: 500 | G20: ='Calculadora INC Febrero'!$E20*'Calculadora INC Febrero'!$F20 -> 500
C21: 10 | D21: Apoyo Contable | E21: 1 | F21: 21000 | G21: ='Calculadora INC Febrero'!$E21*'Calculadora INC Febrero'!$F21 -> 21000
C22: 11 | D22: Compras Colombia | E22: 1 | F22: =+#REF!+1000 -> #REF! | G22: ='Calculadora INC Febrero'!$E22*'Calculadora INC Febrero'!$F22 -> #REF!
F23: Subtotal | G23: =SUM(G12:G22) -> #REF!
F25: =Saldo_pendiente -> #REF!

Sheet Calculadora MCS Febrero
C3: Addiuva Enterprises Ayuda sin fronteras
F6: Fecha: | G6: =TODAY() -> 45974
C11: Item | D11: Concepto | E11: Cantidad | F11: Subtotal | G11: Total | H11: Cabina mes anterior
C12: 1 | D12: Cabina | E12: 1 | F12: =+'Servicios de Cabina MCS'!L61 -> 181169.07 | G12: =+'Calculadora MCS Febrero'!$E12*'Calculadora MCS Febrero'!$F12 -> 181169.07 | H12: =+'[3]Calculadora MCS Enero-24'!$C$11 -> 0
C13: 2 | D13: ODOO | E13: 4 | F13: 1500 | G13: ='Calculadora MCS Febrero'!$E13*'Calculadora MCS Febrero'!$F13 -> 6000 | H13: =+G12-H12 -> 181169.07
C14: 3 | D14: Legales | E14: 1 | F14: -18965 | G14: ='Calculadora MCS Febrero'!$E14*'Calculadora MCS Febrero'!$F14 -> -18965 | H14: =+H13/H12 -> #DIV/0!
C15: 4 | D15: Datateck | E15: 1 | F15: -2252 | G15: ='Calculadora MCS Febrero'!$E15*'Calculadora MCS Febrero'!$F15 -> -2252
C16: 5 | D16: Claro SIP Enero | E16: 1 | F16: -187.5 | G16: ='Calculadora MCS Febrero'!$E16*'Calculadora MCS Febrero'!$F16 -> -187.5
C17: 6 | D17: Worldnet lineas tel adicionales | E17: 1 | F17: -861.79 | G17: ='Calculadora MCS Febrero'!$E17*'Calculadora MCS Febrero'!$F17 -> -861.79
C18: 7 | D18: Legales Bono GT & LC Cuota 2/12 | E18: 1 | F18: -2995.63 | G18: ='Calculadora MCS Febrero'!$E18*'Calculadora MCS Febrero'!$F18 -> -2995.63
C19: 8 | D19: Comision PR (Transcita) | E19: 1 | F19: -3679.38 | G19: ='Calculadora MCS Febrero'!$E19*'Calculadora MCS Febrero'!$F19 -> -3679.38
F21: Subtotal | G21: =SUM(G12:G20) -> 158227.77
F23: ='Calculadora MCS Febrero'!Saldo_pendiente -> #REF!

Sheet Servicios de Cabina INC
E3: SERVICIOS DE CABINA
X4: 0.095
X5: 1.095
C7: A 31 de Diciembre 2025 (expresado en ML) | F7: 45138 | G7: 45169 | H7: 45199 | I7: 45230 | J7: 45260 | K7: 45291 | L7: 45688 | M7: 45716 | N7: 45747 | O7: 45777 | P7: 45808 | Q7: 45838 | R7: 45869 | S7: 45900 | T7: 45930 | U7: 45961 | V7: 45991 | W7: 46022
B8: Tipo de cobro | D8: Servicios Concluidos | F8: 0 | G8: 0 | H8: 0 | I8: 0 | J8: 0 | K8: 0 | L8: =+'Indicadores INC'!P17 -> 4031 | M8: =+'Indicadores INC'!Q17 -> 3691 | N8: =+'Indicadores INC'!R17 -> 4164 | O8: =+'Indicadores INC'!S17 -> 4046 | P8: =+'Indicadores INC'!T17 -> 4135 | Q8: =+'Indicadores INC'!U17 -> 4052 | R8: =+'Indicadores INC'!V17 -> 4213 | S8: =+'Indicadores INC'!W17 -> 4487 | ... U8: =+'Indicadores INC'!Y17 -> 4613
D9: Total de llamadas Validas | F9: =F8*$E$9 -> 0 | G9: =G8*$E$9 -> 0 | H9: =H8*$E$9 -> 0 | I9: =I8*$E$9 -> 0 | J9: =J8*$E$9 -> 0 | K9: =K8*$E$9 -> 0 | L9: =+'Indicadores INC'!P39+'Indicadores INC'!P77 -> 22411 | M9: =+'Indicadores INC'!Q39+'Indicadores INC'!Q77 -> 20531 | N9: =+'Indicadores INC'!R39+'Indicadores INC'!R77 -> 23262 | O9: =+'Indicadores INC'!S39+'Indicadores INC'!S77 -> 23477 | P9: =+'Indicadores INC'!T39+'Indicadores INC'!T77 -> 24376 | Q9: =+'Indicadores INC'!U39+'Indicadores INC'!U77 -> 21542 | R9: =+'Indicadores INC'!V39+'Indicadores INC'!V77 -> 21895 | S9: =+'Indicadores INC'!W39+'Indicadores INC'!W77 -> 20521 | ... U9: =+'Indicadores INC'!Y39+'Indicadores INC'!Y77 -> 22001
D10: Servicios Cancelados Posterior | F10: =F8*$E$10 -> 0 | G10: =G8*$E$10 -> 0 | H10: =H8*$E$10 -> 0 | I10: =I8*$E$10 -> 0 | J10: =J8*$E$10 -> 0 | K10: =K8*$E$10 -> 0 | L10: =+'Indicadores INC'!P27 -> 764 | M10: =+'Indicadores INC'!Q27 -> 700 | N10: =+'Indicadores INC'!R27 -> 739 | O10: =+'Indicadores INC'!S27 -> 758 | P10: =+'Indicadores INC'!T27 -> 746 | Q10: =+'Indicadores INC'!U27 -> 787 | R10: =+'Indicadores INC'!V27 -> 686 | S10: =+'Indicadores INC'!W27 -> 772 | ... U10: =+'Indicadores INC'!Y27 -> 695
B15: CANTIDADES | F15: =F8 -> 0 | G15: =G8 -> 0 | H15: =H8 -> 0 | I15: =I8 -> 0 | J15: =J8 -> 0 | K15: =K8 -> 0 | L15: =L8 -> 4031 | M15: =M8 -> 3691 | ... W15: =W8 -> 0
C16: Rangos Servicios concluidos | F16: Servicios concluidos
C17: 0 | D17: 50 | F17: =IF(F$15>$D17,$D17-$C17,IF(AND($C17<F$15,F$15<$D17),F$15-$C17,IF(F$15=$D17,$D17-$C17,0))) -> 0 | G17: =IF(G$15>$D17,$D17-$C17,IF(AND($C17<G$15,G$15<$D17),G$15-$C17,IF(G$15=$D17,$D17-$C17,0))) -> 0 | H17: =IF(H$15>$D17,$D17-$C17,IF(AND($C17<H$15,H$15<$D17),H$15-$C17,IF(H$15=$D17,$D17-$C17,0))) -> 0 | I17: =IF(I$15>$D17,$D17-$C17,IF(AND($C17<I$15,I$15<$D17),I$15-$C17,IF(I$15=$D17,$D17-$C17,0))) -> 0 | J17: =IF(J$15>$D17,$D17-$C17,IF(AND($C17<J$15,J$15<$D17),J$15-$C17,IF(J$15=$D17,$D17-$C17,0))) -> 0 | K17: =IF(K$15>$D17,$D17-$C17,IF(AND($C17<K$15,K$15<$D17),K$15-$C17,IF(K$15=$D17,$D17-$C17,0))) -> 0 | L17: =IF(L$15>$D17,$D17-$C17,IF(AND($C17<L$15,L$15<$D17),L$15-$C17,IF(L$15=$D17,$D17-$C17,0))) -> 50 | M17: =IF(M$15>$D17,$D17-$C17,IF(AND($C17<M$15,M$15<$D17),M$15-$C17,IF(M$15=$D17,$D17-$C17,0))) -> 50 | ... W17: =IF(W$15>$D17,$D17-$C17,IF(AND($C17<W$15,W$15<$D17),W$15-$C17,IF(W$15=$D17,$D17-$C17,0))) -> 0
C18: =D17 -> 50 | D18: 500 | F18: =IF(F$15>$D18,$D18-$C18,IF(AND($C18<F$15,F$15<$D18),F$15-$C18,IF(F$15=$D18,$D18-$C18,0))) -> 0 | G18: =IF(G$15>$D18,$D18-$C18,IF(AND($C18<G$15,G$15<$D18),G$15-$C18,IF(G$15=$D18,$D18-$C18,0))) -> 0 | H18: =IF(H$15>$D18,$D18-$C18,IF(AND($C18<H$15,H$15<$D18),H$15-$C18,IF(H$15=$D18,$D18-$C18,0))) -> 0 | I18: =IF(I$15>$D18,$D18-$C18,IF(AND($C18<I$15,I$15<$D18),I$15-$C18,IF(I$15=$D18,$D18-$C18,0))) -> 0 | J18: =IF(J$15>$D18,$D18-$C18,IF(AND($C18<J$15,J$15<$D18),J$15-$C18,IF(J$15=$D18,$D18-$C18,0))) -> 0 | K18: =IF(K$15>$D18,$D18-$C18,IF(AND($C18<K$15,K$15<$D18),K$15-$C18,IF(K$15=$D18,$D18-$C18,0))) -> 0 | L18: =IF(L$15>$D18,$D18-$C18,IF(AND($C18<L$15,L$15<$D18),L$15-$C18,IF(L$15=$D18,$D18-$C18,0))) -> 450 | M18: =IF(M$15>$D18,$D18-$C18,IF(AND($C18<M$15,M$15<$D18),M$15-$C18,IF(M$15=$D18,$D18-$C18,0))) -> 450 | ... W18: =IF(W$15>$D18,$D18-$C18,IF(AND($C18<W$15,W$15<$D18),W$15-$C18,IF(W$15=$D18,$D18-$C18,0))) -> 0
C19: =D18 -> 500 | D19: 1000 | F19: =IF(F$15>$D19,$D19-$C19,IF(AND($C19<F$15,F$15<$D19),F$15-$C19,IF(F$15=$D19,$D19-$C19,0))) -> 0 | G19: =IF(G$15>$D19,$D19-$C19,IF(AND($C19<G$15,G$15<$D19),G$15-$C19,IF(G$15=$D19,$D19-$C19,0))) -> 0 | H19: =IF(H$15>$D19,$D19-$C19,IF(AND($C19<H$15,H$15<$D19),H$15-$C19,IF(H$15=$D19,$D19-$C19,0))) -> 0 | I19: =IF(I$15>$D19,$D19-$C19,IF(AND($C19<I$15,I$15<$D19),I$15-$C19,IF(I$15=$D19,$D19-$C19,0))) -> 0 | J19: =IF(J$15>$D19,$D19-$C19,IF(AND($C19<J$15,J$15<$D19),J$15-$C19,IF(J$15=$D19,$D19-$C19,0))) -> 0 | K19: =IF(K$15>$D19,$D19-$C19,IF(AND($C19<K$15,K$15<$D19),K$15-$C19,IF(K$15=$D19,$D19-$C19,0))) -> 0 | L19: =IF(L$15>$D19,$D19-$C19,IF(AND($C19<L$15,L$15<$D19),L$15-$C19,IF(L$15=$D19,$D19-$C19,0))) -> 500 | M19: =IF(M$15>$D19,$D19-$C19,IF(AND($C19<M$15,M$15<$D19),M$15-$C19,IF(M$15=$D19,$D19-$C19,0))) -> 500 | ... W19: =IF(W$15>$D19,$D19-$C19,IF(AND($C19<W$15,W$15<$D19),W$15-$C19,IF(W$15=$D19,$D19-$C19,0))) -> 0
C20: =D19 -> 1000 | D20: 2000 | F20: =IF(F$15>$D20,$D20-$C20,IF(AND($C20<F$15,F$15<$D20),F$15-$C20,IF(F$15=$D20,$D20-$C20,0))) -> 0 | G20: =IF(G$15>$D20,$D20-$C20,IF(AND($C20<G$15,G$15<$D20),G$15-$C20,IF(G$15=$D20,$D20-$C20,0))) -> 0 | H20: =IF(H$15>$D20,$D20-$C20,IF(AND($C20<H$15,H$15<$D20),H$15-$C20,IF(H$15=$D20,$D20-$C20,0))) -> 0 | I20: =IF(I$15>$D20,$D20-$C20,IF(AND($C20<I$15,I$15<$D20),I$15-$C20,IF(I$15=$D20,$D20-$C20,0))) -> 0 | J20: =IF(J$15>$D20,$D20-$C20,IF(AND($C20<J$15,J$15<$D20),J$15-$C20,IF(J$15=$D20,$D20-$C20,0))) -> 0 | K20: =IF(K$15>$D20,$D20-$C20,IF(AND($C20<K$15,K$15<$D20),K$15-$C20,IF(K$15=$D20,$D20-$C20,0))) -> 0 | L20: =IF(L$15>$D20,$D20-$C20,IF(AND($C20<L$15,L$15<$D20),L$15-$C20,IF(L$15=$D20,$D20-$C20,0))) -> 1000 | M20: =IF(M$15>$D20,$D20-$C20,IF(AND($C20<M$15,M$15<$D20),M$15-$C20,IF(M$15=$D20,$D20-$C20,0))) -> 1000 | ... W20: =IF(W$15>$D20,$D20-$C20,IF(AND($C20<W$15,W$15<$D20),W$15-$C20,IF(W$15=$D20,$D20-$C20,0))) -> 0
C21: =D20 -> 2000 | D21: 3000 | F21: =IF(F$15>$D21,$D21-$C21,IF(AND($C21<F$15,F$15<$D21),F$15-$C21,IF(F$15=$D21,$D21-$C21,0))) -> 0 | G21: =IF(G$15>$D21,$D21-$C21,IF(AND($C21<G$15,G$15<$D21),G$15-$C21,IF(G$15=$D21,$D21-$C21,0))) -> 0 | H21: =IF(H$15>$D21,$D21-$C21,IF(AND($C21<H$15,H$15<$D21),H$15-$C21,IF(H$15=$D21,$D21-$C21,0))) -> 0 | I21: =IF(I$15>$D21,$D21-$C21,IF(AND($C21<I$15,I$15<$D21),I$15-$C21,IF(I$15=$D21,$D21-$C21,0))) -> 0 | J21: =IF(J$15>$D21,$D21-$C21,IF(AND($C21<J$15,J$15<$D21),J$15-$C21,IF(J$15=$D21,$D21-$C21,0))) -> 0 | K21: =IF(K$15>$D21,$D21-$C21,IF(AND($C21<K$15,K$15<$D21),K$15-$C21,IF(K$15=$D21,$D21-$C21,0))) -> 0 | L21: =IF(L$15>$D21,$D21-$C21,IF(AND($C21<L$15,L$15<$D21),L$15-$C21,IF(L$15=$D21,$D21-$C21,0))) -> 1000 | M21: =IF(M$15>$D21,$D21-$C21,IF(AND($C21<M$15,M$15<$D21),M$15-$C21,IF(M$15=$D21,$D21-$C21,0))) -> 1000 | ... W21: =IF(W$15>$D21,$D21-$C21,IF(AND($C21<W$15,W$15<$D21),W$15-$C21,IF(W$15=$D21,$D21-$C21,0))) -> 0
C22: =D21 -> 3000 | D22: 6000 | F22: =IF(F$15>$D22,$D22-$C22,IF(AND($C22<F$15,F$15<$D22),F$15-$C22,IF(F$15=$D22,$D22-$C22,0))) -> 0 | G22: =IF(G$15>$D22,$D22-$C22,IF(AND($C22<G$15,G$15<$D22),G$15-$C22,IF(G$15=$D22,$D22-$C22,0))) -> 0 | H22: =IF(H$15>$D22,$D22-$C22,IF(AND($C22<H$15,H$15<$D22),H$15-$C22,IF(H$15=$D22,$D22-$C22,0))) -> 0 | I22: =IF(I$15>$D22,$D22-$C22,IF(AND($C22<I$15,I$15<$D22),I$15-$C22,IF(I$15=$D22,$D22-$C22,0))) -> 0 | J22: =IF(J$15>$D22,$D22-$C22,IF(AND($C22<J$15,J$15<$D22),J$15-$C22,IF(J$15=$D22,$D22-$C22,0))) -> 0 | K22: =IF(K$15>$D22,$D22-$C22,IF(AND($C22<K$15,K$15<$D22),K$15-$C22,IF(K$15=$D22,$D22-$C22,0))) -> 0 | L22: =IF(L$15>$D22,$D22-$C22,IF(AND($C22<L$15,L$15<$D22),L$15-$C22,IF(L$15=$D22,$D22-$C22,0))) -> 1031 | M22: =IF(M$15>$D22,$D22-$C22,IF(AND($C22<M$15,M$15<$D22),M$15-$C22,IF(M$15=$D22,$D22-$C22,0))) -> 691 | ... W22: =IF(W$15>$D22,$D22-$C22,IF(AND($C22<W$15,W$15<$D22),W$15-$C22,IF(W$15=$D22,$D22-$C22,0))) -> 0
C23: =D22 -> 6000 | D23: 9000 | F23: =IF(F$15>$D23,$D23-$C23,IF(AND($C23<F$15,F$15<$D23),F$15-$C23,IF(F$15=$D23,$D23-$C23,0))) -> 0 | G23: =IF(G$15>$D23,$D23-$C23,IF(AND($C23<G$15,G$15<$D23),G$15-$C23,IF(G$15=$D23,$D23-$C23,0))) -> 0 | H23: =IF(H$15>$D23,$D23-$C23,IF(AND($C23<H$15,H$15<$D23),H$15-$C23,IF(H$15=$D23,$D23-$C23,0))) -> 0 | I23: =IF(I$15>$D23,$D23-$C23,IF(AND($C23<I$15,I$15<$D23),I$15-$C23,IF(I$15=$D23,$D23-$C23,0))) -> 0 | J23: =IF(J$15>$D23,$D23-$C23,IF(AND($C23<J$15,J$15<$D23),J$15-$C23,IF(J$15=$D23,$D23-$C23,0))) -> 0 | K23: =IF(K$15>$D23,$D23-$C23,IF(AND($C23<K$15,K$15<$D23),K$15-$C23,IF(K$15=$D23,$D23-$C23,0))) -> 0 | L23: =IF(L$15>$D23,$D23-$C23,IF(AND($C23<L$15,L$15<$D23),L$15-$C23,IF(L$15=$D23,$D23-$C23,0))) -> 0 | M23: =IF(M$15>$D23,$D23-$C23,IF(AND($C23<M$15,M$15<$D23),M$15-$C23,IF(M$15=$D23,$D23-$C23,0))) -> 0 | ... W23: =IF(W$15>$D23,$D23-$C23,IF(AND($C23<W$15,W$15<$D23),W$15-$C23,IF(W$15=$D23,$D23-$C23,0))) -> 0
C24: =D23 -> 9000 | D24: 12000 | F24: =IF(F$15>$D24,$D24-$C24,IF(AND($C24<F$15,F$15<$D24),F$15-$C24,IF(F$15=$D24,$D24-$C24,0))) -> 0 | G24: =IF(G$15>$D24,$D24-$C24,IF(AND($C24<G$15,G$15<$D24),G$15-$C24,IF(G$15=$D24,$D24-$C24,0))) -> 0 | H24: =IF(H$15>$D24,$D24-$C24,IF(AND($C24<H$15,H$15<$D24),H$15-$C24,IF(H$15=$D24,$D24-$C24,0))) -> 0 | I24: =IF(I$15>$D24,$D24-$C24,IF(AND($C24<I$15,I$15<$D24),I$15-$C24,IF(I$15=$D24,$D24-$C24,0))) -> 0 | J24: =IF(J$15>$D24,$D24-$C24,IF(AND($C24<J$15,J$15<$D24),J$15-$C24,IF(J$15=$D24,$D24-$C24,0))) -> 0 | K24: =IF(K$15>$D24,$D24-$C24,IF(AND($C24<K$15,K$15<$D24),K$15-$C24,IF(K$15=$D24,$D24-$C24,0))) -> 0 | L24: =IF(L$15>$D24,$D24-$C24,IF(AND($C24<L$15,L$15<$D24),L$15-$C24,IF(L$15=$D24,$D24-$C24,0))) -> 0 | M24: =IF(M$15>$D24,$D24-$C24,IF(AND($C24<M$15,M$15<$D24),M$15-$C24,IF(M$15=$D24,$D24-$C24,0))) -> 0 | ... W24: =IF(W$15>$D24,$D24-$C24,IF(AND($C24<W$15,W$15<$D24),W$15-$C24,IF(W$15=$D24,$D24-$C24,0))) -> 0
C25: =D24 -> 12000 | D25: 15000 | F25: =IF(F$15>$D25,$D25-$C25,IF(AND($C25<F$15,F$15<$D25),F$15-$C25,IF(F$15=$D25,$D25-$C25,0))) -> 0 | G25: =IF(G$15>$D25,$D25-$C25,IF(AND($C25<G$15,G$15<$D25),G$15-$C25,IF(G$15=$D25,$D25-$C25,0))) -> 0 | H25: =IF(H$15>$D25,$D25-$C25,IF(AND($C25<H$15,H$15<$D25),H$15-$C25,IF(H$15=$D25,$D25-$C25,0))) -> 0 | I25: =IF(I$15>$D25,$D25-$C25,IF(AND($C25<I$15,I$15<$D25),I$15-$C25,IF(I$15=$D25,$D25-$C25,0))) -> 0 | J25: =IF(J$15>$D25,$D25-$C25,IF(AND($C25<J$15,J$15<$D25),J$15-$C25,IF(J$15=$D25,$D25-$C25,0))) -> 0 | K25: =IF(K$15>$D25,$D25-$C25,IF(AND($C25<K$15,K$15<$D25),K$15-$C25,IF(K$15=$D25,$D25-$C25,0))) -> 0 | L25: =IF(L$15>$D25,$D25-$C25,IF(AND($C25<L$15,L$15<$D25),L$15-$C25,IF(L$15=$D25,$D25-$C25,0))) -> 0 | M25: =IF(M$15>$D25,$D25-$C25,IF(AND($C25<M$15,M$15<$D25),M$15-$C25,IF(M$15=$D25,$D25-$C25,0))) -> 0 | ... W25: =IF(W$15>$D25,$D25-$C25,IF(AND($C25<W$15,W$15<$D25),W$15-$C25,IF(W$15=$D25,$D25-$C25,0))) -> 0
C26: =D25 -> 15000 | D26: 200000 | F26: =IF(F$15>$D26,$D26-$C26,IF(AND($C26<F$15,F$15<$D26),F$15-$C26,IF(F$15>$C26,F$15-$C26,IF(F$15=$D26,$D26-$C26,0)))) -> 0 | G26: =IF(G$15>$D26,$D26-$C26,IF(AND($C26<G$15,G$15<$D26),G$15-$C26,IF(G$15>$C26,G$15-$C26,IF(G$15=$D26,$D26-$C26,0)))) -> 0 | H26: =IF(H$15>$D26,$D26-$C26,IF(AND($C26<H$15,H$15<$D26),H$15-$C26,IF(H$15>$C26,H$15-$C26,IF(H$15=$D26,$D26-$C26,0)))) -> 0 | I26: =IF(I$15>$D26,$D26-$C26,IF(AND($C26<I$15,I$15<$D26),I$15-$C26,IF(I$15>$C26,I$15-$C26,IF(I$15=$D26,$D26-$C26,0)))) -> 0 | J26: =IF(J$15>$D26,$D26-$C26,IF(AND($C26<J$15,J$15<$D26),J$15-$C26,IF(J$15>$C26,J$15-$C26,IF(J$15=$D26,$D26-$C26,0)))) -> 0 | K26: =IF(K$15>$D26,$D26-$C26,IF(AND($C26<K$15,K$15<$D26),K$15-$C26,IF(K$15>$C26,K$15-$C26,IF(K$15=$D26,$D26-$C26,0)))) -> 0 | L26: =IF(L$15>$D26,$D26-$C26,IF(AND($C26<L$15,L$15<$D26),L$15-$C26,IF(L$15>$C26,L$15-$C26,IF(L$15=$D26,$D26-$C26,0)))) -> 0 | M26: =IF(M$15>$D26,$D26-$C26,IF(AND($C26<M$15,M$15<$D26),M$15-$C26,IF(M$15>$C26,M$15-$C26,IF(M$15=$D26,$D26-$C26,0)))) -> 0 | ... W26: =IF(W$15>$D26,$D26-$C26,IF(AND($C26<W$15,W$15<$D26),W$15-$C26,IF(W$15>$C26,W$15-$C26,IF(W$15=$D26,$D26-$C26,0)))) -> 0
F27: =F9 -> 0 | G27: =G9 -> 0 | H27: =H9 -> 0 | I27: =I9 -> 0 | J27: =J9 -> 0 | K27: =K9 -> 0 | L27: =L9 -> 22411 | M27: =M9 -> 20531 | ... W27: =W9 -> 0
C28: Rangos Llamadas | F28: Llamadas
C29: 0 | D29: 4000 | F29: =IF(F$27>$D29,$D29-$C29,IF(AND($C29<F$27,F$27<$D29),F$27-$C29,IF(F$27=$D29,$D29-$C29,0))) -> 0 | G29: =IF(G$27>$D29,$D29-$C29,IF(AND($C29<G$27,G$27<$D29),G$27-$C29,IF(G$27=$D29,$D29-$C29,0))) -> 0 | H29: =IF(H$27>$D29,$D29-$C29,IF(AND($C29<H$27,H$27<$D29),H$27-$C29,IF(H$27=$D29,$D29-$C29,0))) -> 0 | I29: =IF(I$27>$D29,$D29-$C29,IF(AND($C29<I$27,I$27<$D29),I$27-$C29,IF(I$27=$D29,$D29-$C29,0))) -> 0 | J29: =IF(J$27>$D29,$D29-$C29,IF(AND($C29<J$27,J$27<$D29),J$27-$C29,IF(J$27=$D29,$D29-$C29,0))) -> 0 | K29: =IF(K$27>$D29,$D29-$C29,IF(AND($C29<K$27,K$27<$D29),K$27-$C29,IF(K$27=$D29,$D29-$C29,0))) -> 0 | L29: =IF(L$27>$D29,$D29-$C29,IF(AND($C29<L$27,L$27<$D29),L$27-$C29,IF(L$27=$D29,$D29-$C29,0))) -> 4000 | M29: =IF(M$27>$D29,$D29-$C29,IF(AND($C29<M$27,M$27<$D29),M$27-$C29,IF(M$27=$D29,$D29-$C29,0))) -> 4000 | ... W29: =IF(W$27>$D29,$D29-$C29,IF(AND($C29<W$27,W$27<$D29),W$27-$C29,IF(W$27=$D29,$D29-$C29,0))) -> 0
C30: =D29 -> 4000 | D30: 20000 | F30: =IF(F$27>$D30,$D30-$C30,IF(AND($C30<F$27,F$27<$D30),F$27-$C30,IF(F$27=$D30,$D30-$C30,0))) -> 0 | G30: =IF(G$27>$D30,$D30-$C30,IF(AND($C30<G$27,G$27<$D30),G$27-$C30,IF(G$27=$D30,$D30-$C30,0))) -> 0 | H30: =IF(H$27>$D30,$D30-$C30,IF(AND($C30<H$27,H$27<$D30),H$27-$C30,IF(H$27=$D30,$D30-$C30,0))) -> 0 | I30: =IF(I$27>$D30,$D30-$C30,IF(AND($C30<I$27,I$27<$D30),I$27-$C30,IF(I$27=$D30,$D30-$C30,0))) -> 0 | J30: =IF(J$27>$D30,$D30-$C30,IF(AND($C30<J$27,J$27<$D30),J$27-$C30,IF(J$27=$D30,$D30-$C30,0))) -> 0 | K30: =IF(K$27>$D30,$D30-$C30,IF(AND($C30<K$27,K$27<$D30),K$27-$C30,IF(K$27=$D30,$D30-$C30,0))) -> 0 | L30: =IF(L$27>$D30,$D30-$C30,IF(AND($C30<L$27,L$27<$D30),L$27-$C30,IF(L$27=$D30,$D30-$C30,0))) -> 16000 | M30: =IF(M$27>$D30,$D30-$C30,IF(AND($C30<M$27,M$27<$D30),M$27-$C30,IF(M$27=$D30,$D30-$C30,0))) -> 16000 | ... W30: =IF(W$27>$D30,$D30-$C30,IF(AND($C30<W$27,W$27<$D30),W$27-$C30,IF(W$27=$D30,$D30-$C30,0))) -> 0
C31: =D30 -> 20000 | D31: 200000 | F31: =IF(F$27>$D31,$D31-$C31,IF(AND($C31<F$27,F$27<$D31),F$27-$C31,IF(F$27>$C31,F$27-$C31,IF(F$27=$D31,$D31-$C31,0)))) -> 0 | J31: =IF(J$27>$D31,$D31-$C31,IF(AND($C31<J$27,J$27<$D31),J$27-$C31,IF(J$27>$C31,J$27-$C31,IF(J$27=$D31,$D31-$C31,0)))) -> 0 | K31: =IF(K$27>$D31,$D31-$C31,IF(AND($C31<K$27,K$27<$D31),K$27-$C31,IF(K$27>$C31,K$27-$C31,IF(K$27=$D31,$D31-$C31,0)))) -> 0 | L31: =IF(L$27>$D31,$D31-$C31,IF(AND($C31<L$27,L$27<$D31),L$27-$C31,IF(L$27>$C31,L$27-$C31,IF(L$27=$D31,$D31-$C31,0)))) -> 2411 | M31: =IF(M$27>$D31,$D31-$C31,IF(AND($C31<M$27,M$27<$D31),M$27-$C31,IF(M$27>$C31,M$27-$C31,IF(M$27=$D31,$D31-$C31,0)))) -> 531 | N31: =IF(N$27>$D31,$D31-$C31,IF(AND($C31<N$27,N$27<$D31),N$27-$C31,IF(N$27>$C31,N$27-$C31,IF(N$27=$D31,$D31-$C31,0)))) -> 3262 | O31: =IF(O$27>$D31,$D31-$C31,IF(AND($C31<O$27,O$27<$D31),O$27-$C31,IF(O$27>$C31,O$27-$C31,IF(O$27=$D31,$D31-$C31,0)))) -> 3477 | P31: =IF(P$27>$D31,$D31-$C31,IF(AND($C31<P$27,P$27<$D31),P$27-$C31,IF(P$27>$C31,P$27-$C31,IF(P$27=$D31,$D31-$C31,0)))) -> 4376 | Q31: =IF(Q$27>$D31,$D31-$C31,IF(AND($C31<Q$27,Q$27<$D31),Q$27-$C31,IF(Q$27>$C31,Q$27-$C31,IF(Q$27=$D31,$D31-$C31,0)))) -> 1542 | ... W31: =IF(W$27>$D31,$D31-$C31,IF(AND($C31<W$27,W$27<$D31),W$27-$C31,IF(W$27>$C31,W$27-$C31,IF(W$27=$D31,$D31-$C31,0)))) -> 0
C33: Precio Unitario por Servicios Concluidos | F33: Llamadas
D34: =+IFERROR(SUM(L37:L46)/L8,0) -> 8.9885974 | F34: =IF(F$31<50,0,$D34)*F$31 -> 0 | G34: =IF(G$31<50,0,$D34)*G$31 -> 0 | H34: =IF(H$31<50,0,$D34)*H$31 -> 0 | I34: =IF(I$31<50,0,$D34)*I$31 -> 0 | J34: =IF(J$31<50,0,$D34)*J$31 -> 0 | K34: =IF(K$31<50,0,$D34)*K$31 -> 0 | L34: =+IFERROR(D34*L8,0) -> 36233.036 | M34: =+IFERROR(D34*M8,0) -> 33176.913 | N34: =+IFERROR(D34*N8,0) -> 37428.519 | O34: =+IFERROR(D34*O8,0) -> 36367.865 | P34: =+IFERROR(D34*P8,0) -> 37167.85 | Q34: =+IFERROR(D34*Q8,0) -> 36421.797 | R34: =+IFERROR(D34*R8,0) -> 37868.961 | S34: =+IFERROR(D34*S8,0) -> 40331.836 | T34: =+IFERROR(D34*T8,0) -> 38704.9 | U34: =+IFERROR(D34*U8,0) -> 41464.4 | V34: =+IFERROR(N34*V8,0) -> 0 | W34: =+IFERROR(O34*W8,0) -> 0
B36: VALORES EN USD | C36: Precios Servicios Concluidos | F36: Servicios concluidos
D37: 3434 | F37: =IF(F$17<1,0,$D$37) -> 0 | G37: =IF(G$17<1,0,$D$37) -> 0 | H37: =IF(H$17<1,0,$D$37) -> 0 | I37: =IF(I$17<1,0,$D$37) -> 0 | J37: =IF(J$17<1,0,$D$37) -> 0 | K37: =IF(K$17<1,0,$D$37) -> 0 | L37: =IF(L$17<1,0,$D$37) -> 3434 | M37: =IF(M$17<1,0,$D$37) -> 3434 | ... W37: =IF(W$17<1,0,$D$37) -> 0
D38: =10.5145425*X5 -> 11.513424 | F38: =IF(F$18=0,0,$D38)*F$18 -> 0 | G38: =IF(G$18=0,0,$D38)*G$18 -> 0 | H38: =IF(H$18=0,0,$D38)*H$18 -> 0 | I38: =IF(I$18=0,0,$D38)*I$18 -> 0 | J38: =IF(J$18=0,0,$D38)*J$18 -> 0 | K38: =IF(K$18=0,0,$D38)*K$18 -> 0 | L38: =IF(L$18=0,0,$D38)*L$18 -> 5181.0408 | M38: =IF(M$18=0,0,$D38)*M$18 -> 5181.0408 | ... W38: =IF(W$18=0,0,$D38)*W$18 -> 0
D39: =9.2775375*X5 -> 10.158904 | F39: =IF(F$19=0,0,$D39)*F$19 -> 0 | G39: =IF(G$19=0,0,$D39)*G$19 -> 0 | H39: =IF(H$19=0,0,$D39)*H$19 -> 0 | I39: =IF(I$19=0,0,$D39)*I$19 -> 0 | J39: =IF(J$19=0,0,$D39)*J$19 -> 0 | K39: =IF(K$19=0,0,$D39)*K$19 -> 0 | L39: =IF(L$19=0,0,$D39)*L$19 -> 5079.4518 | M39: =IF(M$19=0,0,$D39)*M$19 -> 5079.4518 | ... W39: =IF(W$19=0,0,$D39)*W$19 -> 0
D40: =8.0405325*X5 -> 8.8043831 | F40: =IF(F$20=0,0,$D40)*F$20 -> 0 | G40: =IF(G$20=0,0,$D40)*G$20 -> 0 | H40: =IF(H$20=0,0,$D40)*H$20 -> 0 | I40: =IF(I$20=0,0,$D40)*I$20 -> 0 | J40: =IF(J$20=0,0,$D40)*J$20 -> 0 | K40: =IF(K$20=0,0,$D40)*K$20 -> 0 | L40: =IF(L$20=0,0,$D40)*L$20 -> 8804.3831 | M40: =IF(M$20=0,0,$D40)*M$20 -> 8804.3831 | ... W40: =IF(W$20=0,0,$D40)*W$20 -> 0
D41: =6.8035275*X5 -> 7.4498626 | F41: =IF(F$21=0,0,$D41)*F$21 -> 0 | G41: =IF(G$21=0,0,$D41)*G$21 -> 0 | H41: =IF(H$21=0,0,$D41)*H$21 -> 0 | I41: =IF(I$21=0,0,$D41)*I$21 -> 0 | J41: =IF(J$21=0,0,$D41)*J$21 -> 0 | K41: =IF(K$21=0,0,$D41)*K$21 -> 0 | L41: =IF(L$21=0,0,$D41)*L$21 -> 7449.8626 | M41: =IF(M$21=0,0,$D41)*M$21 -> 7449.8626 | ... W41: =IF(W$21=0,0,$D41)*W$21 -> 0
D42: =5.5665225*X5 -> 6.0953421 | F42: =IF(F$22=0,0,$D42)*F$22 -> 0 | G42: =IF(G$22=0,0,$D42)*G$22 -> 0 | H42: =IF(H$22=0,0,$D42)*H$22 -> 0 | I42: =IF(I$22=0,0,$D42)*I$22 -> 0 | J42: =IF(J$22=0,0,$D42)*J$22 -> 0 | K42: =IF(K$22=0,0,$D42)*K$22 -> 0 | L42: =IF(L$22=0,0,$D42)*L$22 -> 6284.2977 | M42: =IF(M$22=0,0,$D42)*M$22 -> 4211.8814 | ... W42: =IF(W$22=0,0,$D42)*W$22 -> 0
D43: =5.25727125*X5 -> 5.756712 | F43: =IF(F$23=0,0,$D43)*F$23 -> 0 | G43: =IF(G$23=0,0,$D43)*G$23 -> 0 | H43: =IF(H$23=0,0,$D43)*H$23 -> 0 | I43: =IF(I$23=0,0,$D43)*I$23 -> 0 | J43: =IF(J$23=0,0,$D43)*J$23 -> 0 | K43: =IF(K$23=0,0,$D43)*K$23 -> 0 | L43: =IF(L$23=0,0,$D43)*L$23 -> 0 | M43: =IF(M$23=0,0,$D43)*M$23 -> 0 | ... W43: =IF(W$23=0,0,$D43)*W$23 -> 0
D44: =4.94802*X5 -> 5.4180819 | F44: =IF(F$24=0,0,$D44)*F$24 -> 0 | G44: =IF(G$24=0,0,$D44)*G$24 -> 0 | H44: =IF(H$24=0,0,$D44)*H$24 -> 0 | I44: =IF(I$24=0,0,$D44)*I$24 -> 0 | J44: =IF(J$24=0,0,$D44)*J$24 -> 0 | K44: =IF(K$24=0,0,$D44)*K$24 -> 0 | L44: =IF(L$24=0,0,$D44)*L$24 -> 0 | M44: =IF(M$24=0,0,$D44)*M$24 -> 0 | ... W44: =IF(W$24=0,0,$D44)*W$24 -> 0
D45: =4.63876875*X5 -> 5.0794518 | F45: =IF(F$25=0,0,$D45)*F$25 -> 0 | G45: =IF(G$25=0,0,$D45)*G$25 -> 0 | H45: =IF(H$25=0,0,$D45)*H$25 -> 0 | I45: =IF(I$25=0,0,$D45)*I$25 -> 0 | J45: =IF(J$25=0,0,$D45)*J$25 -> 0 | K45: =IF(K$25=0,0,$D45)*K$25 -> 0 | L45: =IF(L$25=0,0,$D45)*L$25 -> 0 | M45: =IF(M$25=0,0,$D45)*M$25 -> 0 | ... W45: =IF(W$25=0,0,$D45)*W$25 -> 0
D46: =4.3295175*X5 -> 4.7408217 | F46: =IF(F$26=0,0,$D46)*F$26 -> 0 | G46: =IF(G$26=0,0,$D46)*G$26 -> 0 | H46: =IF(H$26=0,0,$D46)*H$26 -> 0 | I46: =IF(I$26=0,0,$D46)*I$26 -> 0 | J46: =IF(J$26=0,0,$D46)*J$26 -> 0 | K46: =IF(K$26=0,0,$D46)*K$26 -> 0 | L46: =IF(L$26=0,0,$D46)*L$26 -> 0 | M46: =IF(M$26=0,0,$D46)*M$26 -> 0 | ... W46: =IF(W$26=0,0,$D46)*W$26 -> 0
C48: Precios Llamadas | F48: Llamadas
D49: =0.80405325*X5 -> 0.88043831 | F49: =IF(F$29<50,0,$D49)*F$29 -> 0 | G49: =IF(G$29<50,0,$D49)*G$29 -> 0 | H49: =IF(H$29<50,0,$D49)*H$29 -> 0 | I49: =IF(I$29<50,0,$D49)*I$29 -> 0 | J49: =IF(J$29<50,0,$D49)*J$29 -> 0 | K49: =IF(K$29<50,0,$D49)*K$29 -> 0 | L49: =IF(L$29<50,0,$D49)*L$29 -> 3521.7532 | M49: =IF(M$29<50,0,$D49)*M$29 -> 3521.7532 | ... W49: =IF(W$29<50,0,$D49)*W$29 -> 0
D50: =0.3711015*X5 -> 0.40635614 | F50: =IF(F$30=0,0,$D50)*F$30 -> 0 | G50: =IF(G$30=0,0,$D50)*G$30 -> 0 | H50: =IF(H$30=0,0,$D50)*H$30 -> 0 | I50: =IF(I$30=0,0,$D50)*I$30 -> 0 | J50: =IF(J$30=0,0,$D50)*J$30 -> 0 | K50: =IF(K$30=0,0,$D50)*K$30 -> 0 | L50: =IF(L$30=0,0,$D50)*L$30 -> 6501.6983 | M50: =IF(M$30=0,0,$D50)*M$30 -> 6501.6983 | ... W50: =IF(W$30=0,0,$D50)*W$30 -> 0
D51: =0.18555075*X5 -> 0.20317807 | F51: =IF(F$31=0,0,$D51)*F$31 -> 0 | G51: =IF(G$31=0,0,$D51)*G$31 -> 0 | H51: =IF(H$31=0,0,$D51)*H$31 -> 0 | I51: =IF(I$31=0,0,$D51)*I$31 -> 0 | J51: =IF(J$31=0,0,$D51)*J$31 -> 0 | K51: =IF(K$31=0,0,$D51)*K$31 -> 0 | L51: =IF(L$31=0,0,$D51)*L$31 -> 489.86233 | M51: =IF(M$31=0,0,$D51)*M$31 -> 107.88756 | ... W51: =IF(W$31=0,0,$D51)*W$31 -> 0
C53: Servicios Cancelados Posterior | F53: Llamadas
D54: =2.47*X5 -> 2.70465 | F54: =IF(F$31<50,0,$D54)*F$31 -> 0 | G54: =IF(G$31<50,0,$D54)*G$31 -> 0 | H54: =IF(H$31<50,0,$D54)*H$31 -> 0 | I54: =IF(I$31<50,0,$D54)*I$31 -> 0 | J54: =IF(J$31<50,0,$D54)*J$31 -> 0 | K54: =IF(K$31<50,0,$D54)*K$31 -> 0 | L54: =+L10*$D$54 -> 2066.3526 | M54: =+M10*$D$54 -> 1893.255 | N54: =+N10*$D$54 -> 1998.7363 | O54: =+O10*$D$54 -> 2050.1247 | P54: =+P10*$D$54 -> 2017.6689 | Q54: =+Q10*$D$54 -> 2128.5595 | R54: =+R10*$D$54 -> 1855.3899 | S54: =+S10*$D$54 -> 2087.9898 | ... W54: =+W10*$D$54 -> 0
B58: Tipo de cobro usd | D58: Servicios Concluidos | F58: =SUM(F37:F46) -> 0 | G58: =SUM(G37:G46) -> 0 | H58: =SUM(H37:H46) -> 0 | I58: =SUM(I37:I46) -> 0 | J58: =SUM(J37:J46) -> 0 | K58: =SUM(K37:K46) -> 0 | L58: =SUM(L37:L46) -> 36233.036 | M58: =SUM(M37:M46) -> 34160.62 | ... W58: =SUM(W37:W46) -> 0
D59: Total de llamadas Validas | F59: =SUM(F49:F51) -> 0 | G59: =SUM(G49:G51) -> 0 | H59: =SUM(H49:H51) -> 0 | I59: =SUM(I49:I51) -> 0 | J59: =SUM(J49:J51) -> 0 | K59: =SUM(K49:K51) -> 0 | L59: =SUM(L49:L51) -> 10513.314 | M59: =SUM(M49:M51) -> 10131.339 | ... W59: =SUM(W49:W51) -> 0
D60: Servicios Cancelados Posterior | F60: =F10*2*1.05 -> 0 | G60: =G10*2*1.05 -> 0 | H60: =H10*2*1.05 -> 0 | I60: =I10*2*1.05 -> 0 | J60: =J10*2*1.05 -> 0 | K60: =K10*2*1.05 -> 0 | L60: =+L54 -> 2066.3526 | M60: =+M54 -> 1893.255 | N60: =+N54 -> 1998.7363 | O60: =+O54 -> 2050.1247 | P60: =+P54 -> 2017.6689 | Q60: =+Q54 -> 2128.5595 | R60: =+R54 -> 1855.3899 | S60: =+S54 -> 2087.9898 | ... W60: =+W54 -> 0
D61: Total usd | F61: =SUM(F58:F60) -> 0 | G61: =SUM(G58:G60) -> 0 | H61: =SUM(H58:H60) -> 0 | I61: =SUM(I58:I60) -> 0 | J61: =SUM(J58:J60) -> 0 | K61: =SUM(K58:K60) -> 0 | L61: =SUM(L58:L60) -> 48812.702 | M61: =SUM(M58:M60) -> 46185.214 | ... W61: =SUM(W58:W60) -> 0
F66: #REF! | G66: #REF! | H66: #REF! | I66: #REF! | J66: #REF! | K66: #REF! | L66: #REF! | M66: #REF! | N66: #REF! | O66: #REF! | P66: #REF! | Q66: #REF! | R66: #REF! | S66: #REF! | T66: #REF! | U66: #REF! | V66: #REF! | W66: #REF!

Sheet Servicios de Cabina MCS
E3: SERVICIOS DE CABINA
X4: 0.095
X5: 1.095
C7: A 31 de Diciembre 2025 (expresado en ML) | F7: 45138 | G7: 45169 | H7: 45199 | I7: 45230 | J7: 45260 | K7: 45291 | L7: 45688 | M7: 45716 | N7: 45747 | O7: 45777 | P7: 45808 | Q7: 45838 | R7: 45869 | S7: 45900 | T7: 45930 | U7: 45961 | V7: 45991 | W7: 46022
B8: Tipo de cobro | D8: Servicios Concluidos | F8: 0 | G8: 0 | H8: 0 | I8: 0 | J8: 0 | K8: 0 | L8: =+'Indicadores MCS'!P17 -> 25394 | M8: =+'Indicadores MCS'!Q17 -> 23403 | N8: =+'Indicadores MCS'!R17 -> 27858 | O8: =+'Indicadores MCS'!S17 -> 27100 | P8: =+'Indicadores MCS'!T17 -> 26336 | Q8: =+'Indicadores MCS'!U17 -> 30971 | R8: =+'Indicadores MCS'!V17 -> 28672 | S8: =+'Indicadores MCS'!W17 -> 29048 | ... U8: =+'Indicadores MCS'!Y17 -> 32850
D9: Total de llamadas Validas | F9: =F8*$E$9 -> 0 | G9: =G8*$E$9 -> 0 | H9: =H8*$E$9 -> 0 | I9: =I8*$E$9 -> 0 | J9: =J8*$E$9 -> 0 | K9: =K8*$E$9 -> 0 | L9: =+'Indicadores MCS'!P39+'Indicadores MCS'!P77 -> 47063 | M9: =+'Indicadores MCS'!Q39+'Indicadores MCS'!Q77 -> 43318 | N9: =+'Indicadores MCS'!R39+'Indicadores MCS'!R77 -> 46180 | O9: =+'Indicadores MCS'!S39+'Indicadores MCS'!S77 -> 35777 | P9: =+'Indicadores MCS'!T39+'Indicadores MCS'!T77 -> 49883 | Q9: =+'Indicadores MCS'!U39+'Indicadores MCS'!U77 -> 49084 | R9: =+'Indicadores MCS'!V39+'Indicadores MCS'!V77 -> 44750 | S9: =+'Indicadores MCS'!W39+'Indicadores MCS'!W77 -> 43567 | ... U9: =+'Indicadores MCS'!Y39+'Indicadores MCS'!Y77 -> 55284
D10: Servicios Cancelados Posterior | F10: =F8*$E$10 -> 0 | G10: =G8*$E$10 -> 0 | H10: =H8*$E$10 -> 0 | I10: =I8*$E$10 -> 0 | J10: =J8*$E$10 -> 0 | K10: =K8*$E$10 -> 0 | L10: =+'Indicadores MCS'!P27 -> 7163 | M10: =+'Indicadores MCS'!Q27 -> 7310 | N10: =+'Indicadores MCS'!R27 -> 7080 | O10: =+'Indicadores MCS'!S27 -> 7490 | P10: =+'Indicadores MCS'!T27 -> 7063 | Q10: =+'Indicadores MCS'!U27 -> 5914 | R10: =+'Indicadores MCS'!V27 -> 3838 | S10: =+'Indicadores MCS'!W27 -> 3729 | ... U10: =+'Indicadores MCS'!Y27 -> 5400
B15: CANTIDADES | F15: =F8 -> 0 | G15: =G8 -> 0 | H15: =H8 -> 0 | I15: =I8 -> 0 | J15: =J8 -> 0 | K15: =K8 -> 0 | L15: =L8 -> 25394 | M15: =M8 -> 23403 | ... W15: =W8 -> 0
C16: Rangos Servicios concluidos | F16: Servicios concluidos
C17: 0 | D17: 50 | F17: =IF(F$15>$D17,$D17-$C17,IF(AND($C17<F$15,F$15<$D17),F$15-$C17,IF(F$15=$D17,$D17-$C17,0))) -> 0 | G17: =IF(G$15>$D17,$D17-$C17,IF(AND($C17<G$15,G$15<$D17),G$15-$C17,IF(G$15=$D17,$D17-$C17,0))) -> 0 | H17: =IF(H$15>$D17,$D17-$C17,IF(AND($C17<H$15,H$15<$D17),H$15-$C17,IF(H$15=$D17,$D17-$C17,0))) -> 0 | I17: =IF(I$15>$D17,$D17-$C17,IF(AND($C17<I$15,I$15<$D17),I$15-$C17,IF(I$15=$D17,$D17-$C17,0))) -> 0 | J17: =IF(J$15>$D17,$D17-$C17,IF(AND($C17<J$15,J$15<$D17),J$15-$C17,IF(J$15=$D17,$D17-$C17,0))) -> 0 | K17: =IF(K$15>$D17,$D17-$C17,IF(AND($C17<K$15,K$15<$D17),K$15-$C17,IF(K$15=$D17,$D17-$C17,0))) -> 0 | L17: =IF(L$15>$D17,$D17-$C17,IF(AND($C17<L$15,L$15<$D17),L$15-$C17,IF(L$15=$D17,$D17-$C17,0))) -> 50 | M17: =IF(M$15>$D17,$D17-$C17,IF(AND($C17<M$15,M$15<$D17),M$15-$C17,IF(M$15=$D17,$D17-$C17,0))) -> 50 | ... W17: =IF(W$15>$D17,$D17-$C17,IF(AND($C17<W$15,W$15<$D17),W$15-$C17,IF(W$15=$D17,$D17-$C17,0))) -> 0
C18: =D17 -> 50 | D18: 500 | F18: =IF(F$15>$D18,$D18-$C18,IF(AND($C18<F$15,F$15<$D18),F$15-$C18,IF(F$15=$D18,$D18-$C18,0))) -> 0 | G18: =IF(G$15>$D18,$D18-$C18,IF(AND($C18<G$15,G$15<$D18),G$15-$C18,IF(G$15=$D18,$D18-$C18,0))) -> 0 | H18: =IF(H$15>$D18,$D18-$C18,IF(AND($C18<H$15,H$15<$D18),H$15-$C18,IF(H$15=$D18,$D18-$C18,0))) -> 0 | I18: =IF(I$15>$D18,$D18-$C18,IF(AND($C18<I$15,I$15<$D18),I$15-$C18,IF(I$15=$D18,$D18-$C18,0))) -> 0 | J18: =IF(J$15>$D18,$D18-$C18,IF(AND($C18<J$15,J$15<$D18),J$15-$C18,IF(J$15=$D18,$D18-$C18,0))) -> 0 | K18: =IF(K$15>$D18,$D18-$C18,IF(AND($C18<K$15,K$15<$D18),K$15-$C18,IF(K$15=$D18,$D18-$C18,0))) -> 0 | L18: =IF(L$15>$D18,$D18-$C18,IF(AND($C18<L$15,L$15<$D18),L$15-$C18,IF(L$15=$D18,$D18-$C18,0))) -> 450 | M18: =IF(M$15>$D18,$D18-$C18,IF(AND($C18<M$15,M$15<$D18),M$15-$C18,IF(M$15=$D18,$D18-$C18,0))) -> 450 | ... W18: =IF(W$15>$D18,$D18-$C18,IF(AND($C18<W$15,W$15<$D18),W$15-$C18,IF(W$15=$D18,$D18-$C18,0))) -> 0
C19: =D18 -> 500 | D19: 1000 | F19: =IF(F$15>$D19,$D19-$C19,IF(AND($C19<F$15,F$15<$D19),F$15-$C19,IF(F$15=$D19,$D19-$C19,0))) -> 0 | G19: =IF(G$15>$D19,$D19-$C19,IF(AND($C19<G$15,G$15<$D19),G$15-$C19,IF(G$15=$D19,$D19-$C19,0))) -> 0 | H19: =IF(H$15>$D19,$D19-$C19,IF(AND($C19<H$15,H$15<$D19),H$15-$C19,IF(H$15=$D19,$D19-$C19,0))) -> 0 | I19: =IF(I$15>$D19,$D19-$C19,IF(AND($C19<I$15,I$15<$D19),I$15-$C19,IF(I$15=$D19,$D19-$C19,0))) -> 0 | J19: =IF(J$15>$D19,$D19-$C19,IF(AND($C19<J$15,J$15<$D19),J$15-$C19,IF(J$15=$D19,$D19-$C19,0))) -> 0 | K19: =IF(K$15>$D19,$D19-$C19,IF(AND($C19<K$15,K$15<$D19),K$15-$C19,IF(K$15=$D19,$D19-$C19,0))) -> 0 | L19: =IF(L$15>$D19,$D19-$C19,IF(AND($C19<L$15,L$15<$D19),L$15-$C19,IF(L$15=$D19,$D19-$C19,0))) -> 500 | M19: =IF(M$15>$D19,$D19-$C19,IF(AND($C19<M$15,M$15<$D19),M$15-$C19,IF(M$15=$D19,$D19-$C19,0))) -> 500 | ... W19: =IF(W$15>$D19,$D19-$C19,IF(AND($C19<W$15,W$15<$D19),W$15-$C19,IF(W$15=$D19,$D19-$C19,0))) -> 0
C20: =D19 -> 1000 | D20: 2000 | F20: =IF(F$15>$D20,$D20-$C20,IF(AND($C20<F$15,F$15<$D20),F$15-$C20,IF(F$15=$D20,$D20-$C20,0))) -> 0 | G20: =IF(G$15>$D20,$D20-$C20,IF(AND($C20<G$15,G$15<$D20),G$15-$C20,IF(G$15=$D20,$D20-$C20,0))) -> 0 | H20: =IF(H$15>$D20,$D20-$C20,IF(AND($C20<H$15,H$15<$D20),H$15-$C20,IF(H$15=$D20,$D20-$C20,0))) -> 0 | I20: =IF(I$15>$D20,$D20-$C20,IF(AND($C20<I$15,I$15<$D20),I$15-$C20,IF(I$15=$D20,$D20-$C20,0))) -> 0 | J20: =IF(J$15>$D20,$D20-$C20,IF(AND($C20<J$15,J$15<$D20),J$15-$C20,IF(J$15=$D20,$D20-$C20,0))) -> 0 | K20: =IF(K$15>$D20,$D20-$C20,IF(AND($C20<K$15,K$15<$D20),K$15-$C20,IF(K$15=$D20,$D20-$C20,0))) -> 0 | L20: =IF(L$15>$D20,$D20-$C20,IF(AND($C20<L$15,L$15<$D20),L$15-$C20,IF(L$15=$D20,$D20-$C20,0))) -> 1000 | M20: =IF(M$15>$D20,$D20-$C20,IF(AND($C20<M$15,M$15<$D20),M$15-$C20,IF(M$15=$D20,$D20-$C20,0))) -> 1000 | ... W20: =IF(W$15>$D20,$D20-$C20,IF(AND($C20<W$15,W$15<$D20),W$15-$C20,IF(W$15=$D20,$D20-$C20,0))) -> 0
C21: =D20 -> 2000 | D21: 3000 | F21: =IF(F$15>$D21,$D21-$C21,IF(AND($C21<F$15,F$15<$D21),F$15-$C21,IF(F$15=$D21,$D21-$C21,0))) -> 0 | G21: =IF(G$15>$D21,$D21-$C21,IF(AND($C21<G$15,G$15<$D21),G$15-$C21,IF(G$15=$D21,$D21-$C21,0))) -> 0 | H21: =IF(H$15>$D21,$D21-$C21,IF(AND($C21<H$15,H$15<$D21),H$15-$C21,IF(H$15=$D21,$D21-$C21,0))) -> 0 | I21: =IF(I$15>$D21,$D21-$C21,IF(AND($C21<I$15,I$15<$D21),I$15-$C21,IF(I$15=$D21,$D21-$C21,0))) -> 0 | J21: =IF(J$15>$D21,$D21-$C21,IF(AND($C21<J$15,J$15<$D21),J$15-$C21,IF(J$15=$D21,$D21-$C21,0))) -> 0 | K21: =IF(K$15>$D21,$D21-$C21,IF(AND($C21<K$15,K$15<$D21),K$15-$C21,IF(K$15=$D21,$D21-$C21,0))) -> 0 | L21: =IF(L$15>$D21,$D21-$C21,IF(AND($C21<L$15,L$15<$D21),L$15-$C21,IF(L$15=$D21,$D21-$C21,0))) -> 1000 | M21: =IF(M$15>$D21,$D21-$C21,IF(AND($C21<M$15,M$15<$D21),M$15-$C21,IF(M$15=$D21,$D21-$C21,0))) -> 1000 | ... W21: =IF(W$15>$D21,$D21-$C21,IF(AND($C21<W$15,W$15<$D21),W$15-$C21,IF(W$15=$D21,$D21-$C21,0))) -> 0
C22: =D21 -> 3000 | D22: 6000 | F22: =IF(F$15>$D22,$D22-$C22,IF(AND($C22<F$15,F$15<$D22),F$15-$C22,IF(F$15=$D22,$D22-$C22,0))) -> 0 | G22: =IF(G$15>$D22,$D22-$C22,IF(AND($C22<G$15,G$15<$D22),G$15-$C22,IF(G$15=$D22,$D22-$C22,0))) -> 0 | H22: =IF(H$15>$D22,$D22-$C22,IF(AND($C22<H$15,H$15<$D22),H$15-$C22,IF(H$15=$D22,$D22-$C22,0))) -> 0 | I22: =IF(I$15>$D22,$D22-$C22,IF(AND($C22<I$15,I$15<$D22),I$15-$C22,IF(I$15=$D22,$D22-$C22,0))) -> 0 | J22: =IF(J$15>$D22,$D22-$C22,IF(AND($C22<J$15,J$15<$D22),J$15-$C22,IF(J$15=$D22,$D22-$C22,0))) -> 0 | K22: =IF(K$15>$D22,$D22-$C22,IF(AND($C22<K$15,K$15<$D22),K$15-$C22,IF(K$15=$D22,$D22-$C22,0))) -> 0 | L22: =IF(L$15>$D22,$D22-$C22,IF(AND($C22<L$15,L$15<$D22),L$15-$C22,IF(L$15=$D22,$D22-$C22,0))) -> 3000 | M22: =IF(M$15>$D22,$D22-$C22,IF(AND($C22<M$15,M$15<$D22),M$15-$C22,IF(M$15=$D22,$D22-$C22,0))) -> 3000 | ... W22: =IF(W$15>$D22,$D22-$C22,IF(AND($C22<W$15,W$15<$D22),W$15-$C22,IF(W$15=$D22,$D22-$C22,0))) -> 0
C23: =D22 -> 6000 | D23: 9000 | F23: =IF(F$15>$D23,$D23-$C23,IF(AND($C23<F$15,F$15<$D23),F$15-$C23,IF(F$15=$D23,$D23-$C23,0))) -> 0 | G23: =IF(G$15>$D23,$D23-$C23,IF(AND($C23<G$15,G$15<$D23),G$15-$C23,IF(G$15=$D23,$D23-$C23,0))) -> 0 | H23: =IF(H$15>$D23,$D23-$C23,IF(AND($C23<H$15,H$15<$D23),H$15-$C23,IF(H$15=$D23,$D23-$C23,0))) -> 0 | I23: =IF(I$15>$D23,$D23-$C23,IF(AND($C23<I$15,I$15<$D23),I$15-$C23,IF(I$15=$D23,$D23-$C23,0))) -> 0 | J23: =IF(J$15>$D23,$D23-$C23,IF(AND($C23<J$15,J$15<$D23),J$15-$C23,IF(J$15=$D23,$D23-$C23,0))) -> 0 | K23: =IF(K$15>$D23,$D23-$C23,IF(AND($C23<K$15,K$15<$D23),K$15-$C23,IF(K$15=$D23,$D23-$C23,0))) -> 0 | L23: =IF(L$15>$D23,$D23-$C23,IF(AND($C23<L$15,L$15<$D23),L$15-$C23,IF(L$15=$D23,$D23-$C23,0))) -> 3000 | M23: =IF(M$15>$D23,$D23-$C23,IF(AND($C23<M$15,M$15<$D23),M$15-$C23,IF(M$15=$D23,$D23-$C23,0))) -> 3000 | ... W23: =IF(W$15>$D23,$D23-$C23,IF(AND($C23<W$15,W$15<$D23),W$15-$C23,IF(W$15=$D23,$D23-$C23,0))) -> 0
C24: =D23 -> 9000 | D24: 12000 | F24: =IF(F$15>$D24,$D24-$C24,IF(AND($C24<F$15,F$15<$D24),F$15-$C24,IF(F$15=$D24,$D24-$C24,0))) -> 0 | G24: =IF(G$15>$D24,$D24-$C24,IF(AND($C24<G$15,G$15<$D24),G$15-$C24,IF(G$15=$D24,$D24-$C24,0))) -> 0 | H24: =IF(H$15>$D24,$D24-$C24,IF(AND($C24<H$15,H$15<$D24),H$15-$C24,IF(H$15=$D24,$D24-$C24,0))) -> 0 | I24: =IF(I$15>$D24,$D24-$C24,IF(AND($C24<I$15,I$15<$D24),I$15-$C24,IF(I$15=$D24,$D24-$C24,0))) -> 0 | J24: =IF(J$15>$D24,$D24-$C24,IF(AND($C24<J$15,J$15<$D24),J$15-$C24,IF(J$15=$D24,$D24-$C24,0))) -> 0 | K24: =IF(K$15>$D24,$D24-$C24,IF(AND($C24<K$15,K$15<$D24),K$15-$C24,IF(K$15=$D24,$D24-$C24,0))) -> 0 | L24: =IF(L$15>$D24,$D24-$C24,IF(AND($C24<L$15,L$15<$D24),L$15-$C24,IF(L$15=$D24,$D24-$C24,0))) -> 3000 | M24: =IF(M$15>$D24,$D24-$C24,IF(AND($C24<M$15,M$15<$D24),M$15-$C24,IF(M$15=$D24,$D24-$C24,0))) -> 3000 | ... W24: =IF(W$15>$D24,$D24-$C24,IF(AND($C24<W$15,W$15<$D24),W$15-$C24,IF(W$15=$D24,$D24-$C24,0))) -> 0
C25: =D24 -> 12000 | D25: 15000 | F25: =IF(F$15>$D25,$D25-$C25,IF(AND($C25<F$15,F$15<$D25),F$15-$C25,IF(F$15=$D25,$D25-$C25,0))) -> 0 | G25: =IF(G$15>$D25,$D25-$C25,IF(AND($C25<G$15,G$15<$D25),G$15-$C25,IF(G$15=$D25,$D25-$C25,0))) -> 0 | H25: =IF(H$15>$D25,$D25-$C25,IF(AND($C25<H$15,H$15<$D25),H$15-$C25,IF(H$15=$D25,$D25-$C25,0))) -> 0 | I25: =IF(I$15>$D25,$D25-$C25,IF(AND($C25<I$15,I$15<$D25),I$15-$C25,IF(I$15=$D25,$D25-$C25,0))) -> 0 | J25: =IF(J$15>$D25,$D25-$C25,IF(AND($C25<J$15,J$15<$D25),J$15-$C25,IF(J$15=$D25,$D25-$C25,0))) -> 0 | K25: =IF(K$15>$D25,$D25-$C25,IF(AND($C25<K$15,K$15<$D25),K$15-$C25,IF(K$15=$D25,$D25-$C25,0))) -> 0 | L25: =IF(L$15>$D25,$D25-$C25,IF(AND($C25<L$15,L$15<$D25),L$15-$C25,IF(L$15=$D25,$D25-$C25,0))) -> 3000 | M25: =IF(M$15>$D25,$D25-$C25,IF(AND($C25<M$15,M$15<$D25),M$15-$C25,IF(M$15=$D25,$D25-$C25,0))) -> 3000 | ... W25: =IF(W$15>$D25,$D25-$C25,IF(AND($C25<W$15,W$15<$D25),W$15-$C25,IF(W$15=$D25,$D25-$C25,0))) -> 0
C26: =D25 -> 15000 | D26: 200000 | F26: =IF(F$15>$D26,$D26-$C26,IF(AND($C26<F$15,F$15<$D26),F$15-$C26,IF(F$15>$C26,F$15-$C26,IF(F$15=$D26,$D26-$C26,0)))) -> 0 | G26: =IF(G$15>$D26,$D26-$C26,IF(AND($C26<G$15,G$15<$D26),G$15-$C26,IF(G$15>$C26,G$15-$C26,IF(G$15=$D26,$D26-$C26,0)))) -> 0 | H26: =IF(H$15>$D26,$D26-$C26,IF(AND($C26<H$15,H$15<$D26),H$15-$C26,IF(H$15>$C26,H$15-$C26,IF(H$15=$D26,$D26-$C26,0)))) -> 0 | I26: =IF(I$15>$D26,$D26-$C26,IF(AND($C26<I$15,I$15<$D26),I$15-$C26,IF(I$15>$C26,I$15-$C26,IF(I$15=$D26,$D26-$C26,0)))) -> 0 | J26: =IF(J$15>$D26,$D26-$C26,IF(AND($C26<J$15,J$15<$D26),J$15-$C26,IF(J$15>$C26,J$15-$C26,IF(J$15=$D26,$D26-$C26,0)))) -> 0 | K26: =IF(K$15>$D26,$D26-$C26,IF(AND($C26<K$15,K$15<$D26),K$15-$C26,IF(K$15>$C26,K$15-$C26,IF(K$15=$D26,$D26-$C26,0)))) -> 0 | L26: =IF(L$15>$D26,$D26-$C26,IF(AND($C26<L$15,L$15<$D26),L$15-$C26,IF(L$15>$C26,L$15-$C26,IF(L$15=$D26,$D26-$C26,0)))) -> 10394 | M26: =IF(M$15>$D26,$D26-$C26,IF(AND($C26<M$15,M$15<$D26),M$15-$C26,IF(M$15>$C26,M$15-$C26,IF(M$15=$D26,$D26-$C26,0)))) -> 8403 | ... W26: =IF(W$15>$D26,$D26-$C26,IF(AND($C26<W$15,W$15<$D26),W$15-$C26,IF(W$15>$C26,W$15-$C26,IF(W$15=$D26,$D26-$C26,0)))) -> 0
F27: =F9 -> 0 | G27: =G9 -> 0 | H27: =H9 -> 0 | I27: =I9 -> 0 | J27: =J9 -> 0 | K27: =K9 -> 0 | L27: =L9 -> 47063 | M27: =M9 -> 43318 | ... W27: =W9 -> 0
C28: Rangos Llamadas | F28: Llamadas
C29: 0 | D29: 4000 | F29: =IF(F$27>$D29,$D29-$C29,IF(AND($C29<F$27,F$27<$D29),F$27-$C29,IF(F$27=$D29,$D29-$C29,0))) -> 0 | G29: =IF(G$27>$D29,$D29-$C29,IF(AND($C29<G$27,G$27<$D29),G$27-$C29,IF(G$27=$D29,$D29-$C29,0))) -> 0 | H29: =IF(H$27>$D29,$D29-$C29,IF(AND($C29<H$27,H$27<$D29),H$27-$C29,IF(H$27=$D29,$D29-$C29,0))) -> 0 | I29: =IF(I$27>$D29,$D29-$C29,IF(AND($C29<I$27,I$27<$D29),I$27-$C29,IF(I$27=$D29,$D29-$C29,0))) -> 0 | J29: =IF(J$27>$D29,$D29-$C29,IF(AND($C29<J$27,J$27<$D29),J$27-$C29,IF(J$27=$D29,$D29-$C29,0))) -> 0 | K29: =IF(K$27>$D29,$D29-$C29,IF(AND($C29<K$27,K$27<$D29),K$27-$C29,IF(K$27=$D29,$D29-$C29,0))) -> 0 | L29: =IF(L$27>$D29,$D29-$C29,IF(AND($C29<L$27,L$27<$D29),L$27-$C29,IF(L$27=$D29,$D29-$C29,0))) -> 4000 | M29: =IF(M$27>$D29,$D29-$C29,IF(AND($C29<M$27,M$27<$D29),M$27-$C29,IF(M$27=$D29,$D29-$C29,0))) -> 4000 | ... W29: =IF(W$27>$D29,$D29-$C29,IF(AND($C29<W$27,W$27<$D29),W$27-$C29,IF(W$27=$D29,$D29-$C29,0))) -> 0
C30: =D29 -> 4000 | D30: 20000 | F30: =IF(F$27>$D30,$D30-$C30,IF(AND($C30<F$27,F$27<$D30),F$27-$C30,IF(F$27=$D30,$D30-$C30,0))) -> 0 | G30: =IF(G$27>$D30,$D30-$C30,IF(AND($C30<G$27,G$27<$D30),G$27-$C30,IF(G$27=$D30,$D30-$C30,0))) -> 0 | H30: =IF(H$27>$D30,$D30-$C30,IF(AND($C30<H$27,H$27<$D30),H$27-$C30,IF(H$27=$D30,$D30-$C30,0))) -> 0 | I30: =IF(I$27>$D30,$D30-$C30,IF(AND($C30<I$27,I$27<$D30),I$27-$C30,IF(I$27=$D30,$D30-$C30,0))) -> 0 | J30: =IF(J$27>$D30,$D30-$C30,IF(AND($C30<J$27,J$27<$D30),J$27-$C30,IF(J$27=$D30,$D30-$C30,0))) -> 0 | K30: =IF(K$27>$D30,$D30-$C30,IF(AND($C30<K$27,K$27<$D30),K$27-$C30,IF(K$27=$D30,$D30-$C30,0))) -> 0 | L30: =IF(L$27>$D30,$D30-$C30,IF(AND($C30<L$27,L$27<$D30),L$27-$C30,IF(L$27=$D30,$D30-$C30,0))) -> 16000 | M30: =IF(M$27>$D30,$D30-$C30,IF(AND($C30<M$27,M$27<$D30),M$27-$C30,IF(M$27=$D30,$D30-$C30,0))) -> 16000 | ... W30: =IF(W$27>$D30,$D30-$C30,IF(AND($C30<W$27,W$27<$D30),W$27-$C30,IF(W$27=$D30,$D30-$C30,0))) -> 0
C31: =D30 -> 20000 | D31: 200000 | F31: =IF(F$27>$D31,$D31-$C31,IF(AND($C31<F$27,F$27<$D31),F$27-$C31,IF(F$27>$C31,F$27-$C31,IF(F$27=$D31,$D31-$C31,0)))) -> 0 | J31: =IF(J$27>$D31,$D31-$C31,IF(AND($C31<J$27,J$27<$D31),J$27-$C31,IF(J$27>$C31,J$27-$C31,IF(J$27=$D31,$D31-$C31,0)))) -> 0 | K31: =IF(K$27>$D31,$D31-$C31,IF(AND($C31<K$27,K$27<$D31),K$27-$C31,IF(K$27>$C31,K$27-$C31,IF(K$27=$D31,$D31-$C31,0)))) -> 0 | L31: =IF(L$27>$D31,$D31-$C31,IF(AND($C31<L$27,L$27<$D31),L$27-$C31,IF(L$27>$C31,L$27-$C31,IF(L$27=$D31,$D31-$C31,0)))) -> 27063 | M31: =IF(M$27>$D31,$D31-$C31,IF(AND($C31<M$27,M$27<$D31),M$27-$C31,IF(M$27>$C31,M$27-$C31,IF(M$27=$D31,$D31-$C31,0)))) -> 23318 | N31: =IF(N$27>$D31,$D31-$C31,IF(AND($C31<N$27,N$27<$D31),N$27-$C31,IF(N$27>$C31,N$27-$C31,IF(N$27=$D31,$D31-$C31,0)))) -> 26180 | O31: =IF(O$27>$D31,$D31-$C31,IF(AND($C31<O$27,O$27<$D31),O$27-$C31,IF(O$27>$C31,O$27-$C31,IF(O$27=$D31,$D31-$C31,0)))) -> 15777 | P31: =IF(P$27>$D31,$D31-$C31,IF(AND($C31<P$27,P$27<$D31),P$27-$C31,IF(P$27>$C31,P$27-$C31,IF(P$27=$D31,$D31-$C31,0)))) -> 29883 | Q31: =IF(Q$27>$D31,$D31-$C31,IF(AND($C31<Q$27,Q$27<$D31),Q$27-$C31,IF(Q$27>$C31,Q$27-$C31,IF(Q$27=$D31,$D31-$C31,0)))) -> 29084 | ... W31: =IF(W$27>$D31,$D31-$C31,IF(AND($C31<W$27,W$27<$D31),W$27-$C31,IF(W$27>$C31,W$27-$C31,IF(W$27=$D31,$D31-$C31,0)))) -> 0
C33: Precio Unitario por Servicios Concluidos | F33: Llamadas
D34: =+IFERROR(SUM(L37:L46)/L8,0) -> 5.7601639 | F34: =IF(F$31<50,0,$D34)*F$31 -> 0 | G34: =IF(G$31<50,0,$D34)*G$31 -> 0 | H34: =IF(H$31<50,0,$D34)*H$31 -> 0 | I34: =IF(I$31<50,0,$D34)*I$31 -> 0 | J34: =IF(J$31<50,0,$D34)*J$31 -> 0 | K34: =IF(K$31<50,0,$D34)*K$31 -> 0 | L34: =+IFERROR(D34*L8,0) -> 146273.6 | M34: =+IFERROR(D34*M8,0) -> 134805.12 | N34: =+IFERROR(D34*N8,0) -> 160466.65 | O34: =+IFERROR(D34*O8,0) -> 156100.44 | P34: =+IFERROR(D34*P8,0) -> 151699.68 | Q34: =+IFERROR(D34*Q8,0) -> 178398.04 | R34: =+IFERROR(D34*R8,0) -> 165155.42 | S34: =+IFERROR(D34*S8,0) -> 167321.24 | T34: =+IFERROR(D34*T8,0) -> 182464.71 | U34: =+IFERROR(D34*U8,0) -> 189221.38 | V34: =+IFERROR(N34*V8,0) -> 0 | W34: =+IFERROR(O34*W8,0) -> 0
B36: VALORES EN USD | C36: Precios Servicios Concluidos | F36: Servicios concluidos
D37: 3434 | F37: =IF(F$17<1,0,$D$37) -> 0 | G37: =IF(G$17<1,0,$D$37) -> 0 | H37: =IF(H$17<1,0,$D$37) -> 0 | I37: =IF(I$17<1,0,$D$37) -> 0 | J37: =IF(J$17<1,0,$D$37) -> 0 | K37: =IF(K$17<1,0,$D$37) -> 0 | L37: =IF(L$17<1,0,$D$37) -> 3434 | M37: =IF(M$17<1,0,$D$37) -> 3434 | ... W37: =IF(W$17<1,0,$D$37) -> 0
D38: =10.5145425*X5 -> 11.513424 | F38: =IF(F$18=0,0,$D38)*F$18 -> 0 | G38: =IF(G$18=0,0,$D38)*G$18 -> 0 | H38: =IF(H$18=0,0,$D38)*H$18 -> 0 | I38: =IF(I$18=0,0,$D38)*I$18 -> 0 | J38: =IF(J$18=0,0,$D38)*J$18 -> 0 | K38: =IF(K$18=0,0,$D38)*K$18 -> 0 | L38: =IF(L$18=0,0,$D38)*L$18 -> 5181.0408 | M38: =IF(M$18=0,0,$D38)*M$18 -> 5181.0408 | ... W38: =IF(W$18=0,0,$D38)*W$18 -> 0
D39: =9.2775375*X5 -> 10.158904 | F39: =IF(F$19=0,0,$D39)*F$19 -> 0 | G39: =IF(G$19=0,0,$D39)*G$19 -> 0 | H39: =IF(H$19=0,0,$D39)*H$19 -> 0 | I39: =IF(I$19=0,0,$D39)*I$19 -> 0 | J39: =IF(J$19=0,0,$D39)*J$19 -> 0 | K39: =IF(K$19=0,0,$D39)*K$19 -> 0 | L39: =IF(L$19=0,0,$D39)*L$19 -> 5079.4518 | M39: =IF(M$19=0,0,$D39)*M$19 -> 5079.4518 | ... W39: =IF(W$19=0,0,$D39)*W$19 -> 0
D40: =8.0405325*X5 -> 8.8043831 | F40: =IF(F$20=0,0,$D40)*F$20 -> 0 | G40: =IF(G$20=0,0,$D40)*G$20 -> 0 | H40: =IF(H$20=0,0,$D40)*H$20 -> 0 | I40: =IF(I$20=0,0,$D40)*I$20 -> 0 | J40: =IF(J$20=0,0,$D40)*J$20 -> 0 | K40: =IF(K$20=0,0,$D40)*K$20 -> 0 | L40: =IF(L$20=0,0,$D40)*L$20 -> 8804.3831 | M40: =IF(M$20=0,0,$D40)*M$20 -> 8804.3831 | ... W40: =IF(W$20=0,0,$D40)*W$20 -> 0
D41: =6.8035275*X5 -> 7.4498626 | F41: =IF(F$21=0,0,$D41)*F$21 -> 0 | G41: =IF(G$21=0,0,$D41)*G$21 -> 0 | H41: =IF(H$21=0,0,$D41)*H$21 -> 0 | I41: =IF(I$21=0,0,$D41)*I$21 -> 0 | J41: =IF(J$21=0,0,$D41)*J$21 -> 0 | K41: =IF(K$21=0,0,$D41)*K$21 -> 0 | L41: =IF(L$21=0,0,$D41)*L$21 -> 7449.8626 | M41: =IF(M$21=0,0,$D41)*M$21 -> 7449.8626 | ... W41: =IF(W$21=0,0,$D41)*W$21 -> 0
D42: =5.5665225*X5 -> 6.0953421 | F42: =IF(F$22=0,0,$D42)*F$22 -> 0 | G42: =IF(G$22=0,0,$D42)*G$22 -> 0 | H42: =IF(H$22=0,0,$D42)*H$22 -> 0 | I42: =IF(I$22=0,0,$D42)*I$22 -> 0 | J42: =IF(J$22=0,0,$D42)*J$22 -> 0 | K42: =IF(K$22=0,0,$D42)*K$22 -> 0 | L42: =IF(L$22=0,0,$D42)*L$22 -> 18286.026 | M42: =IF(M$22=0,0,$D42)*M$22 -> 18286.026 | ... W42: =IF(W$22=0,0,$D42)*W$22 -> 0
D43: =5.25727125*X5 -> 5.756712 | F43: =IF(F$23=0,0,$D43)*F$23 -> 0 | G43: =IF(G$23=0,0,$D43)*G$23 -> 0 | H43: =IF(H$23=0,0,$D43)*H$23 -> 0 | I43: =IF(I$23=0,0,$D43)*I$23 -> 0 | J43: =IF(J$23=0,0,$D43)*J$23 -> 0 | K43: =IF(K$23=0,0,$D43)*K$23 -> 0 | L43: =IF(L$23=0,0,$D43)*L$23 -> 17270.136 | M43: =IF(M$23=0,0,$D43)*M$23 -> 17270.136 | ... W43: =IF(W$23=0,0,$D43)*W$23 -> 0
D44: =4.94802*X5 -> 5.4180819 | F44: =IF(F$24=0,0,$D44)*F$24 -> 0 | G44: =IF(G$24=0,0,$D44)*G$24 -> 0 | H44: =IF(H$24=0,0,$D44)*H$24 -> 0 | I44: =IF(I$24=0,0,$D44)*I$24 -> 0 | J44: =IF(J$24=0,0,$D44)*J$24 -> 0 | K44: =IF(K$24=0,0,$D44)*K$24 -> 0 | L44: =IF(L$24=0,0,$D44)*L$24 -> 16254.246 | M44: =IF(M$24=0,0,$D44)*M$24 -> 16254.246 | ... W44: =IF(W$24=0,0,$D44)*W$24 -> 0
D45: =4.63876875*X5 -> 5.0794518 | F45: =IF(F$25=0,0,$D45)*F$25 -> 0 | G45: =IF(G$25=0,0,$D45)*G$25 -> 0 | H45: =IF(H$25=0,0,$D45)*H$25 -> 0 | I45: =IF(I$25=0,0,$D45)*I$25 -> 0 | J45: =IF(J$25=0,0,$D45)*J$25 -> 0 | K45: =IF(K$25=0,0,$D45)*K$25 -> 0 | L45: =IF(L$25=0,0,$D45)*L$25 -> 15238.355 | M45: =IF(M$25=0,0,$D45)*M$25 -> 15238.355 | ... W45: =IF(W$25=0,0,$D45)*W$25 -> 0
D46: =4.3295175*X5 -> 4.7408217 | F46: =IF(F$26=0,0,$D46)*F$26 -> 0 | G46: =IF(G$26=0,0,$D46)*G$26 -> 0 | H46: =IF(H$26=0,0,$D46)*H$26 -> 0 | I46: =IF(I$26=0,0,$D46)*I$26 -> 0 | J46: =IF(J$26=0,0,$D46)*J$26 -> 0 | K46: =IF(K$26=0,0,$D46)*K$26 -> 0 | L46: =IF(L$26=0,0,$D46)*L$26 -> 49276.1 | M46: =IF(M$26=0,0,$D46)*M$26 -> 39837.124 | ... W46: =IF(W$26=0,0,$D46)*W$26 -> 0
C48: Precios Llamadas | F48: Llamadas
D49: =0.80405325*X5 -> 0.88043831 | F49: =IF(F$29<50,0,$D49)*F$29 -> 0 | G49: =IF(G$29<50,0,$D49)*G$29 -> 0 | H49: =IF(H$29<50,0,$D49)*H$29 -> 0 | I49: =IF(I$29<50,0,$D49)*I$29 -> 0 | J49: =IF(J$29<50,0,$D49)*J$29 -> 0 | K49: =IF(K$29<50,0,$D49)*K$29 -> 0 | L49: =IF(L$29<50,0,$D49)*L$29 -> 3521.7532 | M49: =IF(M$29<50,0,$D49)*M$29 -> 3521.7532 | ... W49: =IF(W$29<50,0,$D49)*W$29 -> 0
D50: =0.3711015*X5 -> 0.40635614 | F50: =IF(F$30=0,0,$D50)*F$30 -> 0 | G50: =IF(G$30=0,0,$D50)*G$30 -> 0 | H50: =IF(H$30=0,0,$D50)*H$30 -> 0 | I50: =IF(I$30=0,0,$D50)*I$30 -> 0 | J50: =IF(J$30=0,0,$D50)*J$30 -> 0 | K50: =IF(K$30=0,0,$D50)*K$30 -> 0 | L50: =IF(L$30=0,0,$D50)*L$30 -> 6501.6983 | M50: =IF(M$30=0,0,$D50)*M$30 -> 6501.6983 | ... W50: =IF(W$30=0,0,$D50)*W$30 -> 0
D51: =0.18555075*X5 -> 0.20317807 | F51: =IF(F$31=0,0,$D51)*F$31 -> 0 | G51: =IF(G$31=0,0,$D51)*G$31 -> 0 | H51: =IF(H$31=0,0,$D51)*H$31 -> 0 | I51: =IF(I$31=0,0,$D51)*I$31 -> 0 | J51: =IF(J$31=0,0,$D51)*J$31 -> 0 | K51: =IF(K$31=0,0,$D51)*K$31 -> 0 | L51: =IF(L$31=0,0,$D51)*L$31 -> 5498.6081 | M51: =IF(M$31=0,0,$D51)*M$31 -> 4737.7063 | ... W51: =IF(W$31=0,0,$D51)*W$31 -> 0
C53: Servicios Cancelados Posterior | F53: Llamadas
D54: =2.47*X5 -> 2.70465 | F54: =IF(F$31<50,0,$D54)*F$31 -> 0 | G54: =IF(G$31<50,0,$D54)*G$31 -> 0 | H54: =IF(H$31<50,0,$D54)*H$31 -> 0 | I54: =IF(I$31<50,0,$D54)*I$31 -> 0 | J54: =IF(J$31<50,0,$D54)*J$31 -> 0 | K54: =IF(K$31<50,0,$D54)*K$31 -> 0 | L54: =+L10*$D$54 -> 19373.408 | M54: =+M10*$D$54 -> 19770.992 | N54: =+N10*$D$54 -> 19148.922 | O54: =+O10*$D$54 -> 20257.828 | P54: =+P10*$D$54 -> 19102.943 | Q54: =+Q10*$D$54 -> 15995.3 | R54: =+R10*$D$54 -> 10380.447 | S54: =+S10*$D$54 -> 10085.64 | ... W54: =+W10*$D$54 -> 0
B58: Tipo de cobro usd | D58: Servicios Concluidos | F58: =SUM(F37:F46) -> 0 | G58: =SUM(G37:G46) -> 0 | H58: =SUM(H37:H46) -> 0 | I58: =SUM(I37:I46) -> 0 | J58: =SUM(J37:J46) -> 0 | K58: =SUM(K37:K46) -> 0 | L58: =SUM(L37:L46) -> 146273.6 | M58: =SUM(M37:M46) -> 136834.63 | ... W58: =SUM(W37:W46) -> 0
D59: Total de llamadas Validas | F59: =SUM(F49:F51) -> 0 | G59: =SUM(G49:G51) -> 0 | H59: =SUM(H49:H51) -> 0 | I59: =SUM(I49:I51) -> 0 | J59: =SUM(J49:J51) -> 0 | K59: =SUM(K49:K51) -> 0 | L59: =SUM(L49:L51) -> 15522.06 | M59: =SUM(M49:M51) -> 14761.158 | ... W59: =SUM(W49:W51) -> 0
D60: Servicios Cancelados Posterior | F60: =F10*2*1.05 -> 0 | G60: =G10*2*1.05 -> 0 | H60: =H10*2*1.05 -> 0 | I60: =I10*2*1.05 -> 0 | J60: =J10*2*1.05 -> 0 | K60: =K10*2*1.05 -> 0 | L60: =+L54 -> 19373.408 | M60: =+M54 -> 19770.992 | N60: =+N54 -> 19148.922 | O60: =+O54 -> 20257.828 | P60: =+P54 -> 19102.943 | Q60: =+Q54 -> 15995.3 | R60: =+R54 -> 10380.447 | S60: =+S54 -> 10085.64 | ... W60: =+W54 -> 0
D61: Total usd | F61: =SUM(F58:F60) -> 0 | G61: =SUM(G58:G60) -> 0 | H61: =SUM(H58:H60) -> 0 | I61: =SUM(I58:I60) -> 0 | J61: =SUM(J58:J60) -> 0 | K61: =SUM(K58:K60) -> 0 | L61: =SUM(L58:L60) -> 181169.07 | M61: =SUM(M58:M60) -> 171366.78 | ... W61: =SUM(W58:W60) -> 0
F66: #REF! | G66: #REF! | H66: #REF! | I66: #REF! | J66: #REF! | K66: #REF! | L66: #REF! | M66: #REF! | N66: #REF! | O66: #REF! | P66: #REF! | Q66: #REF! | R66: #REF! | S66: #REF! | T66: #REF! | U66: #REF! | V66: #REF! | W66: #REF!

Sheet Indicadores INC
B3: REPORTE EJECUTIVO OPERACIÓN VOCCARE 2025
B5: Filial | D5: PUERTO RICO | P5: PUERTO RICO
B7: TIPO DE CAMBIO USD $ | D7: 1
B9: MES | D9: 45292 | E9: 45323 | F9: 45352 | G9: 45383 | H9: 45413 | I9: 45444 | J9: 45474 | K9: 45505 | L9: 45536 | M9: 45566 | N9: 45597 | O9: 45627 | P9: 45658 | Q9: 45689 | R9: 45717 | S9: 45748 | T9: 45778 | U9: 45809 | V9: 45839 | W9: 45870 | X9: 45901 | Y9: 45931 | Z9: 45962 | AA9: 45992 | AC9: Acumulados | AD9: Promedio
B11: MODULO CARTERA EN RIESGO
B12: Cartera en Riesgo | D12: =SUM([4]CUENTAS!D12:D37) -> 0 | E12: 0 | F12: =SUM([4]CUENTAS!F12:F37) -> 0 | G12: 0 | H12: 0 | I12: 0 | J12: 0 | K12: 0 | L12: 0 | M12: 0 | N12: 0 | O12: 0 | P12: 0 | Q12: 0 | R12: 0 | S12: 0 | T12: 0 | U12: 0 | V12: 0 | W12: 0 | X12: 0 | Y12: 0 | AC12: =SUM(P12:AA12) -> 0 | AD12: =IFERROR(AC12/(COUNT(P12:AA12)),0) -> 0
B13: Ingresos del Mes Técnico | D13: =SUM([4]CUENTAS!D68:D121) -> 0 | E13: 0 | F13: =SUM([4]CUENTAS!F68:F121) -> 0 | G13: 0 | H13: 0 | I13: 0 | J13: 0 | K13: 0 | L13: USD 0 | M13: 0 | N13: 0 | O13: 0 | P13: 0 | Q13: 0 | R13: 0 | S13: 0 | T13: 0 | U13: 0 | V13: 0 | W13: 0 | X13: 0 | Y13: 0 | AC13: =SUM(P13:AA13) -> 0 | AD13: =IFERROR(AC13/(COUNT(P13:AA13)),0) -> 0
B14: Ingreso / Afiliado | D14: =IFERROR(D13/D12,0) -> 0 | E14: 0 | F14: =IFERROR(F13/F12,0) -> 0 | G14: 0 | H14: 0 | I14: 0 | J14: 0 | K14: 0 | L14: USD 0,00 | M14: 0 | N14: 0 | O14: 0 | P14: 0 | Q14: 0 | R14: 0 | S14: 0 | T14: 0 | U14: 0 | V14: 0 | W14: 0 | X14: 0 | Y14: 0 | AC14: =SUM(P14:AA14) -> 0 | AD14: =IFERROR(AC14/(COUNT(P14:AA14)),0) -> 0
B15: COMPORTAMIENTO DE SERVICIOS
B16: Total de Asistencia Solicitadas | D16: 5294 | E16: 5225 | F16: 5453 | G16: 5763 | H16: 6101 | I16: 5808 | J16: 5725 | K16: 5882 | L16: 5752 | M16: 6188 | N16: 6045 | O16: 6110 | P16: 5669 | Q16: 5121 | R16: 5756 | S16: 5645 | T16: 5739 | U16: 5686 | V16: 5748 | W16: 6118 | X16: 5837 | Y16: 6081 | AC16: =SUM(P16:AA16) -> 57400 | AD16: =IFERROR(AC16/(COUNT(P16:AA16)),0) -> 5740
B17: Total Servicios Concluidos (C) | D17: 3684 | E17: 3636 | F17: 3811 | G17: 4047 | H17: 4210 | I17: 3973 | J17: 3854 | K17: 4093 | L17: 3877 | M17: 4385 | N17: 4242 | O17: 4316 | P17: 4031 | Q17: 3691 | R17: 4164 | S17: 4046 | T17: 4135 | U17: 4052 | V17: 4213 | W17: 4487 | X17: 4306 | Y17: 4613 | AC17: =SUM(P17:AA17) -> 41738 | AD17: =IFERROR(AC17/(COUNT(P17:AA17)),0) -> 4173.8
B18: % Servicios Concluidos | D18: 0.69588213 | E18: 0.69588517 | F18: 0.69888135 | G18: 0.70223842 | H18: 0.69005081 | I18: 0.68405647 | J18: 0.67318777 | K18: 0.69585175 | L18: 0.674 | M18: 0.70862961 | N18: 0.70173697 | O18: 0.70638298 | P18: 0.71106015 | Q18: 0.72075766 | R18: 0.72341904 | S18: 0.71674048 | T18: 0.7205088 | U18: 0.71262751 | V18: 0.73295059 | W18: 0.73340961 | X18: 0.73770773 | Y18: 0.75859234 | AC18: =SUM(P18:AA18) -> 7.2677739 | AD18: =IFERROR(AC18/(COUNT(P18:AA18)),0) -> 0.72677739
B19: Servicios (C) con Costo | D19: 2507 | E19: 2505 | F19: 2715 | G19: 2735 | H19: 2949 | I19: 2755 | J19: 2652 | K19: 2772 | L19: 2666 | M19: 3011 | N19: 2865 | O19: 2907 | P19: 2796 | Q19: 2609 | R19: 2911 | S19: 2783 | T19: 2852 | U19: 2811 | V19: 2911 | W19: 3108 | X19: 2938 | Y19: 3196 | AC19: =SUM(P19:AA19) -> 28915 | AD19: =IFERROR(AC19/(COUNT(P19:AA19)),0) -> 2891.5
B20: Servicios (C) Locales | D20: 1504 | E20: 1285 | F20: 1572 | G20: 1607 | H20: 1495 | I20: 1615 | J20: 1342 | K20: 1582 | L20: 1557 | M20: 1787 | N20: 1649 | O20: 1664 | P20: 1670 | Q20: 1478 | R20: 1640 | S20: 1483 | T20: 1478 | U20: 1455 | V20: 1605 | W20: 1634 | X20: 1605 | Y20: 1666 | AC20: =SUM(P20:AA20) -> 15714 | AD20: =IFERROR(AC20/(COUNT(P20:AA20)),0) -> 1571.4
B21: Servicios (C) Foraneos | D21: 1003 | E21: 1037 | F21: 1143 | G21: 1128 | H21: 1246 | I21: 1140 | J21: 1144 | K21: 1190 | L21: 1109 | M21: 1224 | N21: 1216 | O21: 1243 | P21: 1126 | Q21: 1131 | R21: 1271 | S21: 1155 | T21: 1188 | U21: 1223 | V21: 1306 | W21: 1306 | X21: 1184 | Y21: 1304 | AC21: =SUM(P21:AA21) -> 12194 | AD21: =IFERROR(AC21/(COUNT(P21:AA21)),0) -> 1219.4
B22: Servicios (C) Adicionales | D22: 1447 | E22: 1414 | F22: 1343 | G22: 1591 | H22: 1598 | I22: 1541 | J22: 1527 | K22: 1598 | L22: 1535 | M22: 1705 | N22: 1681 | O22: 1719 | P22: 1523 | Q22: 1295 | R22: 1538 | S22: 1582 | T22: 1557 | U22: 1526 | V22: 1584 | W22: 1682 | X22: 1669 | Y22: 1679 | AC22: =SUM(P22:AA22) -> 15635 | AD22: =IFERROR(AC22/(COUNT(P22:AA22)),0) -> 1563.5
B23: Servicios (C) en Conexión | D23: 195 | E23: 206 | F23: 200 | G23: 201 | H23: 247 | I23: 168 | J23: 200 | K23: 382 | L23: 463 | M23: 427 | N23: 369 | O23: 407 | P23: 342 | Q23: 230 | R23: 187 | S23: 208 | T23: 224 | U23: 223 | V23: 252 | W23: 246 | X23: 241 | Y23: 191 | AC23: =SUM(P23:AA23) -> 2344 | AD23: =IFERROR(AC23/(COUNT(P23:AA23)),0) -> 234.4
B24: Servicios (C) por el CAT - Referencias | D24: 275 | E24: 266 | F24: 323 | G24: 284 | H24: 279 | I24: 250 | J24: 241 | K24: 189 | L24: 233 | M24: 225 | N24: 206 | O24: 194 | P24: 204 | Q24: 173 | R24: 182 | S24: 210 | T24: 254 | U24: 177 | V24: 195 | W24: 223 | X24: 194 | Y24: 288 | AC24: =SUM(P24:AA24) -> 2100 | AD24: =IFERROR(AC24/(COUNT(P24:AA24)),0) -> 210
B25: Servicios (C) por Internos | D25: 2 | E25: 5 | F25: 2 | G25: 2 | H25: 285 | I25: 280 | J25: 333 | K25: 296 | L25: 278 | M25: 346 | N25: 345 | O25: 317 | P25: 343 | Q25: 324 | R25: 350 | S25: 321 | T25: 306 | U25: 351 | V25: 328 | W25: 400 | X25: 329 | Y25: 384 | AC25: =SUM(P25:AA25) -> 3436 | AD25: =IFERROR(AC25/(COUNT(P25:AA25)),0) -> 343.6
B26: Servicios (C) por Externos | D26: 129 | E26: 141 | F26: 156 | G26: 137 | H26: 2441 | I26: 2267 | J26: 2123 | K26: 2302 | L26: 2199 | M26: 2453 | N26: 2318 | O26: 2406 | P26: 2174 | Q26: 2023 | R26: 2239 | S26: 2128 | T26: 2183 | U26: 1939 | V26: 1946 | W26: 2060 | X26: 2035 | Y26: 2127 | AC26: =SUM(P26:AA26) -> 20854 | AD26: =IFERROR(AC26/(COUNT(P26:AA26)),0) -> 2085.4
B27: Servicios Cancelado Posterior (CP) | D27: 653 | E27: 704 | F27: 721 | G27: 748 | H27: 848 | I27: 828 | J27: 839 | K27: 744 | L27: 783 | M27: 759 | N27: 839 | O27: 812 | P27: 764 | Q27: 700 | R27: 739 | S27: 758 | T27: 746 | U27: 787 | V27: 686 | W27: 772 | X27: 710 | Y27: 695 | AC27: =SUM(P27:AA27) -> 7357 | AD27: =IFERROR(AC27/(COUNT(P27:AA27)),0) -> 735.7
... B30: % Servicios Cancelado al Momento | D30: 0.18077068 | E30: 0.16937799 | F30: 0.16889785 | G30: 0.16796807 | H30: 0.17095558 | I30: 0.17338154 | J30: 0.18026201 | K30: 0.17766066 | L30: 0.19 | M30: 0.16871364 | N30: 0.15947064 | O30: 0.16072013 | P30: 0.15417181 | Q30: 0.14255028 | R30: 0.14819319 | S30: 0.1489814 | T30: 0.1495034 | U30: 0.14896236 | V30: 0.14770355 | W30: 0.14040536 | X30: 0.14065445 | Y30: 0.12711725 | AC30: =SUM(P30:AA30) -> 1.4482431 | AD30: =IFERROR(AC30/(COUNT(P30:AA30)),0) -> 0.14482431
B31: COMPORTAMIENTO DE SINIESTRALIDAD
B32: Costo Siniestralidad Serv. (C) - Locales | D32: 55155.11 | E32: 52630.3 | F32: 58348.7 | G32: 60991.7 | H32: 63485.3 | I32: 61564.22 | J32: 58610.58 | K32: 75320 | L32: USD 63.827 | M32: 73816 | N32: 73166.7 | O32: 69469.34 | P32: 68609.6 | Q32: 61328.48 | R32: 66680.18 | S32: 67667.2 | T32: 67729.5 | U32: 65232.18 | V32: 63037.05 | W32: 70181.05 | X32: 68971.2 | Y32: 76690.2 | AC32: =SUM(P32:AA32) -> 676126.64 | AD32: =IFERROR(AC32/(COUNT(P32:AA32)),0) -> 67612.664
B33: Costo Siniestralidad Serv. (C) - Foraneos | D33: 58162 | E33: 60416.45 | F33: 61153.2 | G33: 60612.1 | H33: 75126.3 | I33: 67856.1 | J33: 68306.79 | K33: 65193.2 | L33: USD 67.246 | M33: 71499.3 | N33: 65038.91 | O33: 72319.42 | P33: 69574.8 | Q33: 69479.57 | R33: 75085.8 | S33: 69477.9 | T33: 73179.91 | U33: 86074.08 | V33: 81291.13 | W33: 74380.02 | X33: 69776.93 | Y33: 84010.93 | AC33: =SUM(P33:AA33) -> 752331.07 | AD33: =IFERROR(AC33/(COUNT(P33:AA33)),0) -> 75233.107
B34: Costo Siniestralidad Internos | D34: 0 | E34: 0 | F34: 0 | G34: 0 | H34: 5206 | I34: 5797 | J34: 6233 | K34: 5796.6 | L34: USD 5.357 | M34: 6289 | N34: 6382 | O34: 5990 | P34: 5809 | Q34: 4630 | R34: 5153 | S34: 5498 | T34: 4812 | U34: 6406.5 | V34: 6869 | W34: 6155 | X34: 5391.5 | Y34: 9185.8 | AC34: =SUM(P34:AA34) -> 59909.8 | AD34: =IFERROR(AC34/(COUNT(P34:AA34)),0) -> 5990.98
B35: Costo Siniestralidad Externos | D35: 113317.11 | E35: 113046.75 | F35: 119501.9 | G35: 121603.8 | H35: 133405.6 | I35: 123623.32 | J35: 120684.37 | K35: 134716.6 | L35: USD 125.716 | M35: 139026.3 | N35: 131823.61 | O35: 135798.76 | P35: 132375.4 | Q35: 126178.05 | R35: 136612.98 | S35: 131647.1 | T35: 136097.41 | U35: 144899.76 | V35: 137459.18 | W35: 138406.07 | X35: 133356.63 | Y35: 151515.33 | AC35: =SUM(P35:AA35) -> 1368547.9 | AD35: =IFERROR(AC35/(COUNT(P35:AA35)),0) -> 136854.79
B36: Costo Siniestralidad Serv. (CP) | D36: 298.5 | E36: 1050 | F36: 2554.5 | G36: 2093.5 | H36: 1927 | I36: 1923 | J36: 1862 | K36: 1726.5 | L36: USD 1.960 | M36: 2234.5 | N36: 2573.9 | O36: 2346 | P36: 1987.2 | Q36: 1383 | R36: 1542.5 | S36: 2021.7 | T36: 2052.4 | U36: 1916.5 | V36: 2157 | W36: 1855.5 | X36: 1814 | Y36: 1946 | AC36: =SUM(P36:AA36) -> 18675.8 | AD36: =IFERROR(AC36/(COUNT(P36:AA36)),0) -> 1867.58
B37: Costo Siniestralidad Total | D37: 113615.61 | E37: 114096.75 | F37: 122056.4 | G37: 123697.3 | H37: 140538.6 | I37: 131343.32 | J37: 128779.37 | K37: 142239.7 | L37: USD 133.033 | M37: 147549.8 | N37: 140779.51 | O37: 144134.76 | P37: 140171.6 | Q37: 132191.05 | R37: 143308.48 | S37: 139166.8 | T37: 142961.81 | U37: 153222.76 | V37: 146485.18 | W37: 146416.57 | X37: 140562.13 | Y37: 162647.13 | AC37: =SUM(P37:AA37) -> 1447133.5 | AD37: =IFERROR(AC37/(COUNT(P37:AA37)),0) -> 144713.35
B38: LLAMADAS TOTALES
B39: Total de llamadas Validas | D39: 11819 | E39: 12222 | F39: 13024 | G39: 13644 | H39: 14490 | I39: 13272 | J39: 13605 | K39: 14494 | L39: 14012 | M39: 14950 | N39: 13261 | O39: 13701 | P39: 12011 | Q39: 11699 | R39: 13069 | S39: 13351 | T39: 13560 | U39: 12892 | V39: 13197 | W39: 13587 | X39: 13325 | Y39: 13781 | AC39: =SUM(P39:AA39) -> 130472 | AD39: =IFERROR(AC39/(COUNT(P39:AA39)),0) -> 13047.2
B40: Frecuencia Natural Llamadas Inbound, % | D40: 0 | E40: 0 | F40: 0 | G40: 0 | H40: 0 | I40: 0 | J40: 0 | K40: 0 | L40: 0 | M40: 0 | N40: 0 | O40: 0 | P40: 0 | Q40: 0 | R40: 0 | S40: 0 | T40: 0 | U40: 0 | V40: 0 | W40: 0 | X40: 0 | Y40: 0 | AC40: =SUM(P40:AA40) -> 0 | AD40: =IFERROR(AC40/(COUNT(P40:AA40)),0) -> 0
B41: Llamadas al CAT, % | D41: 0.97233268 | E41: 0.97291769 | F41: 0.971207 | G41: 0.9686309 | H41: 0.97073844 | I41: 0.9702381 | J41: 0.97375965 | K41: 0.97750793 | L41: 0.98 | M41: 0.96963211 | N41: 0.97149536 | O41: 0.97255675 | P41: 0.98259928 | Q41: 0.9769211 | R41: 0.97536154 | S41: 0.97827878 | T41: 0.975 | U41: 0.95314924 | V41: 0.95764189 | W41: 0.95768014 | X41: 0.96120075 | Y41: 0.96132356 | AC41: =SUM(P41:AA41) -> 9.6791563 | AD41: =IFERROR(AC41/(COUNT(P41:AA41)),0) -> 0.96791563
B42: LLAMADAS PROVEEDORES
B43: Total de llamadas validas Proveedores | D43: 327 | E43: 331 | F43: 375 | G43: 428 | H43: 424 | I43: 395 | J43: 357 | K43: 326 | L43: 349 | M43: 454 | N43: 378 | O43: 376 | P43: 209 | Q43: 270 | R43: 322 | S43: 290 | T43: 339 | U43: 604 | V43: 559 | W43: 575 | X43: 517 | Y43: 533 | AC43: =SUM(P43:AA43) -> 4218 | AD43: =IFERROR(AC43/(COUNT(P43:AA43)),0) -> 421.8
B44: Llamadas atendidas Proveedores | D44: 319 | E44: 323 | F44: 372 | G44: 421 | H44: 408 | AC44: =SUM(P44:AA44) -> 0 | AD44: =IFERROR(AC44/(COUNT(P44:AA44)),0) -> 0
B45: Tiempo promedio conversación Proveedores | D45: 1.54 | E45: 1.52 | F45: 1.56 | G45: 1.54 | H45: 1.58 | I45: 1.59 | J45: 2.05 | K45: 2.1 | L45: 1.51 | M45: 1.57 | N45: 1.53 | O45: 2.06 | P45: 1.54 | Q45: 1.47 | R45: 1.49 | S45: 2.19 | T45: 2 | U45: 2 | V45: 2.14 | W45: 2.1 | X45: 2.06 | Y45: 1.56 | AC45: =SUM(P45:AA45) -> 18.55 | AD45: =IFERROR(AC45/(COUNT(P45:AA45)),0) -> 1.855
B46: Llamadas atendidas < 15 seg. Proveedores | D46: 295 | E46: 306 | F46: 341 | G46: 363 | H46: 348 | I46: 290 | J46: 294 | K46: 258 | L46: 267 | M46: 342 | N46: 294 | O46: 323 | P46: 185 | Q46: 225 | R46: 291 | S46: 258 | T46: 288 | U46: 503 | V46: 495 | W46: 526 | X46: 460 | Y46: 469 | AC46: =SUM(P46:AA46) -> 3700 | AD46: =IFERROR(AC46/(COUNT(P46:AA46)),0) -> 370
B47: Abandonos mayores a 5 seg. Proveedores | D47: 7 | E47: 7 | F47: 3 | G47: 6 | H47: 14 | I47: 2 | J47: 16 | K47: 21 | L47: 18 | M47: 23 | N47: 18 | O47: 8 | P47: 5 | Q47: 8 | R47: 6 | S47: 2 | T47: 6 | U47: 13 | V47: 11 | W47: 4 | X47: 6 | Y47: 6 | AC47: =SUM(P47:AA47) -> 67 | AD47: =IFERROR(AC47/(COUNT(P47:AA47)),0) -> 6.7
B48: % Indice de abandono Proveedores | D48: 0.021406728 | E48: 0.0211 | F48: 0.008 | G48: 0.014018692 | H48: 0.033018868 | I48: 0.0050632911 | J48: 0.044817927 | K48: 0.06 | L48: 0.051575931 | M48: 0.050660793 | N48: 0.05 | O48: 0.02 | P48: 0.02 | Q48: 0.03 | R48: 0.01863354 | S48: 0.0068965517 | T48: 0.017699115 | U48: 0.021523179 | V48: 0.019677996 | W48: 0.0069565217 | X48: 0.011605416 | Y48: 0.011257036 | AC48: =SUM(P48:AA48) -> 0.16424936 | AD48: =IFERROR(AC48/(COUNT(P48:AA48)),0) -> 0.016424936
B49: Nivel de servicio < 15 seg. Proveedores | D49: 0.92476489 | E49: 0.95 | F49: 0.91666667 | G49: 0.86223278 | H49: 0.85294118 | I49: 0.73417722 | J49: 0.82352941 | K49: 0.79 | L49: 0.76504298 | M49: 0.75330396 | N49: 0.78 | O49: 0.89 | P49: 0.92 | Q49: 0.86 | R49: 0.93 | S49: 0.92 | T49: 0.88 | U49: 0.87 | V49: 0.92 | W49: 0.94 | X49: 0.93 | Y49: 0.93 | AC49: =SUM(P49:AA49) -> 9.1 | AD49: =IFERROR(AC49/(COUNT(P49:AA49)),0) -> 0.91
B50: LLAMADAS CABINA DE EMERGENCIA CLIENTE
B51: Total de llamadas validas Clientes CAT | D51: 11492 | E51: 11891 | F51: 12649 | G51: 13216 | H51: 14066 | I51: 12877 | J51: 13248 | K51: 14168 | L51: 13663 | M51: 14496 | N51: 12883 | O51: 13325 | P51: 11802 | Q51: 11429 | R51: 12747 | S51: 13061 | T51: 13221 | U51: 12288 | V51: 12638 | W51: 13012 | X51: 12808 | Y51: 13248 | AC51: =SUM(P51:AA51) -> 126254 | AD51: =IFERROR(AC51/(COUNT(P51:AA51)),0) -> 12625.4
B52: Llamadas atendidas Clientes CAT | D52: 11199 | E52: 11689 | F52: 12370 | G52: 12860 | H52: 13599 | AC52: =SUM(P52:AA52) -> 0 | AD52: =IFERROR(AC52/(COUNT(P52:AA52)),0) -> 0
B53: Tiempo promedio conversación Clientes CAT | D53: 3.05 | E53: 2.51 | F53: 2.5 | G53: 2.51 | H53: 2.48 | I53: 2.51 | J53: 2.55 | K53: 2.48 | L53: 2.51 | M53: 2.54 | N53: 2.57 | O53: 3.04 | P53: 3.03 | Q53: 3.1 | R53: 3.2 | S53: 3.15 | T53: 3.16 | U53: 3.08 | V53: 3.16 | W53: 3.24 | X53: 3.16 | Y53: 3.1 | AC53: =SUM(P53:AA53) -> 31.38 | AD53: =IFERROR(AC53/(COUNT(P53:AA53)),0) -> 3.138
B54: Llamadas atendidas < 15 seg. Cliente CAT | D54: 10314 | E54: 10801 | F54: 11272 | G54: 11229 | H54: 11376 | I54: 10492 | J54: 11428 | K54: 11455 | L54: 10681 | M54: 11343 | N54: 10262 | O54: 11362 | P54: 10132 | Q54: 9515 | R54: 11419 | S54: 11863 | T54: 11903 | U54: 10768 | V54: 11204 | W54: 10863 | X54: 11349 | Y54: 11859 | AC54: =SUM(P54:AA54) -> 110875 | AD54: =IFERROR(AC54/(COUNT(P54:AA54)),0) -> 11087.5
B55: Abandonos mayores a 5 seg. Clientes CAT | D55: 158 | E55: 133 | F55: 191 | G55: 304 | H55: 411 | I55: 405 | J55: 246 | K55: 626 | L55: 573 | M55: 367 | N55: 331 | O55: 184 | P55: 135 | Q55: 157 | R55: 196 | S55: 119 | T55: 139 | U55: 322 | V55: 174 | W55: 206 | X55: 75 | Y55: 145 | AC55: =SUM(P55:AA55) -> 1668 | AD55: =IFERROR(AC55/(COUNT(P55:AA55)),0) -> 166.8
B56: % Indice de abandono Clientes CAT | D56: 0.013748695 | E56: 0.0112 | F56: 0.015100008 | G56: 0.023002421 | H56: 0.029219394 | I56: 0.031451425 | J56: 0.018568841 | K56: 0.04 | L56: 0.041938081 | M56: 0.025317329 | N56: 0.03 | O56: 0.02 | P56: 0.01 | Q56: 0.01 | R56: 0.015376167 | S56: 0.0091110941 | T56: 0 | U56: 0.026204427 | V56: 0.013768001 | W56: 0.01583154 | X56: 0.0058557152 | Y56: 0.010945048 | AC56: =SUM(P56:AA56) -> 0.11709199 | AD56: =IFERROR(AC56/(COUNT(P56:AA56)),0) -> 0.011709199
B57: Nivel de servicio < 15 seg. Clientes CAT | D57: 0.92097509 | E57: 0.92 | F57: 0.91123686 | G57: 0.87317263 | H57: 0.8365321 | I57: 0.81478605 | J57: 0.86262077 | K57: 0.81 | L57: 0.78174632 | M57: 0.78249172 | N57: 0.8 | O57: 0.87 | P57: 0.88 | Q57: 0.86 | R57: 0.92 | S57: 0.92 | T57: 0.91 | U57: 0.89 | V57: 0.9 | W57: 0.86 | X57: 0.91 | Y57: 0.91 | AC57: =SUM(P57:AA57) -> 8.96 | AD57: =IFERROR(AC57/(COUNT(P57:AA57)),0) -> 0.896
B58: PRODUCTIVIDAD COORDINADORES CAT
B59: Dotacion de coordinadores efectivos | D59: 16 | E59: 16 | F59: 16 | G59: 16 | H59: 16 | I59: 16 | J59: 16 | K59: 16 | L59: 16 | M59: 16 | N59: 16 | O59: 16 | P59: 16 | Q59: 16 | R59: 16 | S59: 16 | T59: 16 | U59: 16 | V59: 16 | W59: 16 | X59: 16 | Y59: 16 | AC59: =SUM(P59:AA59) -> 160 | AD59: =IFERROR(AC59/(COUNT(P59:AA59)),0) -> 16
B60: Servicios solicitados X coordinador | D60: 330.875 | E60: 326.5625 | F60: 340.8125 | G60: 360.1875 | H60: 381.3125 | I60: 363 | J60: 357.8125 | K60: 367.625 | L60: 359.5 | M60: 386.75 | N60: 377.8125 | O60: 381.875 | P60: 354.3125 | Q60: 320.0625 | R60: 359.75 | S60: 352.8125 | T60: 358.6875 | U60: 355.375 | V60: 359.25 | W60: 382.375 | X60: 364.8125 | Y60: 380.0625 | AC60: =SUM(P60:AA60) -> 3587.5 | AD60: =IFERROR(AC60/(COUNT(P60:AA60)),0) -> 358.75
B61: Servicios concluidos X coordinador | D61: 230.25 | E61: 227.25 | F61: 238.1875 | G61: 252.9375 | H61: 263.125 | I61: 248.3125 | J61: 240.875 | K61: 255.8125 | L61: 242.3125 | M61: 274.0625 | N61: 265.125 | O61: 269.75 | P61: 251.9375 | Q61: 230.6875 | R61: 260.25 | S61: 252.875 | T61: 258.4375 | U61: 253.25 | V61: 263.3125 | W61: 280.4375 | X61: 269.125 | Y61: 288.3125 | AC61: =SUM(P61:AA61) -> 2608.625 | AD61: =IFERROR(AC61/(COUNT(P61:AA61)),0) -> 260.8625
B62: Llamadas atendidas X coordinador | D62: 719.875 | E62: 750.75 | F62: 796.375 | G62: 830.0625 | H62: 875.4375 | I62: 0 | J62: 0 | K62: 0 | L62: 0 | M62: 0 | N62: 0 | O62: 0 | P62: 0 | Q62: 0 | R62: 0 | S62: 0 | T62: 0 | U62: 0 | V62: 0 | W62: 0 | X62: 0 | Y62: 0 | AC62: =SUM(P62:AA62) -> 0 | AD62: =IFERROR(AC62/(COUNT(P62:AA62)),0) -> 0
B63: ATENCION DE LLAMADAS SAC
B64: Total de llamadas validas SAC | AC64: =SUM(P64:AA64) -> 0 | AD64: =IFERROR(AC64/(COUNT(P64:AA64)),0) -> 0
B65: Llamadas atendidas SAC | AC65: =SUM(P65:AA65) -> 0 | AD65: =IFERROR(AC65/(COUNT(P65:AA65)),0) -> 0
B66: Tiempo promedio conversación SAC | AC66: =SUM(P66:AA66) -> 0 | AD66: =IFERROR(AC66/(COUNT(P66:AA66)),0) -> 0
B67: Llamadas atendidas < 15 seg. SAC | AC67: =SUM(P67:AA67) -> 0 | AD67: =IFERROR(AC67/(COUNT(P67:AA67)),0) -> 0
B68: Abandonos mayores a 5 seg. SAC | AC68: =SUM(P68:AA68) -> 0 | AD68: =IFERROR(AC68/(COUNT(P68:AA68)),0) -> 0
B69: % Indice de abandono SAC | AC69: =SUM(P69:AA69) -> 0 | AD69: =IFERROR(AC69/(COUNT(P69:AA69)),0) -> 0
B70: Nivel de servicio < 15 seg. SAC | AC70: =SUM(P70:AA70) -> 0 | AD70: =IFERROR(AC70/(COUNT(P70:AA70)),0) -> 0
B71: PRODUCTIVIDAD AGENTES SAC
B72: Dotacion de agentes SAC efectivos | AC72: 0 | AD72: 0
B73: Llamadas atendidas X agente | AC73: 0 | AD73: 0
B74: SEGUIMIENTO LLAMADAS OUTBOUND
B75: Llamadas Outbound Afiliado | D75: 11222 | E75: 11871 | F75: 12249 | G75: 11452 | AC75: 0 | AD75: 0
B76: Lllamadas Outbound Proveedor | D76: 6480 | E76: 6429 | F76: 6319 | G76: 6559 | AC76: 0 | AD76: 0
B77: Llamadas Outbound Totales | D77: 17702 | E77: 18300 | F77: 18568 | G77: 18011 | H77: 10704 | I77: 9725 | J77: 9514 | K77: 9563 | L77: 8772 | M77: 9596 | N77: 8996 | O77: 9810 | P77: 10400 | Q77: 8832 | R77: 10193 | S77: 10126 | T77: 10816 | U77: 8650 | V77: 8698 | W77: 6934 | X77: 6555 | Y77: 8220 | AC77: 0 | AD77: 0
B78: RESULTADOS DE VARIABLES DEL MES
B79: % Frecuencia | D79: 0 | E79: 0 | F79: 0 | G79: 0 | H79: 0 | I79: 0 | J79: 0 | K79: 0 | L79: 0 | M79: 0 | N79: 0 | O79: 0 | P79: 0 | Q79: 0 | R79: 0 | S79: 0 | T79: 0 | U79: 0 | V79: 0 | W79: 0 | X79: 0 | Y79: 0 | AC79: =SUM(P79:AA79) -> 0
B80: % Frecuencia con Costo | D80: 0 | E80: 0 | F80: 0 | G80: 0 | H80: 0 | I80: 0 | J80: 0 | K80: 0 | L80: 0 | M80: 0 | N80: 0 | O80: 0 | P80: 0 | Q80: 0 | R80: 0 | S80: 0 | T80: 0 | U80: 0 | V80: 0 | W80: 0 | X80: 0 | Y80: 0 | AC80: =SUM(P80:AA80) -> 0
B81: % Siniestralidad Total | D81: 0 | E81: 0 | F81: 0 | G81: 0 | H81: 0 | I81: 0 | J81: 0 | K81: 0 | L81: 0 | M81: 0 | N81: 0 | O81: 0 | P81: 0 | Q81: 0 | R81: 0 | S81: 0 | T81: 0 | U81: 0 | V81: 0 | W81: 0 | X81: 0 | Y81: 0 | AC81: =SUM(P81:AA81) -> 0
B82: % de servicios concluidos con internos | D82: 0.015267176 | E82: 0.034246575 | F82: 0.012658228 | G82: 0.014388489 | H82: 0.10454879 | I82: 0.10993325 | J82: 0.13558632 | K82: 0.1139338 | L82: 0.11223254 | M82: 0.12361558 | N82: 0.12955314 | O82: 0.11641572 | P82: 0.13627334 | Q82: 0.13804857 | R82: 0.13518733 | S82: 0.13107391 | T82: 0.12294094 | U82: 0.15327511 | V82: 0.14423923 | W82: 0.16260163 | X82: 0.1391709 | Y82: 0.15292712 | AC82: =SUM(P82:AA82) -> 1.4157381
B83: % de servicios suceptibles con internos | AC83: =SUM(P83:AA83) -> 0
B84: Costo Promedio X Serv. C. Total USD $ | D84: 45.200283 | E84: 45.128443 | F84: 44.015433 | G84: 44.462084 | H84: 47.002916 | I84: 46.976523 | J84: 47.857229 | K84: 50.690188 | L84: 49.164745 | M84: 48.261475 | N84: 48.239305 | O84: 48.774943 | P84: 49.422175 | Q84: 50.137236 | R84: 48.700096 | S84: 49.27959 | T84: 49.407227 | U84: 53.826489 | V84: 49.580275 | W84: 46.512571 | X84: 47.225368 | Y84: 50.281956 | AC84: =SUM(P84:AA84) -> 494.37298

Sheet Indicadores MCS
B3: REPORTE EJECUTIVO OPERACIÓN VOCCARE 2025
B5: Filial | D5: MCS | P5: MCS
B7: TIPO DE CAMBIO USD $ | D7: 1 | P7: 1
B9: MES | D9: 45292 | E9: 45323 | F9: 45352 | G9: 45383 | H9: 45413 | I9: 45444 | J9: 45474 | K9: 45505 | L9: 45536 | M9: 45566 | N9: 45597 | O9: 45627 | AC9: Acumulados | AD9: Promedio
B11: MODULO CARTERA EN RIESGO
B12: Cartera en Riesgo | D12: 0 | E12: 0 | F12: 0 | G12: 0 | H12: 0 | I12: 0 | J12: 0 | K12: 0 | L12: 0 | M12: 0 | N12: 0 | O12: 0 | P12: 0 | Q12: 0 | R12: 0 | S12: 0 | T12: 0 | U12: 0 | V12: 0 | W12: 0 | X12: 0 | Y12: 0 | AC12: =SUM(P12:AA12) -> 0 | AD12: =IFERROR(AC12/(COUNT(P12:AA12)),0) -> 0
B13: Ingresos del Mes Técnico | D13: 20763 | E13: 19787 | F13: 21872 | G13: 21915 | H13: 24377 | I13: 21922 | J13: 25123 | K13: 20535 | L13: 24111 | M13: 27238 | N13: 22115 | O13: 25688 | P13: 25381 | Q13: 23398 | R13: 27855 | S13: 27042 | T13: 26281 | U13: 30910 | V13: 28627 | W13: 28999 | X13: 31628 | Y13: 32791 | AC13: =SUM(P13:AA13) -> 282912 | AD13: =IFERROR(AC13/(COUNT(P13:AA13)),0) -> 28291.2
B14: Ingreso / Afiliado | D14: 0 | E14: 0 | F14: 0 | G14: 0 | H14: 0 | I14: 0 | J14: 0 | K14: 0 | L14: 0 | M14: 0 | N14: 0 | O14: 0 | P14: 0 | Q14: 0 | R14: 0 | S14: 0 | T14: 0 | U14: 0 | V14: 0 | W14: 0 | X14: 0 | Y14: 0 | AC14: =SUM(P14:AA14) -> 0 | AD14: =IFERROR(AC14/(COUNT(P14:AA14)),0) -> 0
B15: COMPORTAMIENTO DE SERVICIOS
B16: Total de Asistencia Solicitadas | D16: 27247 | E16: 26619 | F16: 27999 | G16: 30073 | H16: 32688 | I16: 28925 | J16: 34016 | K16: 28031 | L16: 31089 | M16: 35746 | N16: 30081 | O16: 35119 | P16: 33745 | Q16: 31731 | R16: 36129 | S16: 36182 | T16: 35045 | U16: 37984 | V16: 34072 | W16: 33865 | X16: 37481 | Y16: 40416 | AC16: =SUM(P16:AA16) -> 356650 | AD16: =IFERROR(AC16/(COUNT(P16:AA16)),0) -> 35665
B17: Total Servicios Concluidos (C) | D17: 20794 | E17: 19788 | F17: 21877 | G17: 21938 | H17: 24407 | I17: 21941 | J17: 25153 | K17: 20586 | L17: 24147 | M17: 27267 | N17: 22166 | O17: 25723 | P17: 25394 | Q17: 23403 | R17: 27858 | S17: 27100 | T17: 26336 | U17: 30971 | V17: 28672 | W17: 29048 | X17: 31677 | Y17: 32850 | AC17: =SUM(P17:AA17) -> 283309 | AD17: =IFERROR(AC17/(COUNT(P17:AA17)),0) -> 28330.9
B18: % Servicios Concluidos | D18: 0.76316659 | E18: 0.74337879 | F18: 0.78134933 | G18: 0.72949157 | H18: 0.74666544 | I18: 0.75854797 | J18: 0.73944614 | K18: 0.7344012 | L18: 0.77670559 | M18: 0.76279863 | N18: 0.7368771 | O18: 0.73245252 | P18: 0.7525263 | Q18: 0.73754373 | R18: 0.77107033 | S18: 0.74899121 | T18: 0.75149094 | U18: 0.81536963 | V18: 0.84151209 | W18: 0.85775875 | X18: 0.84514821 | Y18: 0.81279691 | AC18: =SUM(P18:AA18) -> 7.9342081 | AD18: =IFERROR(AC18/(COUNT(P18:AA18)),0) -> 0.79342081
B19: Servicios (C) con Costo | D19: 20790 | E19: 19787 | F19: 21872 | G19: 21930 | H19: 24400 | I19: 21935 | J19: 25146 | K19: 20573 | L19: 24133 | M19: 27264 | N19: 22162 | O19: 25718 | P19: 25381 | Q19: 23398 | R19: 27855 | S19: 27100 | T19: 26333 | U19: 30964 | V19: 28666 | W19: 29039 | X19: 31663 | Y19: 32843 | AC19: =SUM(P19:AA19) -> 283242 | AD19: =IFERROR(AC19/(COUNT(P19:AA19)),0) -> 28324.2
B20: Servicios (C) Locales | D20: 14324 | E20: 12139 | F20: 15988 | G20: 16218 | H20: 17877 | I20: 4619 | J20: 5278 | K20: 18358 | L20: 23674 | M20: 25221 | N20: 14727 | O20: 17616 | P20: 6283 | Q20: 4515 | R20: 6003 | S20: 7154 | T20: 7929 | U20: 9305 | V20: 8357 | W20: 8846 | X20: 9202 | Y20: 9989 | AC20: =SUM(P20:AA20) -> 77583 | AD20: =IFERROR(AC20/(COUNT(P20:AA20)),0) -> 7758.3
B21: Servicios (C) Foraneos | D21: 6466 | E21: 7648 | F21: 5884 | G21: 5712 | H21: 6523 | I21: 17316 | J21: 19868 | K21: 2215 | L21: 459 | M21: 2043 | N21: 7435 | O21: 8102 | P21: 19098 | Q21: 18883 | R21: 21852 | S21: 19946 | T21: 18404 | U21: 21659 | V21: 20309 | W21: 20193 | X21: 22461 | Y21: 22854 | AC21: =SUM(P21:AA21) -> 205659 | AD21: =IFERROR(AC21/(COUNT(P21:AA21)),0) -> 20565.9
B22: Servicios (C) Adicionales | D22: 27239 | E22: 26615 | F22: 27988 | G22: 30054 | H22: 32677 | I22: 28919 | J22: 34005 | K22: 28016 | L22: 31074 | M22: 35743 | N22: 30076 | O22: 35110 | P22: 33726 | Q22: 31723 | R22: 36126 | S22: 36182 | T22: 35039 | U22: 37975 | V22: 34063 | W22: 33850 | X22: 37463 | Y22: 40407 | AC22: =SUM(P22:AA22) -> 356554 | AD22: =IFERROR(AC22/(COUNT(P22:AA22)),0) -> 35655.4
B23: Servicios (C) en Conexión | D23: 0 | E23: 0 | F23: 0 | G23: 0 | H23: 0 | I23: 0 | J23: 0 | K23: 2 | L23: 1 | M23: 0 | N23: 0 | O23: 0 | P23: 0 | Q23: 0 | R23: 0 | S23: 0 | T23: 0 | U23: 0 | V23: 0 | W23: 0 | X23: 0 | Y23: 0 | AC23: =SUM(P23:AA23) -> 0 | AD23: =IFERROR(AC23/(COUNT(P23:AA23)),0) -> 0
B24: Servicios (C) por el CAT - Referencias | D24: 3153 | E24: 3738 | F24: 4400 | G24: 0 | H24: 4019 | I24: 4900 | J24: 4437 | K24: 4195 | L24: 4911 | M24: 4137 | N24: 3993 | O24: 4360 | P24: 3466 | Q24: 3641 | R24: 5184 | S24: 4544 | T24: 4726 | U24: 5952 | V24: 4258 | W24: 5474 | X24: 7268 | Y24: 6527 | AC24: =SUM(P24:AA24) -> 51040 | AD24: =IFERROR(AC24/(COUNT(P24:AA24)),0) -> 5104
B25: Servicios (C) por Internos | D25: 1567 | E25: 1343 | F25: 1445 | G25: 1552 | H25: 2258 | I25: 2137 | J25: 2540 | K25: 2030 | L25: 2059 | M25: 2855 | N25: 2256 | O25: 2256 | P25: 2519 | Q25: 2572 | R25: 2625 | S25: 2788 | T25: 2111 | U25: 2485 | V25: 2317 | W25: 2260 | X25: 2431 | Y25: 2821 | AC25: =SUM(P25:AA25) -> 24929 | AD25: =IFERROR(AC25/(COUNT(P25:AA25)),0) -> 2492.9
B26: Servicios (C) por Externos | D26: 19223 | E26: 18444 | F26: 20427 | G26: 20378 | H26: 22142 | I26: 19798 | J26: 22606 | K26: 18543 | L26: 22074 | M26: 24409 | N26: 19906 | O26: 23462 | P26: 22862 | Q26: 20826 | R26: 25230 | S26: 24312 | T26: 24222 | U26: 28479 | V26: 26349 | W26: 26779 | X26: 29232 | Y26: 30022 | AC26: =SUM(P26:AA26) -> 258313 | AD26: =IFERROR(AC26/(COUNT(P26:AA26)),0) -> 25831.3
B27: Servicios Cancelado Posterior (CP) | D27: 5691 | E27: 6253 | F27: 5433 | G27: 7393 | H27: 7333 | I27: 6317 | J27: 7925 | K27: 6767 | L27: 6189 | M27: 7310 | N27: 6795 | O27: 8030 | P27: 7163 | Q27: 7310 | R27: 7080 | S27: 7490 | T27: 7063 | U27: 5914 | V27: 3838 | W27: 3729 | X27: 4292 | Y27: 5400 | AC27: =SUM(P27:AA27) -> 59279 | AD27: =IFERROR(AC27/(COUNT(P27:AA27)),0) -> 5927.9
... B30: % Servicios Cancelado al Momento | D30: 0.027966382 | E30: 0.021713813 | F30: 0.024608022 | G30: 0.024673295 | H30: 0.029001468 | I30: 0.023059637 | J30: 0.027575259 | K30: 0.024187507 | L30: 0.024220785 | M30: 0.03270296 | N30: 0.037232805 | O30: 0.038896324 | P30: 0.035205216 | Q30: 0.032082191 | R30: 0.032965208 | S30: 0.043999779 | T30: 0.046968184 | U30: 0.028933235 | V30: 0.045844095 | W30: 0.032127565 | X30: 0.040340439 | Y30: 0.053592637 | AC30: =SUM(P30:AA30) -> 0.39205855 | AD30: =IFERROR(AC30/(COUNT(P30:AA30)),0) -> 0.039205855
B31: COMPORTAMIENTO DE SINIESTRALIDAD
B32: Costo Siniestralidad Serv. (C) - Locales | D32: 875351 | E32: 695678 | F32: 935908 | G32: 959844 | H32: 1070080 | I32: 221871 | J32: 262425 | K32: 982945 | L32: 1101349 | M32: 274623 | N32: 211074 | O32: 518807 | P32: 127200 | Q32: 140780 | R32: 171991 | S32: 199660 | T32: 221788 | U32: 278464 | V32: 275458 | W32: 222690 | X32: 234938 | Y32: 250666 | AC32: =SUM(P32:AA32) -> 2123635 | AD32: =IFERROR(AC32/(COUNT(P32:AA32)),0) -> 212363.5
B33: Costo Siniestralidad Serv. (C) - Foraneos | D33: 266088 | E33: 316572 | F33: 180480 | G33: 202781 | H33: 234509 | I33: 865284 | J33: 1066962 | K33: 71015 | L33: 26057 | M33: 5981 | N33: 107951 | O33: 122026 | P33: 417288 | Q33: 491685 | R33: 589280 | S33: 504829 | T33: 466967 | U33: 560507 | V33: 557646 | W33: 444768 | X33: 507030 | Y33: 523745 | AC33: =SUM(P33:AA33) -> 5063745 | AD33: =IFERROR(AC33/(COUNT(P33:AA33)),0) -> 506374.5
B34: Costo Siniestralidad Internos | D34: 104556 | E34: 89842 | F34: 96324 | G34: 103965 | H34: 123933 | I34: 121301 | J34: 143473 | K34: 111850 | L34: 94987 | M34: 3469 | N34: 1229 | O34: 45922 | P34: 40 | Q34: 3582 | R34: 6434 | S34: 5495 | T34: 35 | U34: 0 | V34: 0 | W34: 0 | X34: 0 | Y34: 0 | AC34: =SUM(P34:AA34) -> 15586 | AD34: =IFERROR(AC34/(COUNT(P34:AA34)),0) -> 1558.6
B35: Costo Siniestralidad Externos | D35: 1036883 | E35: 922408 | F35: 1020064 | G35: 1058660 | H35: 1180656 | I35: 965854 | J35: 1185914 | K35: 942110 | L35: 1032419 | M35: 277135 | N35: 317796 | O35: 594911 | P35: 544448 | Q35: 628883 | R35: 754837 | S35: 698994 | T35: 688720 | U35: 838971 | V35: 833104 | W35: 667458 | X35: 741968 | Y35: 774411 | AC35: =SUM(P35:AA35) -> 7171794 | AD35: =IFERROR(AC35/(COUNT(P35:AA35)),0) -> 717179.4
B36: Costo Siniestralidad Serv. (CP) | D36: 83345 | E36: 72663 | F36: 83089 | G36: 91282 | H36: 99695 | I36: 91115 | J36: 111251 | K36: 80431 | L36: 82644 | M36: 66151 | N36: 4721 | O36: 128766 | P36: 7772 | Q36: 2086 | R36: 2814 | S36: 3342 | T36: 1988 | U36: 2438 | V36: 2751 | W36: 2734 | X36: 2483 | Y36: 3536 | AC36: =SUM(P36:AA36) -> 31944 | AD36: =IFERROR(AC36/(COUNT(P36:AA36)),0) -> 3194.4
B37: Costo Siniestralidad Total | D37: 1224784 | E37: 1084913 | F37: 1199477 | G37: 1253907 | H37: 1404284 | I37: 1178270 | J37: 1440638 | K37: 1134391 | L37: 1210050 | M37: 346755 | N37: 323746 | O37: 769599 | P37: 552260 | Q37: 634551 | R37: 764085 | S37: 707831 | T37: 690743 | U37: 841409 | V37: 835855 | W37: 670192 | X37: 744451 | Y37: 777947 | AC37: =SUM(P37:AA37) -> 7219324 | AD37: =IFERROR(AC37/(COUNT(P37:AA37)),0) -> 721932.4
B38: LLAMADAS TOTALES
B39: Total de llamadas Validas | D39: 20429 | E39: 19281 | F39: 19846 | G39: 22267 | H39: 21698 | I39: 19936 | J39: 23075 | K39: 20984 | L39: 21885 | M39: 25103 | N39: 22036 | O39: 22791 | P39: 25957 | Q39: 22756 | R39: 26373 | S39: 26294 | T39: 25887 | U39: 28914 | V39: 29891 | W39: 28894 | X39: 32221 | Y39: 35977 | AC39: =SUM(P39:AA39) -> 283164 | AD39: =IFERROR(AC39/(COUNT(P39:AA39)),0) -> 28316.4
B40: Frecuencia Natural Llamadas Inbound, % | D40: 0 | E40: 0 | F40: 0 | G40: 0 | H40: 0 | I40: 0 | J40: 0 | K40: 0 | L40: 0 | M40: 0 | N40: 0 | O40: 0 | P40: 0 | Q40: 0 | R40: 0 | S40: 0 | T40: 0 | U40: 0 | V40: 0 | W40: 0 | X40: 0 | Y40: 0 | AC40: =SUM(P40:AA40) -> 0 | AD40: =IFERROR(AC40/(COUNT(P40:AA40)),0) -> 0
B41: Llamadas al CAT, % | D41: 0.98673454 | E41: 0.98599658 | F41: 0.98584098 | G41: 0.9891319 | H41: 0.9899069 | I41: 0.99026886 | J41: 0.9912026 | K41: 0.99270873 | L41: 0.99186658 | M41: 0.99255069 | N41: 0.98947177 | O41: 0.98828485 | P41: 0.99318103 | Q41: 0.98778344 | R41: 0.99472946 | S41: 0.99353465 | T41: 0.99300807 | U41: 0.98931314 | V41: 0.99484795 | W41: 0.99186682 | X41: 0.99515844 | Y41: 0.99508019 | AC41: =SUM(P41:AA41) -> 9.9285032 | AD41: =IFERROR(AC41/(COUNT(P41:AA41)),0) -> 0.99285032
B42: LLAMADAS PROVEEDORES
B43: Total de llamadas validas Proveedores | D43: 271 | E43: 270 | F43: 281 | G43: 242 | H43: 219 | I43: 194 | J43: 203 | K43: 153 | L43: 178 | M43: 187 | N43: 232 | O43: 267 | P43: 177 | Q43: 278 | R43: 139 | S43: 170 | T43: 181 | U43: 309 | V43: 154 | W43: 235 | X43: 156 | Y43: 177 | AC43: =SUM(P43:AA43) -> 1976 | AD43: =IFERROR(AC43/(COUNT(P43:AA43)),0) -> 197.6
B44: Llamadas atendidas Proveedores | D44: 259 | E44: 262 | F44: 269 | G44: 222 | H44: 209 | Q44: 0.10625 | W44: 0.10833333 | AC44: =SUM(P44:AA44) -> 0.21458333 | AD44: =IFERROR(AC44/(COUNT(P44:AA44)),0) -> 0.10729167
B45: Tiempo promedio conversación Proveedores | D45: 3.2 | E45: 2.49 | F45: 3.1 | G45: 2.5 | H45: 3.04 | I45: 2.43 | J45: 2.44 | K45: 2.34 | L45: 2.35 | M45: 2.55 | N45: 2.4 | O45: 2.32 | P45: 2.57 | Q45: 2.33 | R45: 2.5 | S45: 2.59 | T45: 3.05 | U45: 1.44 | V45: 2.46 | W45: 2.36 | X45: 2.26 | Y45: 2.41 | AC45: =SUM(P45:AA45) -> 23.97 | AD45: =IFERROR(AC45/(COUNT(P45:AA45)),0) -> 2.397
B46: Llamadas atendidas < 15 seg. Proveedores | D46: 225 | E46: 203 | F46: 154 | G46: 150 | H46: 185 | I46: 189 | J46: 195 | K46: 137 | L46: 158 | M46: 164 | N46: 197 | O46: 217 | P46: 142 | Q46: 232 | R46: 125 | S46: 168 | T46: 160 | U46: 285 | V46: 133 | W46: 227 | X46: 147 | Y46: 171 | AC46: =SUM(P46:AA46) -> 1790 | AD46: =IFERROR(AC46/(COUNT(P46:AA46)),0) -> 179
B47: Abandonos mayores a 5 seg. Proveedores | D47: 3 | E47: 8 | F47: 11 | G47: 16 | H47: 7 | I47: 1 | J47: 1 | K47: 1 | L47: 5 | M47: 2 | N47: 4 | O47: 4 | P47: 3 | Q47: 5 | R47: 8 | S47: 2 | T47: 1 | U47: 4 | V47: 2 | W47: 2 | X47: 1 | Y47: 1 | AC47: =SUM(P47:AA47) -> 29 | AD47: =IFERROR(AC47/(COUNT(P47:AA47)),0) -> 2.9
B48: % Indice de abandono Proveedores | D48: 0.01 | E48: 0.03 | F48: 0.039145907 | G48: 0.066115702 | H48: 0.03196347 | I48: 0.0051546392 | J48: 0.0049261084 | K48: 0.01 | L48: 0.028089888 | M48: 0.01 | N48: 0.01 | O48: 0.02 | P48: 1,7% | Q48: 0.02 | R48: 0.057553957 | S48: 0.011764706 | T48: 0.0055248619 | U48: 0.012944984 | V48: 0.012987013 | W48: 0.01 | X48: 0.0064102564 | Y48: 0.0056497175 | AC48: =SUM(P48:AA48) -> 0.1428355 | AD48: =IFERROR(AC48/(COUNT(P48:AA48)),0) -> 0.015870611
B49: Nivel de servicio < 15 seg. Proveedores | D49: 0.83 | E49: 0.75 | F49: 0.5480427 | G49: 0.67567568 | H49: 0.88516746 | I49: 0.9742268 | J49: 0.96059113 | K49: 0.9 | L49: 0.88764045 | M49: 0.9 | N49: 0.87 | O49: 0.84 | P49: 0.83 | Q49: 0.85 | R49: 0.9 | S49: 0.99 | T49: 0.92 | U49: 0.93 | V49: 0.94 | W49: 0.97 | X49: 0.94230769 | Y49: 0.96610169 | AC49: =SUM(P49:AA49) -> 9.2384094 | AD49: =IFERROR(AC49/(COUNT(P49:AA49)),0) -> 0.92384094
B50: LLAMADAS CABINA DE EMERGENCIA CLIENTE
B51: Total de llamadas validas Clientes CAT | D51: 20158 | E51: 19011 | F51: 19565 | G51: 22025 | H51: 21479 | I51: 19742 | J51: 22872 | K51: 20831 | L51: 21707 | M51: 24916 | N51: 21804 | O51: 22524 | P51: 25780 | Q51: 22478 | R51: 26234 | S51: 26124 | T51: 25706 | U51: 28605 | V51: 29737 | W51: 28659 | X51: 32065 | Y51: 35800 | AC51: =SUM(P51:AA51) -> 281188 | AD51: =IFERROR(AC51/(COUNT(P51:AA51)),0) -> 28118.8
B52: Llamadas atendidas Clientes CAT | D52: 19707 | E52: 18620 | F52: 18860 | G52: 21174 | H52: 21127 | Q52: 0.27152778 | W52: 0.26875 | AC52: =SUM(P52:AA52) -> 0.54027778 | AD52: =IFERROR(AC52/(COUNT(P52:AA52)),0) -> 0.27013889
B53: Tiempo promedio conversación Clientes CAT | D53: 6.23 | E53: 6.22 | F53: 6.31 | G53: 6.36 | H53: 7.11 | I53: 6.55 | J53: 6.28 | K53: 6.43 | L53: 7.08 | M53: 7.23 | N53: 8.15 | O53: 7.05 | P53: 6.47 | Q53: 6.31 | R53: 6.2 | S53: 6.22 | T53: 6.17 | U53: 6 | V53: 6.1 | W53: 6.27 | X53: 6.2 | Y53: 6.15 | AC53: =SUM(P53:AA53) -> 62.09 | AD53: =IFERROR(AC53/(COUNT(P53:AA53)),0) -> 6.209
B54: Llamadas atendidas < 15 seg. Cliente CAT | D54: 14399 | E54: 13560 | F54: 12290 | G54: 12885 | H54: 18168 | I54: 18745 | J54: 21305 | K54: 19207 | L54: 20109 | M54: 21370 | N54: 19223 | O54: 19218 | P54: 21560 | Q54: 19212 | R54: 23482 | S54: 25261 | T54: 25073 | U54: 23950 | V54: 26954 | W54: 26828 | X54: 30156 | Y54: 34038 | AC54: =SUM(P54:AA54) -> 256514 | AD54: =IFERROR(AC54/(COUNT(P54:AA54)),0) -> 25651.4
B55: Abandonos mayores a 5 seg. Clientes CAT | D55: 341 | E55: 275 | F55: 590 | G55: 679 | H55: 263 | I55: 111 | J55: 124 | K55: 139 | L55: 108 | M55: 136 | N55: 81 | O55: 70 | P55: 162 | Q55: 67 | R55: 217 | S55: 39 | T55: 114 | U55: 173 | V55: 111 | W55: 107 | X55: 145 | Y55: 82 | AC55: =SUM(P55:AA55) -> 1217 | AD55: =IFERROR(AC55/(COUNT(P55:AA55)),0) -> 121.7
B56: % Indice de abandono Clientes CAT | D56: 2% | E56: 0.01 | F56: 0.030155891 | G56: 0.030828604 | H56: 0.012244518 | I56: 0.0056225306 | J56: 0.005421476 | K56: 0.01 | L56: 0.0049753536 | M56: 0 | N56: 0.01 | O56: 0.01 | P56: 0,63% | Q56: 0 | R56: 0.0082717085 | S56: 0.0014928801 | T56: 0.0044347623 | U56: 0.01 | V56: 0.0037327235 | W56: 0 | X56: 0.0045220646 | Y56: 0.0022905028 | AC56: =SUM(P56:AA56) -> 0.034744642 | AD56: =IFERROR(AC56/(COUNT(P56:AA56)),0) -> 0.0038605158
B57: Nivel de servicio < 15 seg. Clientes CAT | D57: 0.71 | E57: 0.71 | F57: 0.62816254 | G57: 0.60852933 | H57: 0.84584943 | I57: 0.94949853 | J57: 0.93148828 | K57: 0.92 | L57: 0.92638319 | M57: 0.93 | N57: 0.91 | O57: 0.88 | P57: 0.87 | Q57: 0.88 | R57: 0.9 | S57: 0.99 | T57: 0.93 | U57: 0.91 | V57: 0.94 | W57: 0.94 | X57: 0.94046468 | Y57: 0.95078212 | AC57: =SUM(P57:AA57) -> 9.2512468 | AD57: =IFERROR(AC57/(COUNT(P57:AA57)),0) -> 0.92512468
B58: PRODUCTIVIDAD COORDINADORES CAT
B59: Dotacion de coordinadores efectivos | D59: 42 | E59: 42 | F59: 42 | G59: 42 | H59: 42 | I59: 56 | J59: 56 | K59: 56 | L59: 56 | M59: 56 | N59: 56 | O59: 56 | P59: 56 | Q59: 56 | R59: 56 | S59: 56 | T59: 56 | U59: 56 | V59: 56 | W59: 56 | X59: 56 | Y59: 56 | AC59: =SUM(P59:AA59) -> 560 | AD59: =IFERROR(AC59/(COUNT(P59:AA59)),0) -> 56
B60: Servicios solicitados X coordinador | D60: 648.7381 | E60: 633.78571 | F60: 666.64286 | G60: 716.02381 | H60: 778.28571 | I60: 516.51786 | J60: 607.42857 | K60: 500.55357 | L60: 555.16071 | M60: 638.32143 | N60: 537.16071 | O60: 627.125 | P60: 602.58929 | Q60: 566.625 | R60: 645.16071 | S60: 646.10714 | T60: 625.80357 | U60: 678.28571 | V60: 608.42857 | W60: 604.73214 | X60: 669.30357 | Y60: 721.71429 | AC60: =SUM(P60:AA60) -> 6368.75 | AD60: =IFERROR(AC60/(COUNT(P60:AA60)),0) -> 636.875
B61: Servicios concluidos X coordinador | D61: 495.09524 | E61: 471.14286 | F61: 520.88095 | G61: 522.33333 | H61: 581.11905 | I61: 391.80357 | J61: 449.16071 | K61: 367.60714 | L61: 431.19643 | M61: 486.91071 | N61: 395.82143 | O61: 459.33929 | P61: 453.46429 | Q61: 417.91071 | R61: 497.46429 | S61: 483.92857 | T61: 470.28571 | U61: 553.05357 | V61: 512 | W61: 518.71429 | X61: 565.66071 | Y61: 586.60714 | AC61: =SUM(P61:AA61) -> 5059.0893 | AD61: =IFERROR(AC61/(COUNT(P61:AA61)),0) -> 505.90893
B62: Llamadas atendidas X coordinador | D62: 475.38095 | E62: 449.57143 | F62: 455.45238 | G62: 509.42857 | H62: 508 | I62: 0 | J62: 0 | K62: 0 | L62: 0 | M62: 0 | N62: 0 | O62: 0 | P62: 0 | Q62: 0.0067460317 | R62: 0 | S62: 0 | T62: 0 | U62: 0 | V62: 0 | W62: 0.006733631 | X62: 0 | Y62: 0 | AC62: =SUM(P62:AA62) -> 0.013479663 | AD62: =IFERROR(AC62/(COUNT(P62:AA62)),0) -> 0.0013479663
B63: ATENCION DE LLAMADAS SAC
B64: Total de llamadas validas SAC | AC64: =SUM(P64:AA64) -> 0 | AD64: =IFERROR(AC64/(COUNT(P64:AA64)),0) -> 0
B65: Llamadas atendidas SAC | AC65: =SUM(P65:AA65) -> 0 | AD65: =IFERROR(AC65/(COUNT(P65:AA65)),0) -> 0
B66: Tiempo promedio conversación SAC | AC66: =SUM(P66:AA66) -> 0 | AD66: =IFERROR(AC66/(COUNT(P66:AA66)),0) -> 0
B67: Llamadas atendidas < 15 seg. SAC | AC67: =SUM(P67:AA67) -> 0 | AD67: =IFERROR(AC67/(COUNT(P67:AA67)),0) -> 0
B68: Abandonos mayores a 5 seg. SAC | AC68: =SUM(P68:AA68) -> 0 | AD68: =IFERROR(AC68/(COUNT(P68:AA68)),0) -> 0
B69: % Indice de abandono SAC | AC69: =SUM(P69:AA69) -> 0 | AD69: =IFERROR(AC69/(COUNT(P69:AA69)),0) -> 0
B70: Nivel de servicio < 15 seg. SAC | AC70: =SUM(P70:AA70) -> 0 | AD70: =IFERROR(AC70/(COUNT(P70:AA70)),0) -> 0
B71: PRODUCTIVIDAD AGENTES SAC
B72: Dotacion de agentes SAC efectivos | AC72: 0 | AD72: 0
B73: Llamadas atendidas X agente | AC73: 0 | AD73: 0
B74: SEGUIMIENTO LLAMADAS OUTBOUND
B75: Llamadas Outbound Afiliado | D75: 60269 | E75: 61609 | F75: 57659 | G75: 54477 | AC75: 0 | AD75: 0
B76: Lllamadas Outbound Proveedor | D76: 3172 | E76: 3273 | F76: 2753 | G76: 3954 | AC76: 0 | AD76: 0
B77: Llamadas Outbound Totales | D77: 63441 | E77: 64882 | F77: 60412 | G77: 58431 | H77: 25271 | I77: 19892 | J77: 21097 | K77: 22132 | L77: 21344 | M77: 22011 | N77: 26860 | O77: 20514 | P77: 21106 | Q77: 20562 | R77: 19807 | S77: 9483 | T77: 23996 | U77: 20170 | V77: 14859 | W77: 14673 | X77: 18743 | Y77: 19307 | AC77: 0 | AD77: 0
B78: RESULTADOS DE VARIABLES DEL MES
B79: % Frecuencia | D79: 0 | E79: 0 | F79: 0 | G79: 0 | H79: 0 | I79: 0 | J79: 0 | K79: 0 | L79: 0 | M79: 0 | N79: 0 | O79: 0 | P79: 0 | Q79: 0 | R79: 0 | S79: 0 | T79: 0 | U79: 0 | V79: 0 | W79: 0 | X79: 0 | Y79: 0 | AC79: =SUM(P79:AA79) -> 0
B80: % Frecuencia con Costo | D80: 0 | E80: 0 | F80: 0 | G80: 0 | H80: 0 | I80: 0 | J80: 0 | K80: 0 | L80: 0 | M80: 0 | N80: 0 | O80: 0 | P80: 0 | Q80: 0 | R80: 0 | S80: 0 | T80: 0 | U80: 0 | V80: 0 | W80: 0 | X80: 0 | Y80: 0 | AC80: =SUM(P80:AA80) -> 0
B81: % Siniestralidad Total | D81: 58.988778 | E81: 54.829585 | F81: 54.840755 | G81: 57.216838 | H81: 57.606925 | I81: 53.748289 | J81: 57.343391 | K81: 55.241831 | L81: 50.186637 | M81: 12.73056 | N81: 14.639204 | O81: 29.959475 | P81: 21.758796 | Q81: 27.119882 | R81: 27.430802 | S81: 26.175246 | T81: 26.28298 | U81: 27.221255 | V81: 29.198135 | W81: 23.110866 | X81: 23.53772 | Y81: 23.724406 | AC81: =SUM(P81:AA81) -> 255.56009
B82: % de servicios concluidos con internos | D82: 0.075372775 | E82: 0.067872846 | F82: 0.066066203 | G82: 0.070770634 | H82: 0.092540984 | I82: 0.097424208 | J82: 0.1010101 | K82: 0.098673018 | L82: 0.085318858 | M82: 0.10471684 | N82: 0.10179587 | O82: 0.087720663 | P82: 0.099247469 | Q82: 0.10992393 | R82: 0.094238018 | S82: 0.10287823 | T82: 0.080165572 | U82: 0.080254489 | V82: 0.080827461 | W82: 0.077826371 | X82: 0.076777311 | Y82: 0.085893493 | AC82: =SUM(P82:AA82) -> 0.88803234
B83: % de servicios suceptibles con internos | AC83: =SUM(P83:AA83) -> 0
B84: Costo Promedio X Serv. C. Total USD $ | D84: 54.903271 | E84: 51.157326 | F84: 51.04188 | G84: 53.015276 | H84: 53.466762 | I84: 49.562571 | J84: 52.866738 | K84: 51.230253 | L84: 46.716363 | M84: 10.292107 | N84: 14.395136 | O84: 24.917684 | P84: 21.452583 | Q84: 27.030729 | R84: 27.329779 | S84: 25.995904 | T84: 26.155584 | U84: 27.095046 | V84: 29.062443 | W84: 22.984882 | X84: 23.433282 | Y84: 23.57918 | AC84: =SUM(P84:AA84) -> 254.11941

Sheet Historico2
C2: Enero | D2: Febrero | E2: Marzo | F2: Abril | G2: Mayo | H2: Junio | I2: Julio | J2: Agosto | K2: Septiembre | L2: Octubre | M2: Noviembre | N2: Diciembre
B3: Cabina INC | C3: 43350.862 | D3: 45378.702 | E3: 45378.702 | F3: 45670.493 | G3: 46363.179 | H3: 46363.179 | I3: 46363.179 | J3: 47795.809 | K3: 46370.245
B4: Cabina Smart | C4: 165183.73 | D4: 177735.07 | E4: 177735.07 | F4: 184414.26 | G4: 182503.42 | H4: 201207.15 | I4: 201207.15 | J4: 201207.15 | K4: 200549.2

Sheet Historico
B2: Colombia | C2: Febrero | D2: Marzo | E2: Abril | F2: Mayo | G2: Junio | H2: Julio | I2: Agosto | J2: Septiembre | K2: Octubre | L2: Noviembre | M2: Diciembre | N2: Enero
B3: Servicios de Cabina | C3: 95798.72 | D3: 93042.974 | E3: 98991.301 | F3: 132073.24 | G3: 162154.31 | H3: 162154.31 | I3: 162154.31
B4: Fee Corporativo INC | C4: 3150 | D4: 3150 | E4: 3150 | F4: 3150 | G4: 3150 | H4: 3150 | I4: 3150
B5: Fee Corporativo Smart | C5: 3150 | D5: 3150 | E5: 3150 | F5: 3150 | G5: 3150 | H5: 3150 | I5: 3150
B6: Apoyo Contable | C6: 21000 | D6: 23000 | E6: 23000 | F6: 23000 | G6: 23000 | H6: 23000 | I6: 23610
B7: Odoo / Sap | C7: 10500 | D7: 10500 | E7: 10500 | F7: 10500 | G7: 10500 | H7: 11500 | I7: 11000
B8: Gmail | C8: 562.5 | D8: 575 | E8: 575 | F8: 575 | G8: 587.5 | H8: 587.5 | I8: 587.5
B9: Calidad | C9: 500 | D9: 500 | E9: 500 | F9: 500 | G9: 500 | H9: 500 | I9: 500
B10: MPLS | C10: 3539 | D10: 3539 | E10: 3539 | F10: 3539 | G10: 3539 | H10: 3539 | I10: 3539
B11: Strategic management | C11: 105 | D11: 105 | E11: 105 | F11: 105 | G11: 105 | H11: =105*2 -> 210 | I11: 105
B12: Factorial | C12: 87.5 | D12: 87.5 | E12: 87.5 | F12: 87.5 | G12: 87.5 | H12: =87.5*2 -> 175 | I12: 87.5
B13: Estrategia Tributaria | C13: 350 | D13: 350 | E13: 350 | F13: 350 | G13: 350 | H13: =350*2 -> 700 | I13: 350
B14: Compras Colombia | C14: 1324.2922 | D14: 1023.3682 | E14: 0 | F14: 0 | I14: 75.555447
B15: Legales | C15: -18965 | D15: -19243 | E15: -19243 | F15: -19243 | G15: -19243 | H15: -19243 | I15: -19243
B16: Comision PR (transcita) | C16: -3679.38 | D16: -3679.38 | E16: -3679.38 | F16: -3679.38 | G16: -3679.38 | H16: -3679.38 | I16: -3679.38
B17: Legales Bono GT & LC | C17: -2995.63 | D17: -2995.63 | E17: -2995.63 | F17: -2995.63 | G17: -2995.63 | H17: -2995.63 | I17: -2995.63
B18: Datateck | G18: -2252 | H18: -2252 | I18: -2252
B19: Claro SIP Enero | G19: -187.5 | H19: -187.5 | I19: -187.5
B20: Worldnet lineas tel adicionales | G20: -861.79 | H20: -861.79 | I20: -861.79
B21: Almacenamiento de Llamadas | G21: 0 | H21: 0
B22: Salario Ana Borland | G22: -6400.3414 | H22: -8803.44 | I22: -8588.26
B23: Neptuno | G23: -4248.2653 | H23: -4248.2653 | I23: -4248.2653
B24: Ajuste Llamadas Outbound | F24: 18902.43 | H24: 22079
B25: Conectividad | H25: 5383 | I25: 1176.32
B26: Total Ingreso | C26: =SUM(C3:C25) -> 114427 | D26: =SUM(D3:D25) -> 113104.83 | E26: =SUM(E3:E25) -> 118029.79 | F26: =SUM(F3:F25) -> 170014.16 | G26: =SUM(G3:G25) -> 167255.4 | H26: =SUM(H3:H25) -> 193856.8 | I26: =SUM(I3:I25) -> 167429.36 | J26: =SUM(J3:J25) -> 0 | ... N26: =SUM(N3:N25) -> 0
B27: Personal MCS | D27: 11120 | E27: 11120 | F27: 11120 | G27: 17051 | H27: 17051
B29: México | C29: Febrero | D29: Marzo | E29: Abril | F29: Mayo | G29: Junio | H29: Julio | I29: Agosto | J29: Septiembre | K29: Octubre | L29: Noviembre | M29: Diciembre | N29: Enero
B30: Servicios de Cabina | C30: 16398.382 | D30: 15918.646 | E30: 16482.573 | F30: 0 | G30: 0 | H30: 0
B31: Total Ingreso | C31: =SUM(C30) -> 16398.382 | D31: =SUM(D30) -> 15918.646 | E31: =SUM(E30) -> 16482.573 | F31: =SUM(F30) -> 0 | G31: =SUM(G30) -> 0 | H31: =SUM(H30) -> 0 | I31: =SUM(I30) -> 0 | J31: =SUM(J30) -> 0 | ... N31: =SUM(N30) -> 0
B33: Guatemala | C33: Febrero | D33: Marzo | E33: Abril | F33: Mayo | G33: Junio | H33: Julio | I33: Agosto | J33: Septiembre | K33: Octubre | L33: Noviembre | M33: Diciembre | N33: Enero
B34: Servicios de Cabina | C34: 57737.471 | D34: 57307.126 | E34: 59337.261 | F34: 49931.464 | G34: 39452.059 | H34: 50344.91 | I34: 50007.167
B35: Datateck | C35: -2252 | D35: -2252 | E35: -2252 | F35: -2252
B36: Claro SIP Enero | C36: -187.5 | D36: -187.5 | E36: -187.5 | F36: -187.5
B37: Worldnet lineas tel adicionales | C37: -861.79 | D37: -861.79 | E37: -861.79 | F37: -861.79
B38: Almacenamiento de Llamadas | E38: -1447.76 | F38: 0
B39: Neptuno | E39: -4248.2653 | F39: -4248.2653
B40: Total Ingreso | C40: =SUM(C34:C39) -> 54436.181 | D40: =SUM(D34:D39) -> 54005.836 | E40: =SUM(E34:E39) -> 50339.946 | F40: =SUM(F34:F39) -> 42381.909 | G40: =SUM(G34:G39) -> 39452.059 | H40: =SUM(H34:H39) -> 50344.91 | I40: =SUM(I34:I39) -> 50007.167 | J40: =SUM(J34:J39) -> 0 | ... N40: =SUM(N34:N39) -> 0
